Workbook

Sheet 00 Contents
B2: 00 — ALPHABET (GOOGL) RESEARCH DATA PACK
B3: Compiled September 10, 2026; share prices and peer multiples refreshed October 16, 2026. All figures $ millions unless noted. Personal hobby project by Mohammad Ahmadi, for informational and educational purposes only; not investment advice. Model outputs are assumption-dependent. Use at your own risk. Methodology, sources, assumptions and revisions are documented within the file.
B5: Sheet | C5: What it holds and why it sits here
B6: PART 1 - THE EVIDENCE: what Alphabet actually filed
B7: 01 Income Statement | C7: FY2023-FY2025 plus TTM Mar'26 and TTM Jun'26, with a derived-vs-filed flag. The top line of the whole argument.
B8: 02 Quarterly | C8: Q1 and Q2 2026 versus prior year. Isolates the ex-gain other-income line where the distortion first shows.
B9: 03 Segments | C9: ="Revenue, operating income, growth and margin by segment. Establishes that ~"&TEXT('02 Quarterly'!$D$29,"0")&"% operating margin is the real earning power." -> Revenue, operating income, growth and margin by segment. Establishes that ~34% operating margin is the real earning power.
B10: 04 Balance Sheet | C10: FY2023-Jun'26, PP&E corrected to filed figures. Holds the equity-securities portfolio that creates the gain.
B11: 05 Capital Structure | C11: The June 2026 raise as filed, share counts, preferred dividend. The denominator of every per-share figure.
B12: PART 2 - THE DISTORTION: why reported earnings overstate the business
B13: 06 Core EPS Bridge | C13: THE PIVOT OF THE PACK. Strips the equity-securities gain, tax-effects it, restates EPS. Reported becomes core here.
B14: 07 Consensus | C14: ="Consensus is GAAP-basis: FY2026 EPS of "&TEXT('07 Consensus'!$C$6,"0.00")&" implies a "&TEXT('07 Consensus'!$C$9/100,"0.0%")&" net margin against a "&TEXT('07 Consensus'!$C$11/100,"0.0%")&" Q2 operating margin because it books the H1'26 marks. The reported "&TEXT('11 Valuation'!$C$11,"0.0")&"x flatters the stock on a screen; it is not a consensus error." -> Consensus is GAAP-basis: FY2026 EPS of 20.60 implies a 50.8% net margin against a 34.0% Q2 operating margin because it books the H1'26 marks. The reported 17.1x flatters the stock on a screen; it is not a consensus error.
B15: PART 3 - WHAT DRIVES CASH: the capex question
B16: 08 PPE and Depreciation | C16: ="Asset classes, useful lives, and the "&TEXT('08 PPE and Depreciation'!$C$24,"#,##0")&" sitting in assets NOT YET IN SERVICE - the future depreciation charge." -> Asset classes, useful lives, and the 122,814 sitting in assets NOT YET IN SERVICE - the future depreciation charge.
B17: 09 Cash Flow | C17: Annual and quarterly, including the first negative FCF quarter. Where the capex actually lands.
B18: 10 Guidance and Quotes | C18: Capex guidance trail and verbatim management quotes. What management says about when capex plateaus.
B19: PART 4 - THE VERDICT: what it is worth
B20: 11 Valuation | C20: ="Reported versus core multiples at "&TEXT('11 Valuation'!$C$6,"$0.00")&". "&TEXT('11 Valuation'!$C$11,"0.0")&"x reported, "&TEXT('11 Valuation'!$C$12,"0.0")&"x core - the gap Parts 2 and 3 explain." -> Reported versus core multiples at $340.59. 17.1x reported, 33.0x core - the gap Parts 2 and 3 explain.
B21: 12 Peers | C21: Mega-cap comp table. Shows negative FCF is a cohort feature, not a GOOGL defect.
B22: 13 EPIC Ranking | C22: EPIC factor ranking: Exceeds materiality, Probably occurs, I can forecast, Consensus gap; totals are live and feed the research agenda.
B23: PART 5 - THE FORWARD MODEL: what FCF normalises to
B24: 14 Model Cover | C24: Explains the forward-model architecture, source links, scenario design and scope.
B25: 15 Assumptions | C25: Central model inputs for growth, margin, capex, depreciation, tax, financing and balance-sheet drivers.
B26: 16 Scenarios | C26: One visible switch drives Base, Best and Worst operating assumptions.
B27: 17 Model | C27: Integrated revenue, earnings, depreciation and cash-flow forecast through FY2030E.
B28: 18 Balance Sheet | C28: Live balance-sheet, cash, debt and equity roll-forwards following the active scenario, with eight checks.
B29: 19 Model Summary | C29: Scenario-linked operating summary and narrative interpretation.
B30: 20 DCF Valuation | C30: Three-scenario unlevered FCFF valuation at WACC, equity bridge, sensitivity and nineteen live checks.
B31: 21 Reverse DCF | C31: What the price assumes: single-lever break-evens, layered levers and validation against the earlier model state. Static tables must be refreshed after any model change.
B32: PART 6 - VISUAL ANALYSIS: data first, charts second
B33: 22 Earnings Quality | C33: Reported versus core EPS and P/E, with the live source table printed above the charts.
B34: 23 Growth and Mix | C34: Revenue, operating income and segment mix from FY2023 through FY2030E.
B35: 24 Cash and Margins | C35: Operating cash flow, capex, FCF, depreciation and margin paths.
B36: 25 Peers and Priorities | C36: Peer capital-efficiency map and EPIC research-priority ranking.
B37: PART 7 - PROVE IT: verification and provenance
B38: 26 Pack Audit | C38: =(COUNTIF('26 Pack Audit'!$F:$F,"TIES")+COUNTIF('26 Pack Audit'!$F:$F,"DOES NOT TIE"))&" live cross-sheet checks re-deriving key research-pack figures from source cells." -> 26 live cross-sheet checks re-deriving key research-pack figures from source cells.
B39: 27 Model Audit | C39: =(COUNTIF('27 Model Audit'!$F:$F,"TIES")+COUNTIF('27 Model Audit'!$F:$F,"DOES NOT TIE"))&" live checks re-deriving the model from the original pack sources." -> 71 live checks re-deriving the model from the original pack sources.
B40: 28 Sources | C40: Every cited URL, with verification status and quality classification.
B41: 29 Change Log | C41: Chronological record of workbook changes, audit findings and repairs.
B42: THE ONE STORY THIS PACK TELLS
B43: ="Alphabet's reported earnings overstate its earning power, so the reported multiple makes the stock look cheaper than it is. At $"&TEXT('11 Valuation'!$C$6,"0.00")&" the stock trades at "&TEXT('06 Core EPS Bridge'!$C$19,"0.0")&"x trailing REPORTED earnings and "&TEXT('06 Core EPS Bridge'!$D$19,"0.0")&"x trailing CORE earnings, because TTM net income of "&TEXT('01 Income Statement'!$G$18,"#,##0")&" contains "&TEXT('17 Model'!$K$28,"#,##0")&" of pretax mark-to-market gains on the equity-securities portfolio. Consensus does not appear to be misled by it: FY2026 consensus EPS of "&TEXT('07 Consensus'!$C$6,"0.00")&" is about "&TEXT('07 Consensus'!$C$63,"0.00")&" of core earnings plus the H1'26 marks already booked, FY2027 consensus of "&TEXT('07 Consensus'!$C$34,"0.00")&" is "&TEXT(1-'07 Consensus'!$C$34/'07 Consensus'!$C$6,"0%")&" lower, consistent with marks that do not recur, and the stock fell "&TEXT(-'12 Peers'!$E$15/100,"0.0%")&" over the eleven weeks to Sep 10 while Q2 reported EPS rose "&TEXT('02 Quarterly'!$E$37,"0")&"%. The "&TEXT('11 Valuation'!$C$11,"0.0")&"x flatters the stock for anyone who strikes a multiple off GAAP EPS. Parts 1 and 2 establish the gap from filed figures. Part 3 shows the cash question underneath it: capex has pushed free cash flow negative for th"&"e first time, and "&TEXT('08 PPE and Depreciation'!$C$24,"#,##0")&" of assets are not yet in service, so the depreciation charge is still ahead of the business. Part 4 prices it. Part 5 forecasts what free cash flow normalises to once capex plateaus. Part 6 visualise"&"s the evidence, and Part 7 proves the model ties back to its sources." -> Alphabet's reported earnings overstate its earning power, so the reported multiple makes the stock look cheaper than it is. At $340.59 the stock trades at 17.1x trailing REPORTED earnings and 33.0x trailing CORE earnings, because TTM net income of 244,205 contains 148,982 of pretax mark-to-market gains on the equity-securities portfolio. Consensus does not appear to be misled by it: FY2026 consensus EPS of 20.60 is about 11.85 of core earnings plus the H1'26 marks already booked, FY2027 consensus of 15.24 is 26% lower, consistent with marks that do not recur, and the stock fell 1.6% over the eleven weeks to Sep 10 while Q2 reported EPS rose 294%. The 17.1x flatters the stock for anyone who strikes a multiple off GAAP EPS. Parts 1 and 2 establish the gap from filed figures. Part 3 shows the cash question underneath it: capex has pushed free cash flow negative for the first time, and 122,814 of assets are not yet in service, so the depreciation charge is still ahead of the business. Part 4 prices it. Part 5 forecasts what free cash flow normalises to once capex plateaus. Part 6 visualises the evidence, and Part 7 proves the model ties back to its sources.
B45: AI ASSISTANCE DISCLOSURE — Generative AI assisted with research and source gathering, filing checks, workbook construction and formulas, Python scripts (scenario engine, Monte Carlo), charts and slides, consistency checks, change tracking and drafting. I set the key assumptions and judgments and reviewed the work; that review is not a guarantee of accuracy. AI-generated content, citations, code and calculations may contain errors or omissions and should be independently verified. AI assistance is not independent assurance or an audit.
B46: How to use this pack
B47: • READ THIS FIRST. Cells and rows flagged DERIVED are my own arithmetic, not filed or provider figures. They have not been audited and must be re-checked before anything is published.
B48: ="• PP&E IS CARRIED AS FILED. Standardized data feeds fold lease right-of-use assets into PP&E, which overstates it by a gap that grows year over year. Filed net PP&E is "&TEXT('04 Balance Sheet'!$D$12,"#,##0")&" at Dec 2024 and "&TEXT('04 Balance Sheet'!$E$12,"#,##0")&" at Dec 2025. Sheet '04 Balance Sheet' carries an AS FILED row, complete for every period - use it." -> • PP&E IS CARRIED AS FILED. Standardized data feeds fold lease right-of-use assets into PP&E, which overstates it by a gap that grows year over year. Filed net PP&E is 171,036 at Dec 2024 and 246,597 at Dec 2025. Sheet '04 Balance Sheet' carries an AS FILED row, complete for every period - use it.
B49: ="• THE FORMER ~85 TTM NET-INCOME DISCREPANCY IS RESOLVED. The difference is the H1'26 preferred-dividend allocation: consolidated TTM net income is "&TEXT('01 Income Statement'!$G$18,"#,##0")&", while income available to common is 244,119, effectively the provider's rounded 244,120. See '01 Income Statement'." -> • THE FORMER ~85 TTM NET-INCOME DISCREPANCY IS RESOLVED. The difference is the H1'26 preferred-dividend allocation: consolidated TTM net income is 244,205, while income available to common is 244,119, effectively the provider's rounded 244,120. See '01 Income Statement'.
B50: • FY2028 CONSENSUS IS SOURCED and the valuation layer is complete. '07 Consensus' carries FY2028 EPS, revenue, EBIT, operating margin and FCF; '18 Balance Sheet' carries the forecast balance sheet; '20 DCF Valuation' carries the three-scenario FCFF/WACC valuation.
B51: ="• ACTIVE SOURCES: "&(COUNTA('28 Sources'!$I$6:$I$216)-COUNTIF('28 Sources'!$E$6:$E$216,"Archive - not used in workbook exhibits"))&" URLs support the workbook; "&COUNTIF('28 Sources'!$E$6:$E$216,"Archive - not used in workbook exhibits")&" research-only links are retained as an archive. Dead links are zero." -> • ACTIVE SOURCES: 179 URLs support the workbook; 32 research-only links are retained as an archive. Dead links are zero.
B52: • SOURCE QUALITY: '28 Sources' applies a documented source-quality policy. Tier 5 items are retained only where no free primary transcript exists; archived links do not support workbook exhibits.
B53: ="• FOUR CONTROL LAYERS ARE LIVE. '26 Pack Audit' carries "&(COUNTIF('26 Pack Audit'!$F:$F,"TIES")+COUNTIF('26 Pack Audit'!$F:$F,"DOES NOT TIE"))&" checks, '27 Model Audit' carries "&(COUNTIF('27 Model Audit'!$F:$F,"TIES")+COUNTIF('27 Model Audit'!$F:$F,"DOES NOT TIE"))&", '18 Balance Sheet' carries "&(COUNTIF('18 Balance Sheet'!$I:$I,"TIES")+COUNTIF('18 Balance Sheet'!$I:$I,"DOES NOT TIE"))&", and '20 DCF Valuation' carries "&(COUNTIF('20 DCF Valuation'!$F:$F,"TIES")+COUNTIF('20 DCF Valuation'!$F:$F,"DOES NOT TIE"))&". "&IF((COUNTIF('26 Pack Audit'!$F:$F,"DOES NOT TIE")+COUNTIF('27 Model Audit'!$F:$F,"DOES NOT TIE")+COUNTIF('18 Balance Sheet'!$I:$I,"DOES NOT TIE")+COUNTIF('20 DCF Valuation'!$F:$F,"DOES NOT TIE"))=0,"All "&((COUNTIF('26 Pack Audit'!$F:$F,"TIES")+COUNTIF('26 Pack Audit'!$F:$F,"DOES NOT TIE"))+(COUNTIF('27 Model Audit'!$F:$F,"TIES")+COUNTIF('27 Model Audit'!$F:$F,"DOES NOT TIE"))+(COUNTIF('18 Balance Sheet'!$I:$I,"TIES")+COUNTIF('18 Balance Sheet'!$I:$I,"DOES NOT TIE"))+(COUNTIF('20 DCF Valuation'!$F:$F,"TIES")+COUNTIF('20 DCF Valuation'!$F:$F,"DOES NOT TIE")))&" tie in the active scenario ("&'16 Scenarios'!$F$6&"); flip '16 Scenarios'!D6 to confirm the other two cases.",(COUNTIF('26 Pack Audit'!$F:$F,"DOES NOT TIE")+COUNTIF('27 Model Audit'!$F:$F,"DOES NOT TIE")+COUNTIF('18 Balance Sheet'!$I:$I,"DOES NOT TIE")+COUNTIF('20 DCF Valuation'!$F:$F,"DOES NOT TIE"))&" of "&((COUNTIF('26 Pack Audit'!$F:$F,"TIES")+COUNTIF('26 Pack Audit'!$F:$F,"DOES NOT TIE"))+(COUNTIF('27 Model Audit'!$F:$F,"TIES")+COUNTIF('27 Model Audit'!$F:$F,"DOES NOT TIE"))+(COUNTIF('18 Balance Sheet'!$I:$I,"TIES")+COUNTIF('18 Balance Sheet'!$I:$I,"DOES NOT TIE"))+(COUNTIF('20 DCF Valuation'!$F:$F,"TIES")+COUNTIF('20 DCF Valuation'!$F:$F,"DOES NOT TIE")))&" DO NOT TIE in the active scenario.") -> • FOUR CONTROL LAYERS ARE LIVE. '26 Pack Audit' carries 26 checks, '27 Model Audit' carries 71, '18 Balance Sheet' carries 8, and '20 DCF Valuation' carries 19. All 124 tie in the active scenario (BASE CASE); flip '16 Scenarios'!D6 to confirm the other two cases.
B55: Cell colour convention (financial-modelling standard)
B56: BLUE | C56: Hard-coded input - a filed, provider or sourced number typed in directly. Change these to drive the model.
B57: BLACK | C57: Formula calculated on this same sheet. Do not overwrite - it will recalculate.
B58: GREEN | C58: Formula that links to another sheet. Trace with Formulas > Trace Precedents, or F2 to see the source.
C59: Text labels, headers and notes are left in their original formatting.
B61: Layout, print and visual conventions
B62: Column A | C62: Narrow empty gutter on every sheet - a left margin so content never touches the edge on screen or in print.
B63: Row 1 | C63: Thin spacer row giving the same breathing room at the top.
B64: Print setup | C64: Landscape, fit to 1 page wide, 0.3" margins, centred horizontally. Rows 2:5 repeat as titles on every printed page.
B65: Header / footer | C65: Landscape, fit to one page wide, consistent margins and restrained headers/footers; analytical sheets repeat their title/header band where useful.
B66: Visual grammar | C66: All 30 visible sheets use Arial, gridlines off, an 18pt blue title over a navy rule, navy table headers, pale-blue section bands and restrained notes.
B67: Tab colours | C67: Encode the PART, not the layer: teal = evidence, amber = the distortion, orange = cash drivers, green = the verdict, blue = the forward model, purple = verification and provenance.
B68: Tab colour key | C68: PARTS 1 to 7 in narrative order, matching the tab colours along the bottom of the window: | D68: 1 | E68: 2 | F68: 3 | G68: 4 | H68: 5 | I68: 6 | J68: 7
B69: HOW THE TWO LAYERS RELATE - READ BEFORE EDITING SHEETS 01-13. The model sheets do not copy the pack, they LINK to it live. Sheets 01, 03, 05, 06, 08, 09 and 11 are precedents for the forecast: most of the checks on '27 Model Audit' reach back into them. Inserting or deleting rows on those sheets will silently repoint formulas and break the forecast, because the links are cell-address based. Add new content BELOW existing blocks rather than inserting rows inside them. The pack remains the single source of truth for all history; the model sheets add no new facts, only forward assumptions.
B70: NUMBERING. Final numbering was applied on September 22, 2026; Reverse DCF was added on 2026-10-07 and moved into Part 5 on 2026-10-14; the physical tab order was restored on 2026-10-18. All 30 visible sheets run sequentially from 00 Contents through 29 Change Log. The forecast extension is 17 Model, 18 Balance Sheet, 19 Model Summary, 20 DCF Valuation and 21 Reverse DCF; visual analysis is 22-25; controls and provenance are 26-29. Six hidden DCF scenario-engine sheets retain descriptive helper names and are excluded from the reader-facing sequence.

Sheet 01 Income Statement
B2: 01 — CONSOLIDATED INCOME STATEMENT
B3: $ millions except per-share. TTM Jun'26 is DERIVED as FY2025 + H1'26 - H1'25.
B5: Line item | C5: FY2023 | D5: FY2024 | E5: FY2025 | F5: TTM Mar'26 | G5: TTM Jun'26 | H5: Basis
B6: Total revenues | C6: 307394 | D6: 350018 | E6: 402836 | F6: 422498 | G6: =E6+'02 Quarterly'!D7+'02 Quarterly'!D23-'02 Quarterly'!C7-'02 Quarterly'!C23 -> 445866 | H6: filed / derived TTM
B7: Cost of revenues | C7: 133332 | D7: 146306 | E7: 162535 | F7: 167445 | G7: =E7+'02 Quarterly'!D8+'02 Quarterly'!D24-'02 Quarterly'!C8-'02 Quarterly'!C24 -> 174349 | H7: filed / derived TTM
B8: Research and development | C8: 45427 | D8: 49326 | E8: 61087 | F8: 64563 | G8: 68974 | H8: filed / derived TTM
B9: Sales and marketing | C9: 27917 | D9: 27808 | E9: 28693 | G9: 31429 | H9: filed / derived TTM
B10: General and administrative | C10: 16425 | D10: 14188 | E10: 21482 | G10: 23486 | H10: filed / derived TTM
B11: Total costs and expenses | C11: =C7+C8+C9+C10 -> 223101 | D11: =D7+D8+D9+D10 -> 237628 | E11: =E7+E8+E9+E10 -> 273797 | F11: 284369 | G11: =G7+G8+G9+G10 -> 298238 | H11: filed / derived TTM
B12: Income from operations | C12: =C6-C11 -> 84293 | D12: =D6-D11 -> 112390 | E12: =E6-E11 -> 129039 | F12: =F6-F11 -> 138129 | G12: =G6-G11 -> 147628 | H12: filed / derived TTM
B13: Operating margin % | C13: =C12/C6*100 -> 27.42181 | D13: =D12/D6*100 -> 32.109777 | E13: =E12/E6*100 -> 32.032639 | F13: =F12/F6*100 -> 32.693409 | G13: =G12/G6*100 -> 33.110396 | H13: calc
B14: Other income (expense), net | C14: 1424 | D14: 7425 | E14: 29787 | F14: 56320 | G14: =E14+'02 Quarterly'!D12+'02 Quarterly'!D30-'02 Quarterly'!C12-'02 Quarterly'!C30 -> 151641 | H14: filed / derived TTM
B15: Income before taxes | C15: =C12+C14 -> 85717 | D15: =D12+D14 -> 119815 | E15: =E12+E14 -> 158826 | F15: =F12+F14 -> 194449 | G15: =G12+G14 -> 299269 | H15: filed / derived TTM
B16: Provision for income taxes | C16: 11922 | D16: 19697 | E16: 26656 | F16: 34241 | G16: =E16+'02 Quarterly'!D15+'02 Quarterly'!D34-'02 Quarterly'!C15-'02 Quarterly'!C34 -> 55064 | H16: filed / derived TTM
B17: Effective tax rate % | C17: =C16/C15*100 -> 13.90856 | D17: =D16/D15*100 -> 16.439511 | E17: =E16/E15*100 -> 16.783146 | F17: =F16/F15*100 -> 17.609245 | G17: =G16/G15*100 -> 18.3995 | H17: calc
B18: Net income | C18: =C15-C16 -> 73795 | D18: =D15-D16 -> 100118 | E18: =E15-E16 -> 132170 | F18: =F15-F16 -> 160208 | G18: =G15-G16 -> 244205 | H18: filed / DERIVED TTM consolidated NI; see common-income note
B19: Diluted EPS ($) | C19: 5.8 | D19: 8.04 | E19: 10.81 | F19: 13.11 | G19: 19.93 | H19: ="DERIVED from filed: FY2025 "&TEXT($E$19,"0.00")&" + H1'26 "&TEXT('06 Core EPS Bridge'!$J$13,"0.00")&" - H1'25 "&TEXT('06 Core EPS Bridge'!$F$13+'06 Core EPS Bridge'!$H$13,"0.00") -> DERIVED from filed: FY2025 10.81 + H1'26 14.24 - H1'25 5.12
B20: Diluted weighted-avg shares | C20: 12722 | D20: 12447 | E20: 12230 | F20: 12217 | G20: =E20+'05 Capital Structure'!C16-'05 Capital Structure'!C21 -> 12259 | H20: DERIVED TTM = FY2025 + H1'26 - H1'25, the same roll as TTM EPS
B22: Notes and caveats
B23: • TTM (Jun'26) columns are DERIVED as FY2025 + H1 2026 - H1 2025 from filed statements. They are not a reported figure.
B24: • RESOLVED 2026-09-22: derived TTM consolidated net income is 244,205. The Q2 2026 10-Q reports H1'26 net income of 174,771 but only 174,685 available to common stockholders after 86 of preferred dividends. On the common-income basis, FY2025 132,170 + H1'26 174,685 - H1'25 62,736 = 244,119, effectively the provider's 244,120 after rounding. Keep row 18 as consolidated net income; per-share work must deduct preferred dividends separately.
B25: ="• TTM diluted EPS of "&TEXT($G$19,"0.00")&" is as-reported by the data provider. A TTM EPS cannot be built by summing weighted-average share counts." -> • TTM diluted EPS of 19.93 is as-reported by the data provider. A TTM EPS cannot be built by summing weighted-average share counts.
B26: ="• FY2025 G&A jumped "&"("&TEXT($E$10,"#,##0")&" vs "&TEXT($D$10,"#,##0")&")"&" partly on the EUR 2.95B EU ad-tech fine booked in Q3 2025 plus legal charges." -> • FY2025 G&A jumped (21,482 vs 14,188) partly on the EUR 2.95B EU ad-tech fine booked in Q3 2025 plus legal charges.
B27: • S&M / G&A not separately pulled for TTM Mar'26; combined SG&A for that period was 52,361.

Sheet 02 Quarterly
B2: 02 — QUARTERLY INCOME STATEMENT
B3: $ millions except per-share.
B5: Q1 2026 vs Q1 2025
B6: Line item | C6: Q1'25 | D6: Q1'26
B7: Revenue | C7: 90234 | D7: 109896
B8: Cost of revenue | C8: 36361 | D8: 41271
B9: Operating expenses | C9: 23267 | D9: 28929
B10: Income from operations | C10: =C7-C8-C9 -> 30606 | D10: =D7-D8-D9 -> 39696
B11: Operating margin % | C11: =C10/C7*100 -> 33.918479 | D11: =D10/D7*100 -> 36.121424
B12: Other income (expense), net | C12: 11183 | D12: 37716
B13: of which: gain on equity securities, net | C13: 9758 | D13: 36915
B14: Pretax income | C14: =C10+C12 -> 41789 | D14: =D10+D12 -> 77412
B15: Income tax | C15: 7249 | D15: 14834
B16: Net income | C16: =C14-C15 -> 34540 | D16: =D14-D15 -> 62578
B17: Diluted EPS reported ($) | C17: 2.81 | D17: 5.11
B18: Diluted EPS CORE ($) | C18: ='06 Core EPS Bridge'!F12 -> 2.1829941 | D18: ='06 Core EPS Bridge'!G12 -> 2.7304421
B19: Diluted shares | C19: 12291 | D19: 12238
B21: Q2 2026 vs Q2 2025
B22: Line item | C22: Q2'25 | D22: Q2'26 | E22: YoY %
B23: Revenue | C23: 96428 | D23: 119796 | E23: =(D23/C23-1)*100 -> 24.233625
B24: Cost of revenue | C24: 39039 | D24: 45943 | E24: =(D24/C24-1)*100 -> 17.684879
B25: Research and development | C25: 13808 | D25: 18219 | E25: =(D25/C25-1)*100 -> 31.945249
B26: Sales and marketing | C26: 7101 | D26: 8403 | E26: =(D26/C26-1)*100 -> 18.335446
B27: General and administrative | C27: 5209 | D27: 6461 | E27: =(D27/C27-1)*100 -> 24.035323
B28: Income from operations | C28: =C23-C24-C25-C26-C27 -> 31271 | D28: =D23-D24-D25-D26-D27 -> 40770 | E28: =(D28/C28-1)*100 -> 30.376387
B29: Operating margin % | C29: =C28/C23*100 -> 32.429377 | D29: =D28/D23*100 -> 34.032856
B30: Other income (expense), net | C30: 2662 | D30: 97983
B31: of which: gain on equity securities | C31: 1286 | D31: 99031
B32: other income EX-GAIN | C32: =C30-C31 -> 1376 | D32: =D30-D31 -> -1048
B33: Pretax income | C33: =C28+C30 -> 33933 | D33: =D28+D30 -> 138753
B34: Income tax | C34: 5737 | D34: 26560
B35: Effective tax rate % | C35: =C34/C33*100 -> 16.906846 | D35: =D34/D33*100 -> 19.141928
B36: Net income | C36: =C33-C34 -> 28196 | D36: =D33-D34 -> 112193 | E36: =(D36/C36-1)*100 -> 297.90396
B37: Diluted EPS reported ($) | C37: 2.31 | D37: 9.11 | E37: =(D37/C37-1)*100 -> 294.37229
B38: Diluted EPS CORE ($) | C38: ='06 Core EPS Bridge'!H12 -> 2.2282391 | D38: ='06 Core EPS Bridge'!I12 -> 2.7588358 | E38: =(D38/C38-1)*100 -> 23.81238
B39: Diluted shares | C39: 12198 | D39: 12309 | E39: =(D39/C39-1)*100 -> 0.90998524
B41: Notes and caveats
B42: • Q1'26 quarterly figures are as filed. Diluted EPS CORE rows are DERIVED (see '06 Core EPS Bridge').
B43: ="• THE EX-GAIN LINE: other income excluding the securities gain went "&"+"&TEXT($C$32,"#,##0")&" (Q2'25) to "&TEXT($D$32,"#,##0")&" (Q2'26). Interest expense rose to 1,278 from 261 on a debt book that grew from "&TEXT('04 Balance Sheet'!$D$17,"#,##0")&" (FY2024) to "&TEXT('04 Balance Sheet'!$G$17,"#,##0")&" (Jun'26), but interest income of 1,430 still exceeds it; most of the swing is the 'other' line (-973). Model it explicitly." -> • THE EX-GAIN LINE: other income excluding the securities gain went +1,376 (Q2'25) to -1,048 (Q2'26). Interest expense rose to 1,278 from 261 on a debt book that grew from 13,559 (FY2024) to 102,754 (Jun'26), but interest income of 1,430 still exceeds it; most of the swing is the 'other' line (-973). Model it explicitly.
B44: ="• Reported Q2 net income grew "&"+"&TEXT($E$36,"0.0")&"%"&" and reported EPS "&"+"&TEXT($E$37,"0.0")&"%"&". Core EPS grew "&"+"&TEXT($E$38,"0.0")&"%"&"." -> • Reported Q2 net income grew +297.9% and reported EPS +294.4%. Core EPS grew +23.8%.

Sheet 03 Segments
B2: 03 — SEGMENT REVENUE, OPERATING INCOME, GROWTH AND MARGIN
B3: $ millions.
B5: Revenue by segment
B6: Line item | C6: FY2023 | D6: FY2024 | E6: FY2025 | F6: Q1'25 | G6: Q1'26 | H6: Q2'25 | I6: Q2'26
B7: Google Search & other | C7: 175033 | D7: 198084 | E7: 224532 | F7: 50702 | G7: 60399 | H7: 54190 | I7: 63271
B8: YouTube ads | C8: 31510 | D8: 36147 | E8: 40367 | F8: 8927 | G8: 9883 | H8: 9796 | I8: 11055
B9: Google Network | C9: 31312 | D9: 30359 | E9: 29792 | F9: 7256 | G9: 6971 | H9: 7354 | I9: 7303
B10: Google advertising subtotal | C10: =C7+C8+C9 -> 237855 | D10: =D7+D8+D9 -> 264590 | E10: =E7+E8+E9 -> 294691 | F10: =F7+F8+F9 -> 66885 | G10: =G7+G8+G9 -> 77253 | H10: =H7+H8+H9 -> 71340 | I10: =I7+I8+I9 -> 81629
B11: Subscriptions, platforms & devices | C11: 34688 | D11: 40340 | E11: 48030 | F11: 10379 | G11: 12384 | H11: 11203 | I11: 12911
B12: GOOGLE SERVICES TOTAL | C12: =C10+C11 -> 272543 | D12: =D10+D11 -> 304930 | E12: =E10+E11 -> 342721 | F12: =F10+F11 -> 77264 | G12: =G10+G11 -> 89637 | H12: =H10+H11 -> 82543 | I12: =I10+I11 -> 94540
B13: Google Cloud | C13: 33088 | D13: 43229 | E13: 58705 | F13: 12260 | G13: 20028 | H13: 13624 | I13: 24768
B14: Other Bets | C14: 1527 | D14: 1648 | E14: 1537 | F14: 450 | G14: 411 | H14: 373 | I14: 382
B15: Hedging gains (losses) | C15: 236 | D15: 211 | E15: -127 | F15: 260 | G15: -180 | H15: -112 | I15: 106
B16: TOTAL REVENUES | C16: =C12+C13+C14+C15 -> 307394 | D16: =D12+D13+D14+D15 -> 350018 | E16: =E12+E13+E14+E15 -> 402836 | F16: =F12+F13+F14+F15 -> 90234 | G16: =G12+G13+G14+G15 -> 109896 | H16: =H12+H13+H14+H15 -> 96428 | I16: =I12+I13+I14+I15 -> 119796
B18: Operating income (loss) by segment
B19: Line item | C19: FY2023 | D19: FY2024 | E19: FY2025 | F19: Q1'25 | G19: Q1'26 | H19: Q2'25 | I19: Q2'26
B20: Google Services | C20: 95858 | D20: 121263 | E20: 139404 | F20: 32682 | G20: 40589 | H20: 33063 | I20: 39544
B21: Google Cloud | C21: 1716 | D21: 6112 | E21: 13910 | F21: 2177 | G21: 6598 | H21: 2826 | I21: 8814
B22: Other Bets | C22: -4095 | D22: -4444 | E22: -7515 | F22: -1226 | G22: -2100 | H22: -1246 | I22: -1799
B23: Alphabet-level activities | C23: -9186 | D23: -10541 | E23: -16760 | F23: -3027 | G23: -5391 | H23: -3372 | I23: -5789
B24: TOTAL INCOME FROM OPERATIONS | C24: =C20+C21+C22+C23 -> 84293 | D24: =D20+D21+D22+D23 -> 112390 | E24: =E20+E21+E22+E23 -> 129039 | F24: =F20+F21+F22+F23 -> 30606 | G24: =G20+G21+G22+G23 -> 39696 | H24: =H20+H21+H22+H23 -> 31271 | I24: =I20+I21+I22+I23 -> 40770
B26: Revenue growth, YoY %
B27: Line item | C27: FY2024 | D27: FY2025 | E27: Q1'26 | F27: Q2'26
B28: Search & other | C28: =(D7/C7-1)*100 -> 13.169517 | D28: =(E7/D7-1)*100 -> 13.351911 | E28: =(G7/F7-1)*100 -> 19.125478 | F28: =(I7/H7-1)*100 -> 16.757704
B29: YouTube ads | C29: =(D8/C8-1)*100 -> 14.715963 | D29: =(E8/D8-1)*100 -> 11.674551 | E29: =(G8/F8-1)*100 -> 10.709085 | F29: =(I8/H8-1)*100 -> 12.852185
B30: Google Network | C30: =(D9/C9-1)*100 -> -3.0435616 | D30: =(E9/D9-1)*100 -> -1.8676504 | E30: =(G9/F9-1)*100 -> -3.9277839 | F30: =(I9/H9-1)*100 -> -0.69350014
B31: Subscriptions/platforms/devices | C31: =(D11/C11-1)*100 -> 16.293819 | D31: =(E11/D11-1)*100 -> 19.062965 | E31: =(G11/F11-1)*100 -> 19.317853 | F31: =(I11/H11-1)*100 -> 15.245916
B32: Google Services | C32: =(D12/C12-1)*100 -> 11.883262 | D32: =(E12/D12-1)*100 -> 12.393336 | E32: =(G12/F12-1)*100 -> 16.013926 | F32: =(I12/H12-1)*100 -> 14.534243
B33: Google Cloud | C33: =(D13/C13-1)*100 -> 30.648574 | D33: =(E13/D13-1)*100 -> 35.800042 | E33: =(G13/F13-1)*100 -> 63.360522 | F33: =(I13/H13-1)*100 -> 81.796829
B34: Total | C34: =(D16/C16-1)*100 -> 13.866243 | D34: =(E16/D16-1)*100 -> 15.090081 | E34: =(G16/F16-1)*100 -> 21.790013 | F34: =(I16/H16-1)*100 -> 24.233625
B36: Segment operating margin %
B37: Line item | C37: FY2023 | D37: FY2024 | E37: FY2025 | F37: Q1'26 | G37: Q2'26
B38: Google Services operating margin % | C38: =C20/C12*100 -> 35.171698 | D38: =D20/D12*100 -> 39.767488 | E38: =E20/E12*100 -> 40.675652 | F38: =G20/G12*100 -> 45.281524 | G38: =I20/I12*100 -> 41.827798
B39: Google Cloud operating margin % | C39: =C21/C13*100 -> 5.1861702 | D39: =D21/D13*100 -> 14.138657 | E39: =E21/E13*100 -> 23.694745 | F39: =G21/G13*100 -> 32.943879 | G39: =I21/I13*100 -> 35.58624
B41: Notes and caveats
B42: • Hedging gains (losses) are filed figures: Alphabet reports them as their own line in the revenue-by-type table (Q2 2026 10-Q R39: 106 and (112); FY2025 10-K R44: (127), 211 and 236). Corrected 2026-10-16; this note had called the Q2 figures a derived residual.
B43: ="• Cloud margin arc is the standout: "&TEXT($C$39,"0.0")&"% -> "&TEXT($D$39,"0.0")&"% -> "&TEXT($E$39,"0.0")&"% -> "&TEXT($F$39,"0.0")&"% (Q1'26) -> "&TEXT($G$39,"0.0")&"% (Q2'26)"&", on revenue that grew "&"+"&TEXT($F$33,"0.0")&"% YoY"&"." -> • Cloud margin arc is the standout: 5.2% -> 14.1% -> 23.7% -> 32.9% (Q1'26) -> 35.6% (Q2'26), on revenue that grew +81.8% YoY.
B44: ="• Services margin of "&TEXT($G$38,"0.0")&"% in Q2 vs "&TEXT($F$38,"0.0")&"% in Q1"&": Q1 is seasonally stronger, so read the pair rather than the sequential step-down." -> • Services margin of 41.8% in Q2 vs 45.3% in Q1: Q1 is seasonally stronger, so read the pair rather than the sequential step-down.
B45: ="• Alphabet-level activities (shared AI/DeepMind R&D, unallocated) is the fast-growing cost offset: "&TEXT($H$23,"#,##0")&" (Q2'25) -> "&TEXT($G$23,"#,##0")&" (Q1'26) -> "&TEXT($I$23,"#,##0")&" (Q2'26), +"&TEXT(($I$23/$H$23-1)*100,"0.0")&"% YoY"&"." -> • Alphabet-level activities (shared AI/DeepMind R&D, unallocated) is the fast-growing cost offset: -3,372 (Q2'25) -> -5,391 (Q1'26) -> -5,789 (Q2'26), +71.7% YoY.
B46: ="• Cloud backlog / remaining performance obligations at Jun 30, 2026: "&TEXT('15 Assumptions'!$C$112,"#,##0")&" (Cloud) of 519,500 total RPO. Just over 50% expected to convert within 24 months."&" Model cross-check at 17 Model rows 107-112." -> • Cloud backlog / remaining performance obligations at Jun 30, 2026: 513,900 (Cloud) of 519,500 total RPO. Just over 50% expected to convert within 24 months. Model cross-check at 17 Model rows 107-112.

Sheet 04 Balance Sheet
B2: 04 — BALANCE SHEET
B3: $ millions. Balance-sheet figures are point-in-time. FY2023-FY2025 are at December 31; Mar'26 and Jun'26 are at quarter end. All periods complete as filed.
B5: Line item | C5: FY2023 | D5: FY2024 | E5: FY2025 | F5: Mar'26 | G5: Jun'26
B6: Cash & equivalents | C6: 24048 | D6: 23466 | E6: 30708 | F6: 38063 | G6: 55911
B7: Marketable securities | C7: 86868 | D7: 72191 | E7: 96135 | F7: 88777 | G7: 186563
B8: Cash + marketable securities | C8: =C6+C7 -> 110916 | D8: =D6+D7 -> 95657 | E8: =E6+E7 -> 126843 | F8: =F6+F7 -> 126840 | G8: =G6+G7 -> 242474
B9: Receivables | C9: 47964 | D9: 52340 | E9: 62886 | F9: 62999 | G9: 69175
B10: Total current assets | C10: 171530 | D10: 163711 | E10: 206038 | F10: 213753 | G10: 343524
B11: Property & equipment, net (as previously carried) | C11: 148436 | D11: 184624 | E11: 261818 | F11: 296529 | G11: 321212
B12: Property & equipment, net (AS FILED) | C12: 134345 | D12: 171036 | E12: 246597 | F12: 281020 | G12: 321212 | H12: Complete - all periods as filed
B13: Goodwill | C13: 29198 | D13: 31885 | E13: 33380 | F13: 57774 | G13: 57828
B14: Total assets | C14: 402392 | D14: 450256 | E14: 595281 | F14: 703919 | G14: 921983
B15: Total current liabilities | C15: 81814 | D15: 89122 | E15: 102745 | F15: 111188 | G15: 126111
B16: Long-term debt | C16: 11870 | D16: 10883 | E16: 46547 | F16: 77501 | G16: 98165
B17: Total debt (excl. operating leases) | C17: 14536 | D17: 13559 | E17: 51043 | F17: 81713 | G17: 102754 | H17: Filed: long-term debt + current portion + finance leases
B18: Total liabilities | C18: 119013 | D18: 125172 | E18: 180016 | F18: 225173 | G18: 281503
B19: Total stockholders' equity | C19: 283379 | D19: 325084 | E19: 415265 | F19: 478746 | G19: 640480
B20: Common shares outstanding | C20: 12433 | D20: 12190 | E20: 12097 | F20: 12116 | G20: 12230
B21: Memo: operating lease liabilities (not debt) | C21: 15251 | D21: 14578 | E21: 15954 | F21: 16161 | G21: 18037 | H21: Lease cost is already in operating expenses and FCFF
B22: Net cash (derived) | C22: =C8-C17 -> 96380 | D22: =D8-D17 -> 82098 | E22: =E8-E17 -> 75800 | F22: =F8-F17 -> 45127 | G22: =G8-G17 -> 139720 | H22: DERIVED = cash+securities less total debt
B24: Notes and caveats
B25: ="• PP&E IS CARRIED AS FILED. Net PP&E is "&TEXT($D$12,"#,##0")&" at Dec 31 2024 and "&TEXT($E$12,"#,##0")&" at Dec 31 2025, per the FY2025 10-K property note. Standardized data feeds commonly fold lease right-of-use assets into PP&E, which overstates the figure and by a gap that grows year over year - the "&"AS FILED row in this sheet avoids that." -> • PP&E IS CARRIED AS FILED. Net PP&E is 171,036 at Dec 31 2024 and 246,597 at Dec 31 2025, per the FY2025 10-K property note. Standardized data feeds commonly fold lease right-of-use assets into PP&E, which overstates the figure and by a gap that grows year over year - the AS FILED row in this sheet avoids that.
B26: ="• USE THE AS FILED ROW (row 12) for all PP&E work. It is complete for every period: "&TEXT($C$12,"#,##0")&" / "&TEXT($D$12,"#,##0")&" / "&TEXT($E$12,"#,##0")&" / "&TEXT($F$12,"#,##0")&" / "&TEXT($G$12,"#,##0")&". Row 11 is retained only to show the overstatement in the standardized feed and must not be used in the model." -> • USE THE AS FILED ROW (row 12) for all PP&E work. It is complete for every period: 134,345 / 171,036 / 246,597 / 281,020 / 321,212. Row 11 is retained only to show the overstatement in the standardized feed and must not be used in the model.
B27: • All Jun'26 lines are taken from the Q2 2026 10-Q.
B28: ="• Mar'26 is PRE the 2026 equity raise; Jun'26 is post-raise. Cash and securities nearly doubled to "&TEXT($G$8,"#,##0")&" and net cash rose to "&"+"&TEXT($G$22,"#,##0")&" from "&"+"&TEXT($F$22,"#,##0")&". Jun'26 figures are as filed. Total debt excludes operating lease liabilities (row 21), because their cost already sits in operating expenses and in free cash flow; counting them as debt too double-c"&"ounted them (corrected 2026-09-24, entry 44)." -> • Mar'26 is PRE the 2026 equity raise; Jun'26 is post-raise. Cash and securities nearly doubled to 242,474 and net cash rose to +139,720 from +45,127. Jun'26 figures are as filed. Total debt excludes operating lease liabilities (row 21), because their cost already sits in operating expenses and in free cash flow; counting them as debt too double-counted them (corrected 2026-09-24, entry 44).
B29: • Goodwill rose 33,380 -> 57,774 at Mar 2026, an increase of 24,394, as the Wiz and Intersect acquisitions closed in Q1 2026 (57,828 at Jun 2026). Corrected 2026-10-13: this note put the Wiz goodwill at about 33,000, which is close to the purchase price, not the goodwill.
B30: ="• Common shares outstanding at Jun'26 is the July 15, 2026 cover-page count "&"(Class A "&TEXT('05 Capital Structure'!$C$18,"#,##0")&" / Class B "&TEXT('05 Capital Structure'!$C$19,"#,##0")&" / Class C "&TEXT('05 Capital Structure'!$C$20,"#,##0")&")"&"." -> • Common shares outstanding at Jun'26 is the July 15, 2026 cover-page count (Class A 5,868 / Class B 835 / Class C 5,527).
B32: MEMO ADDED 2026-10-07: DEFERRED TAX AND EQUITY STAKES (Q2 2026 10-Q; 29 Change Log entries 53 and 58)
B33: Memo line | E33: FY2025 | G33: Jun'26 | H33: Basis
B34: Deferred income taxes, liability | E34: 919 | G34: 22819 | H34: filed, Q2 2026 10-Q balance sheet (R2)
B35: Deferred income taxes, asset | E35: 9113 | G35: 1448 | H35: filed, Q2 2026 10-Q balance sheet (R2)
B36: Net deferred tax liability | E36: =E34-E35 -> -8194 | G36: =G34-G35 -> 21371 | H36: DERIVED
B37: Increase in H1'26 as % of H1'26 equity-securities gains | G37: =(G36-E36)/'06 Core EPS Bridge'!J7 -> 0.21747606 | H37: DERIVED: corroborates a ~21% rate on the gains
B39: Equity stakes | E39: FY2025 | G39: Jun'26 | H39: Basis
B40: Marketable equity securities, inside marketable securities (row 7) | G40: 87063 | H40: filed, Q2 2026 10-Q financial instruments note (R12)
B41: Debt securities, inside marketable securities (government 51,822, corporate 26,157, MBS/ABS 21,521) | G41: 99500 | H41: filed, Q2 2026 10-Q financial instruments note (R12)
B42: Marketable equity securities in other non-current assets | G42: 14126 | H42: filed, R12; in the 20 DCF bridge at fair value since 2026-10-07
B43: Non-marketable securities (balance-sheet line) | E43: 68687 | G43: 131461 | H43: filed, Q2 2026 10-Q balance sheet (R2)
B44: of which non-marketable equity securities under the measurement alternative, carrying value | E44: 64094 | G44: 124259 | H44: filed, Q2 2026 10-Q financial instruments note (R12)
B45: initial cost | G45: 47642 | H45: filed, Q2 2026 10-Q financial instruments note (R12)
B46: cumulative upward adjustments | G46: 85732 | H46: filed, Q2 2026 10-Q financial instruments note (R12)
B47: cumulative downward adjustments, including impairments | G47: -9115 | H47: filed, Q2 2026 10-Q financial instruments note (R12)
B48: Unrealized gain in the carrying value (row 44 less row 45) | G48: =G44-G45 -> 76617 | H48: DERIVED
B49: Deferred tax on that gain at '15 Assumptions' C85 | G49: =G48*'15 Assumptions'!C85 -> 16089.57 | H49: DERIVED; the 10-Q does not split the deferred tax liability (row 34) by holding
B50: Non-marketable equity securities, net of deferred tax (to 20 DCF Valuation row 25) | G50: =G44-G49 -> 108169.43 | H50: DERIVED
B51: Equity-method and other non-marketable securities (row 43 less row 44), at carrying value | E51: =E43-E44 -> 4593 | G51: =G43-G44 -> 7202 | H51: DERIVED; in the 20 DCF bridge since 2026-10-07
B52: ="• EQUITY STAKES (added 2026-10-07, entry 58). The DCF strips equity-securities gains out of earnings, so the stakes themselves must be valued in the bridge or they count nowhere. Net cash already car"&"ries the "&TEXT($G$40,"#,##0")&" of marketable equity (row 40) at fair value. The "&TEXT($G$44,"#,##0")&" of non-marketable equity under the measurement alternative sits outside net cash, so 20 DCF Valuation row 25 adds it net of deferred tax on its "&TEXT($G$48,"#,##0")&" unrealized gain." -> • EQUITY STAKES (added 2026-10-07, entry 58). The DCF strips equity-securities gains out of earnings, so the stakes themselves must be valued in the bridge or they count nowhere. Net cash already carries the 87,063 of marketable equity (row 40) at fair value. The 124,259 of non-marketable equity under the measurement alternative sits outside net cash, so 20 DCF Valuation row 25 adds it net of deferred tax on its 76,617 unrealized gain.
B53: ="• ALSO IN THE BRIDGE since 2026-10-07 (entry 61): the "&TEXT($G$42,"#,##0")&" of marketable equity held in other non-current assets, at fair value like the marketable equity inside net cash, and the "&TEXT($G$51,"#,##0")&" of equity-method and other non-marketable securities at carrying value. Neither carries a disclosed unrealized gain, so no deferred tax is deducted. Mark-to-market stakes are not cash-like in a drawd"&"own; row 27 of 20 DCF Valuation discloses the equity inside net cash." -> • ALSO IN THE BRIDGE since 2026-10-07 (entry 61): the 14,126 of marketable equity held in other non-current assets, at fair value like the marketable equity inside net cash, and the 7,202 of equity-method and other non-marketable securities at carrying value. Neither carries a disclosed unrealized gain, so no deferred tax is deducted. Mark-to-market stakes are not cash-like in a drawdown; row 27 of 20 DCF Valuation discloses the equity inside net cash.
B54: Equity stakes outside net cash, to 20 DCF Valuation row 25 (rows 42 + 50 + 51) | G54: =G42+G50+G51 -> 129497.43 | H54: DERIVED

Sheet 05 Capital Structure
B2: 05 — CAPITAL STRUCTURE AFTER THE JUNE 2026 RAISE
B3: $ millions. Confirmed against the Q2 2026 10-Q.
B5: Component | C5: Amount | D5: Note
B6: Common stock offering (June 2026) | C6: 30500 | D6: net of costs
B7: 6.25% mandatory convertible preferred, Series A + B | C7: 19000 | D7: 19M shares, $1,000 liquidation preference, issued June 5, 2026
B8: ATM program drawn through June 30, 2026 (40,000 authorised) | C8: 0 | D8: none sold at June 30 per the Q2 10-Q
B9: TOTAL RAISED | C9: =C6+C7+C8 -> 49500 | D9: vs the $84,750 headline figure
B11: Share counts (millions)
B12: Measure | C12: Shares
B13: Q2 2026 weighted-average basic | C13: 12151
B14: Q2 2026 weighted-average diluted | C14: ='02 Quarterly'!D39 -> 12309
B15: H1 2026 weighted-average basic | C15: 12125
B16: H1 2026 weighted-average diluted | C16: 12274
B17: Shares outstanding, July 15, 2026 | C17: =C18+C19+C20 -> 12230
B18: of which Class A | C18: 5868
B19: of which Class B | C19: 835
B20: of which Class C | C20: 5527
B21: H1 2025 weighted-average diluted | C21: 12245 | D21: Filed, Q2 2025 10-Q. Used to roll TTM share count the same way as TTM EPS
B22: Model inputs
B23: Item | C23: Value | D23: Note
B24: Preferred dividend, annual | C24: =C7*0.0625 -> 1187.5 | D24: DERIVED = 19,000 x 6.25%
B25: Net cash at Jun'26 | C25: ='04 Balance Sheet'!G22 -> 139720 | D25: ="DERIVED = "&TEXT('04 Balance Sheet'!G8,"#,##0")&" less "&TEXT('04 Balance Sheet'!G17,"#,##0") -> DERIVED = 242,474 less 102,754
B26: Net cash at Mar'26 | C26: ='04 Balance Sheet'!F22 -> 45127 | D26: DERIVED - pre-raise; use the Jun'26 figure in row 25
B28: Notes and caveats
B29: ="• THE RAISE AS FILED: "&TEXT($C$6,"#,##0")&" of common"&" stock and "&TEXT($C$7,"#,##0")&" of preferred"&", "&"about "&TEXT($C$9,"#,##0")&" in total"&". The 40,000 ATM was authorised on June 1 2026 and no shares had been sold under it by June 30 (Q2 10-Q); it is forward dilution, stated to fund tax on employee equity grants. Corrected 2026-09-24 fro"&"m 'already drawn 30,400', which double-counted the common offering." -> • THE RAISE AS FILED: 30,500 of common stock and 19,000 of preferred, about 49,500 in total. The 40,000 ATM was authorised on June 1 2026 and no shares had been sold under it by June 30 (Q2 10-Q); it is forward dilution, stated to fund tax on employee equity grants. Corrected 2026-09-24 from 'already drawn 30,400', which double-counted the common offering.
B30: • SHARE COUNT: rows 13 to 16 and 21 are filed weighted averages (corrected to the Q2 10-Q 2026-09-24). The forecast count on 17 Model row 37 grows by stock-based compensation issued at the reference price.
B31: ="• PREFERRED is "&TEXT($C$7,"#,##0")&" at 6.25%"&", which is "&"roughly "&TEXT($C$24,"#,##0")&" PER YEAR"&" of preferred dividends reducing income available to common, plus dilution on mandatory conversion. Both effects must be carried in any per-share figure." -> • PREFERRED is 19,000 at 6.25%, which is roughly 1,188 PER YEAR of preferred dividends reducing income available to common, plus dilution on mandatory conversion. Both effects must be carried in any per-share figure.
B32: • THE EPS BUILD NEEDS A PREFERRED DIVIDEND LINE.
B33: • Buybacks remain suspended, so the historical share-count tailwind is gone and the count now drifts up.
B34: ="• Net cash at Jun'26 is "&"+"&TEXT($C$25,"#,##0")&" ("&TEXT('04 Balance Sheet'!$G$8,"#,##0")&" cash and securities less "&TEXT('04 Balance Sheet'!$G$17,"#,##0")&" of debt: "&TEXT('04 Balance Sheet'!$G$16,"#,##0")&" long-term, 1,999 current and 2,590 finance leases), up from "&"+"&TEXT($C$26,"#,##0")&" at Mar'26. Operating lease liabilities of "&TEXT('04 Balance Sheet'!$G$21,"#,##0")&" are not debt here because FCFF already pays the lease cost. Use the Jun'26 figure in the DCF equity bridge." -> • Net cash at Jun'26 is +139,720 (242,474 cash and securities less 102,754 of debt: 98,165 long-term, 1,999 current and 2,590 finance leases), up from +45,127 at Mar'26. Operating lease liabilities of 18,037 are not debt here because FCFF already pays the lease cost. Use the Jun'26 figure in the DCF equity bridge.
B35: ="• Other income excluding the securities gain went "&"+"&TEXT('02 Quarterly'!$C$32,"#,##0")&" (Q2'25) to "&TEXT('02 Quarterly'!$D$32,"#,##0")&" (Q2'26). Interest expense rose to 1,278 from 261 on a debt book that grew from "&TEXT('04 Balance Sheet'!$D$17,"#,##0")&" (FY2024) to "&TEXT('04 Balance Sheet'!$G$17,"#,##0")&" (Jun'26), but interest income of 1,430 still exceeds it; most of the swing is the 'other' line (-973). Model it explicitly." -> • Other income excluding the securities gain went +1,376 (Q2'25) to -1,048 (Q2'26). Interest expense rose to 1,278 from 261 on a debt book that grew from 13,559 (FY2024) to 102,754 (Jun'26), but interest income of 1,430 still exceeds it; most of the swing is the 'other' line (-973). Model it explicitly.
B36: ="• DISCLOSURE NOTE: two consecutive earnings calls (Apr 29 and Jul 22) passed with NO mention of the equity raise, buybacks, or the preferred. "&"The "&TEXT($C$9,"#,##0")&" raise (common plus preferred, as filed)"&" priced five weeks after the April call without being signalled on it." -> • DISCLOSURE NOTE: two consecutive earnings calls (Apr 29 and Jul 22) passed with NO mention of the equity raise, buybacks, or the preferred. The 49,500 raise (common plus preferred, as filed) priced five weeks after the April call without being signalled on it.

Sheet 06 Core EPS Bridge
B2: 06 — NORMALIZED (CORE) EPS BRIDGE
B3: Strip the gain on equity securities, tax the gain at the gains rate ('15 Assumptions' C85), treat the rest of reported tax as core tax, divide by diluted shares.
B5: Line item | C5: FY2023 | D5: FY2024 | E5: FY2025 | F5: Q1'25 | G5: Q1'26 | H5: Q2'25 | I5: Q2'26 | J5: H1'26 | K5: Basis
B6: Reported pretax income | C6: 85717 | D6: 119815 | E6: 158826 | F6: 41789 | G6: 77412 | H6: 33933 | I6: 138753 | J6: =G6+I6 -> 216165 | K6: filed
B7: less: gain on equity securities | C7: 392 | D7: 3714 | E7: 24080 | F7: 9758 | G7: 36915 | H7: 1286 | I7: 99031 | J7: =G7+I7 -> 135946 | K7: filed
B8: Normalized pretax income | C8: =C6-C7 -> 85325 | D8: =D6-D7 -> 116101 | E8: =E6-E7 -> 134746 | F8: =F6-F7 -> 32031 | G8: =G6-G7 -> 40497 | H8: =H6-H7 -> 32647 | I8: =I6-I7 -> 39722 | J8: =J6-J7 -> 80219 | K8: DERIVED
B9: Core effective tax rate applied % (row 36) | C9: =C36 -> 13.87598 | D9: =D36 -> 16.293624 | E9: =E36 -> 16.029567 | F9: =F36 -> 16.233711 | G9: =G36 -> 17.487345 | H9: =H36 -> 16.745612 | I9: =I36 -> 14.509566 | J9: =J36 -> 16.01284 | K9: DERIVED
B10: Normalized net income | C10: =C8-C35 -> 73485.32 | D10: =D8-D35 -> 97183.94 | E10: =E8-E35 -> 113146.8 | F10: =F8-F35 -> 26831.18 | G10: =G8-G35 -> 33415.15 | H10: =H8-H35 -> 27180.06 | I10: =I8-I35 -> 33958.51 | J10: =J8-J35 -> 67373.66 | K10: DERIVED
B11: Diluted shares | C11: 12722 | D11: 12447 | E11: 12230 | F11: 12291 | G11: 12238 | H11: 12198 | I11: ='02 Quarterly'!D39 -> 12309 | J11: ='05 Capital Structure'!C16 -> 12274 | K11: filed
B12: CORE diluted EPS ($) | C12: =C10/C11 -> 5.7762396 | D12: =D10/D11 -> 7.8078204 | E12: =E10/E11 -> 9.2515781 | F12: =F10/F11 -> 2.1829941 | G12: =G10/G11 -> 2.7304421 | H12: =H10/H11 -> 2.2282391 | I12: =I10/I11 -> 2.7588358 | J12: =J10/J11 -> 5.4891364 | K12: DERIVED
B13: Reported diluted EPS ($) | C13: 5.8 | D13: 8.04 | E13: 10.81 | F13: 2.81 | G13: 5.11 | H13: 2.31 | I13: 9.11 | J13: 14.24 | K13: filed
B15: Derived summary figures
B16: Metric | C16: Reported | D16: CORE | E16: Basis
B17: TTM (Jun'26) EPS ($) | C17: ='01 Income Statement'!G19 -> 19.93 | D17: =E12-F12-H12+J12 -> 10.329481 | E17: DERIVED core
B18: FY2026E EPS ($) | C18: ='07 Consensus'!C6 -> 20.6 | D18: ='17 Model'!L48 -> 11.818616 | E18: consensus vs model core ('17 Model' L48, follows the scenario switch)
B19: ="P/E at $"&TEXT('11 Valuation'!$C$6,"0.00") -> P/E at $340.59 | C19: ='11 Valuation'!C6/C17 -> 17.089313 | D19: ='11 Valuation'!C6/D17 -> 32.972614 | E19: DERIVED core multiple
B20: ="Forward P/E at $"&TEXT('11 Valuation'!$C$6,"0.00") -> Forward P/E at $340.59 | C20: ='11 Valuation'!C6/C18 -> 16.533495 | D20: ='11 Valuation'!C6/D18 -> 28.818094 | E20: DERIVED core multiple
B22: Notes and caveats
B23: • Method (rebuilt 2026-10-07, entry 53): strip the gain on equity securities from pretax income; core tax is reported tax less the gain taxed at '15 Assumptions' C85 (rows 31-38). Before this, the blended period rate was applied to normalized income, which overstated core tax because the gains carry the higher rate.
B24: ="• Q2 2026 gain of "&TEXT($I$7,"#,##0")&" is the largest on record: "&TEXT($I$7/$G$7,"0.0")&"x"&" the prior record set one quarter earlier "&"("&TEXT($G$7,"#,##0")&")"&", "&TEXT($I$7/$E$7,"0.0")&"x"&" all of FY2025 "&"("&TEXT($E$7,"#,##0")&")"&", and "&TEXT($I$7/$I$6,"0%")&" of Q2"&" pretax income." -> • Q2 2026 gain of 99,031 is the largest on record: 2.7x the prior record set one quarter earlier (36,915), 4.1x all of FY2025 (24,080), and 71% of Q2 pretax income.
B25: ="• Reported Q2 2026 EPS grew "&"+"&TEXT(($I$13/$H$13-1)*100,"0")&"% YoY"&". CORE EPS grew "&"+"&TEXT(($I$12/$H$12-1)*100,"0.0")&"% ($"&TEXT($H$12,"0.00")&" -> $"&TEXT($I$12,"0.00")&")"&". The headline is an artifact." -> • Reported Q2 2026 EPS grew +294% YoY. CORE EPS grew +23.8% ($2.23 -> $2.76). The headline is an artifact.
B26: ="• Core H1 2026 EPS of "&TEXT(J12,"0.00")&" is "&TEXT(J12/J13,"0%")&" of the reported "&TEXT(J13,"0.00")&"." -> • Core H1 2026 EPS of 5.49 is 39% of the reported 14.24.
B27: ="• TTM (Jun'26) core EPS "&TEXT(D17,"0.00")&" vs reported "&TEXT(C17,"0.00")&". Built as FY2025 core "&TEXT(E12,"0.00")&" less H1'25 core "&TEXT(F12+H12,"0.00")&" plus H1'26 core "&TEXT(J12,"0.00")&". Gains are the filed figures (XBRL EquitySecuritiesFvNiGainLoss), corrected 2026-09-24." -> • TTM (Jun'26) core EPS 10.33 vs reported 19.93. Built as FY2025 core 9.25 less H1'25 core 4.41 plus H1'26 core 5.49. Gains are the filed figures (XBRL EquitySecuritiesFvNiGainLoss), corrected 2026-09-24.
B28: ="• FY2026E core EPS is "&TEXT('06 Core EPS Bridge'!$D$18,"0.00")&" ("&'16 Scenarios'!$F$6&"), linked live to '17 Model' L48 since 2026-09-21. It replaced a hard-typed ~10.85 (H1 actual core 5.29 plus an assumed H2 path), which predated the model." -> • FY2026E core EPS is 11.82 (BASE CASE), linked live to '17 Model' L48 since 2026-09-21. It replaced a hard-typed ~10.85 (H1 actual core 5.29 plus an assumed H2 path), which predated the model.
B29: • ALL rows marked DERIVED are my own arithmetic, not filed figures. Re-check before publication.
B31: CORE TAX REBUILT 2026-10-07: reported tax less the tax on the equity-securities gain (29 Change Log entry 53)
B32: Line item | C32: =C$5 -> FY2023 | D32: =D$5 -> FY2024 | E32: =E$5 -> FY2025 | F32: =F$5 -> Q1'25 | G32: =G$5 -> Q1'26 | H32: =H$5 -> Q2'25 | I32: =I$5 -> Q2'26 | J32: =J$5 -> H1'26 | K32: Basis
B33: Reported provision for income taxes | C33: ='01 Income Statement'!C16 -> 11922 | D33: ='01 Income Statement'!D16 -> 19697 | E33: ='01 Income Statement'!E16 -> 26656 | F33: ='02 Quarterly'!C15 -> 7249 | G33: ='02 Quarterly'!D15 -> 14834 | H33: ='02 Quarterly'!C34 -> 5737 | I33: ='02 Quarterly'!D34 -> 26560 | J33: =G33+I33 -> 41394 | K33: filed
B34: less: tax on the equity-securities gain (row 7 x '15 Assumptions' C85) | C34: =C7*'15 Assumptions'!$C$85 -> 82.32 | D34: =D7*'15 Assumptions'!$C$85 -> 779.94 | E34: =E7*'15 Assumptions'!$C$85 -> 5056.8 | F34: =F7*'15 Assumptions'!$C$85 -> 2049.18 | G34: =G7*'15 Assumptions'!$C$85 -> 7752.15 | H34: =H7*'15 Assumptions'!$C$85 -> 270.06 | I34: =I7*'15 Assumptions'!$C$85 -> 20796.51 | J34: =J7*'15 Assumptions'!$C$85 -> 28548.66 | K34: DERIVED
B35: Core tax | C35: =C33-C34 -> 11839.68 | D35: =D33-D34 -> 18917.06 | E35: =E33-E34 -> 21599.2 | F35: =F33-F34 -> 5199.82 | G35: =G33-G34 -> 7081.85 | H35: =H33-H34 -> 5466.94 | I35: =I33-I34 -> 5763.49 | J35: =J33-J34 -> 12845.34 | K35: DERIVED
B36: Core effective tax rate % | C36: =C35/C8*100 -> 13.87598 | D36: =D35/D8*100 -> 16.293624 | E36: =E35/E8*100 -> 16.029567 | F36: =F35/F8*100 -> 16.233711 | G36: =G35/G8*100 -> 17.487345 | H36: =H35/H8*100 -> 16.745612 | I36: =I35/I8*100 -> 14.509566 | J36: =J35/J8*100 -> 16.01284 | K36: DERIVED
B37: Reported effective tax rate %, for reference | C37: =C33/C6*100 -> 13.90856 | D37: =D33/D6*100 -> 16.439511 | E37: =E33/E6*100 -> 16.783146 | F37: =F33/F6*100 -> 17.34667 | G37: =G33/G6*100 -> 19.162404 | H37: =H33/H6*100 -> 16.906846 | I37: =I33/I6*100 -> 19.141928 | J37: =J33/J6*100 -> 19.149261 | K37: filed-derived
B38: Check: core tax + gain tax - reported tax (must be 0) | C38: =C35+C34-C33 -> 0 | D38: =D35+D34-D33 -> 0 | E38: =E35+E34-E33 -> 0 | F38: =F35+F34-F33 -> 0 | G38: =G35+G34-G33 -> 0 | H38: =H35+H34-H33 -> 0 | I38: =I35+I34-I33 -> 0 | J38: =J35+J34-J33 -> 0 | K38: check

Sheet 07 Consensus
B2: 07 — CONSENSUS ESTIMATES AND THE IMPLIED NET MARGIN
B3: Rows 6-32: FY2026 GAAP-basis consensus as of September 8, 2026, kept as a dated record. Rows 34-39 and 56-76: October 12-13, 2026 (StockAnalysis, MarketScreener). Rows 78-83: a provider check on October 16, 2026. $ millions except per-share.
B5: Metric | C5: Value | D5: Basis
B6: Consensus FY2026 EPS ($) | C6: 20.6 | D6: 51 analysts
B7: Consensus FY2026 revenue | C7: 498080
B8: Implied FY2026 net income | C8: ='07 Consensus'!C6*'05 Capital Structure'!C16 -> 252844.4 | D8: ="DERIVED = consensus EPS x H1'26 wtd-avg DILUTED shares ("&TEXT('05 Capital Structure'!$C$16,"#,##0")&")" -> DERIVED = consensus EPS x H1'26 wtd-avg DILUTED shares (12,274)
B9: IMPLIED NET MARGIN % | C9: =C8/C7*100 -> 50.763813
B11: Alphabet Q2 2026 operating margin % | C11: ='02 Quarterly'!D29 -> 34.032856 | D11: actual
B12: Alphabet FY2025 net margin % | C12: ='01 Income Statement'!E18/'01 Income Statement'!E6*100 -> 32.809878 | D12: ="actual, already includes "&TEXT('06 Core EPS Bridge'!$E$7,"#,##0")&" of gains" -> actual, already includes 24,080 of gains
B13: Alphabet FY2025 CORE net margin % | C13: ='06 Core EPS Bridge'!E10/'01 Income Statement'!E6*100 -> 28.087559
B15: Average price target ($) | C15: 430.4 | D15: ="+"&TEXT(C15/'11 Valuation'!$C$6-1,"0.0%")&" vs "&TEXT('11 Valuation'!$C$6,"$0.00") -> +26.4% vs $340.59
B16: Median price target ($) | C16: 430
B17: High price target ($) | C17: 515
B18: Low price target ($) | C18: 340
B20: Ratings - Strong Buy | C20: 44
B21: Ratings - Buy | C21: 13
B22: Ratings - Hold | C22: 5
B23: Ratings - Sell | C23: 0
B24: Ratings - Strong Sell | C24: 0
B26: FY2026 EPS - LOW estimate ($) | C26: 19.7 | D26: most bearish of 51 analysts
B27: FY2026 EPS - mean ($) | C27: =C6 -> 20.6
B28: FY2026 EPS - HIGH estimate ($) | C28: 21.92
B29: FY2026 EPS spread as % of mean | C29: =(C28-C26)/C27*100 -> 10.776699 | D29: DERIVED
B30: FY2026 revenue - LOW | C30: 489800
B31: FY2026 revenue - HIGH | C31: 519800
B32: FY2026 revenue spread as % of mean | C32: =(C31-C30)/C7*100 -> 6.0231288 | D32: DERIVED
B34: FY2027 EPS - consensus mean ($) | C34: 15.24 | D34: StockAnalysis, Oct 12 2026 (S&P Global poll). The page gave +28.95% on its FY2026 mean of 11.82 (row 67), a provider-stated growth rate. Was 14.84 on Sep 8 (49 analysts, range 13.67-17.21); the range is not shown on the free page. 15.25 on Oct 16 (row 80).
B35: FY2027 revenue - consensus | C35: 618790 | D35: StockAnalysis, Oct 12 2026. Was 612,190 in Sep.
B36: FY2026 EBIT - consensus | C36: 171690 | D36: MarketScreener, retrieved Oct 13 2026; on revenue 499,293. Was 171,734 on Sep 21.
B37: FY2026 operating margin - consensus % | C37: 34.39 | D37: MarketScreener, provider-stated, Oct 13 2026
B38: FY2027 EBIT - consensus | C38: 218330 | D38: MarketScreener, retrieved Oct 13 2026; on revenue 618,791 and GAAP EPS 15.03. Was 216,725 on Sep 21.
B39: FY2027 operating margin - consensus % | C39: 35.28 | D39: MarketScreener, provider-stated, Oct 13 2026. EBT of 227,265 implies about 8,900 of pretax non-operating income.
B41: Notes and caveats
B42: ="• THE IMPLIED MARGIN, READ CORRECTLY: FY2026 consensus EPS of "&TEXT($C$6,"0.00")&" on consensus revenue of "&TEXT($C$7,"#,##0")&" implies a "&TEXT($C$9,"0.0")&"% NET margin against a "&TEXT($C$11,"0.0")&"% Q2 OPERATING margin. The gap is the H1'26 marks, which a GAAP-basis consensus has to include because they are booked: taking them out leaves about "&TEXT($C$63,"0.00")&" (row 63, derived here, not a published figure) against the model's core "&TEXT('06 Core EPS Bridge'!$D$18,"0.00")&", and FY2027 consensus of "&TEXT($C$34,"0.00")&" sits "&TEXT(1-$C$34/$C$6,"0%")&" below 20.60, consistent with marks that do not recur. Consensus is not mis-specified. The reported "&TEXT('11 Valuation'!$C$13,"0.0")&"x forward P/E on the September GAAP consensus makes the stock look cheaper than it is to anyone striking a multiple off GAAP EPS. The provider's own forward P/E ("&TEXT($C$70,"0.0")&"x, row 70) does not state its earnings basis, and by October 16 its FY2026 estimates mixed analysts who include the marks with analysts who leave them out (row 79). On the Q2 call nobody asked about the "&TEXT('06 Core EPS Bridge'!$I$7,"#,##0")&" gain." -> • THE IMPLIED MARGIN, READ CORRECTLY: FY2026 consensus EPS of 20.60 on consensus revenue of 498,080 implies a 50.8% NET margin against a 34.0% Q2 OPERATING margin. The gap is the H1'26 marks, which a GAAP-basis consensus has to include because they are booked: taking them out leaves about 11.85 (row 63, derived here, not a published figure) against the model's core 11.82, and FY2027 consensus of 15.24 sits 26% below 20.60, consistent with marks that do not recur. Consensus is not mis-specified. The reported 16.5x forward P/E on the September GAAP consensus makes the stock look cheaper than it is to anyone striking a multiple off GAAP EPS. The provider's own forward P/E (25.6x, row 70) does not state its earnings basis, and by October 16 its FY2026 estimates mixed analysts who include the marks with analysts who leave them out (row 79). On the Q2 call nobody asked about the 99,031 gain.
B43: ="• Consensus FY2026 EPS moved from 14.22 before the Q2 print to 20.60 after it. The rise of 6.38 is close to the Q2 gain of "&TEXT('06 Core EPS Bridge'!$I$7,"#,##0")&" after tax ("&TEXT('06 Core EPS Bridge'!$I$7*(1-'15 Assumptions'!$C$85)/'05 Capital Structure'!$C$16,"0.00")&" a share), so the marks explain most of it."&" This pack has no bridge of individual revisions, so changes to the operating outlook cannot be ruled out." -> • Consensus FY2026 EPS moved from 14.22 before the Q2 print to 20.60 after it. The rise of 6.38 is close to the Q2 gain of 99,031 after tax (6.37 a share), so the marks explain most of it. This pack has no bridge of individual revisions, so changes to the operating outlook cannot be ruled out.
B44: • REVISION DATA CORRECTION: verified 30-day revisions were FY2026 4 up / 1 down and FY2027 9 up / 1 down. An earlier secondary-source count was removed.
B45: • PRICE TARGETS: MarketBeat showed 420.19 across 54 analysts (range 255-515) in September against StockAnalysis's 428.07, so the 360.92 figure flagged earlier was the outlier and is not used. The current StockAnalysis mean is at C15.
B46: • FIRST NAMED POST-Q2 SELL-SIDE ACTIONS: BMO Capital 455 to 465 (raised), Barclays 405 to 425 (raised), PIPER SANDLER 445 to 395 (CUT). Piper's is the first target cut recorded since HSBC's before the Q2 print, and it comes from a house that had been raising into the earlier selloff.
B47: • DISPERSION INTERPRETATION: narrowing reflects booked H1 marks that analysts must include; it is not evidence that consensus is mis-specified.
B48: ="• THE MOST BEARISH ANALYST OF 51 IS AT "&TEXT($C$26,"0.00")&", against a core FY2026E of "&TEXT('06 Core EPS Bridge'!$D$18,"0.00")&" (17 Model). The panel works off the GAAP line, which includes the H1 marks already booked; excluding them, consensus is about "&TEXT($C$63,"0.00")&" (row 63; see 29 Change Log entry 31)." -> • THE MOST BEARISH ANALYST OF 51 IS AT 19.70, against a core FY2026E of 11.82 (17 Model). The panel works off the GAAP line, which includes the H1 marks already booked; excluding them, consensus is about 11.85 (row 63; see 29 Change Log entry 31).
B49: ="• THE SEPTEMBER CONSENSUS IS STRUCK ON REPORTED EPS: the +90.54% FY2026 growth rate implies a base of 20.60/1.9054 = 10.81, which is the reported FY2025 EPS."&" That fits a GAAP basis; it does not show how each analyst treats the marks. Core growth over the same period is "&TEXT('06 Core EPS Bridge'!$D$18,"0.00")&"/"&TEXT('06 Core EPS Bridge'!$E$12,"0.00")&" = +"&TEXT(('06 Core EPS Bridge'!$D$18/'06 Core EPS Bridge'!$E$12-1)*100,"0.0")&"%. A +90.5% headline against that core growth is the gap the multiple misreads." -> • THE SEPTEMBER CONSENSUS IS STRUCK ON REPORTED EPS: the +90.54% FY2026 growth rate implies a base of 20.60/1.9054 = 10.81, which is the reported FY2025 EPS. That fits a GAAP basis; it does not show how each analyst treats the marks. Core growth over the same period is 11.82/9.25 = +27.7%. A +90.5% headline against that core growth is the gap the multiple misreads.
B50: • FY2027 consensus is verified at rows 34-39; the earlier two-house stopgap has been retired.
B51: • The FY2027 EPS decline largely reflects the roll-off of FY2026 securities gains rather than an assumed operating collapse.
B52: • Use the verified consensus block above for comparisons. Earlier provisional estimates are preserved only in '29 Change Log'.
B53: • EPS and revenue consensus in rows 6-32 as of September 8, 2026 (GAAP basis); rows 34-39 and 56-61 re-pulled October 12-13, 2026. Price targets and ratings as of October 12, 2026; ratings total 62. Rows 66-76 carry the October 12-13 update and rows 78-83 the October 16 provider check.
B54: ="• SHARE-COUNT CONVENTION, corrected September 15 2026. Implied FY2026 net income (C8) previously multiplied the FULL-YEAR consensus EPS of 20.60 by the Q2'26-ONLY weighted-average diluted count of "&TEXT('05 Capital Structure'!$C$14,"#,##0")&". A full-year EPS figure must be paired with a full-year share count; mixing a period EPS with a different period's share count overstates the implied figure. It now uses the H1'26 weighted-average di"&"luted count of "&TEXT('05 Capital Structure'!$C$16,"#,##0")&" ('05 Capital Structure'!C16), the longest weighted-average period available in this pack. NOTE the true basis would be the FY2026 weighted-average, which is not yet knowable - and with buybacks suspe"&"nded "&"and SBC issuance continuing (the ATM is authorised but was undrawn at Jun 30),"&" the count DRIFTS UP through H2, so "&TEXT('05 Capital Structure'!$C$16,"#,##0")&" is a mild UNDERSTATEMENT: with EPS and revenue held, a higher full-year count makes implied net income and the implied net margin slightly HIGHER"&" still. Corrected 2026-10-18; this note had said lower. The direction of the finding is unchanged: the implied net margin remains far above any achievable operating margin." -> • SHARE-COUNT CONVENTION, corrected September 15 2026. Implied FY2026 net income (C8) previously multiplied the FULL-YEAR consensus EPS of 20.60 by the Q2'26-ONLY weighted-average diluted count of 12,309. A full-year EPS figure must be paired with a full-year share count; mixing a period EPS with a different period's share count overstates the implied figure. It now uses the H1'26 weighted-average diluted count of 12,274 ('05 Capital Structure'!C16), the longest weighted-average period available in this pack. NOTE the true basis would be the FY2026 weighted-average, which is not yet knowable - and with buybacks suspended and SBC issuance continuing (the ATM is authorised but was undrawn at Jun 30), the count DRIFTS UP through H2, so 12,274 is a mild UNDERSTATEMENT: with EPS and revenue held, a higher full-year count makes implied net income and the implied net margin slightly HIGHER still. Corrected 2026-10-18; this note had said lower. The direction of the finding is unchanged: the implied net margin remains far above any achievable operating margin.
B56: FY2028 CONSENSUS - major public provider
B57: FY2028 EPS - consensus ($) | C57: 18.03 | D57: MarketScreener, retrieved Oct 13 2026 (GAAP). Was 17.80 on Sep 22.
B58: FY2028 revenue - consensus | C58: 741819 | D58: MarketScreener, retrieved Oct 13 2026
B59: FY2028 EBIT - consensus | C59: 265388 | D59: MarketScreener, retrieved Oct 13 2026
B60: FY2028 operating margin - consensus % | C60: 35.78 | D60: MarketScreener, provider-stated, Oct 13 2026
B61: FY2028 FCF - consensus | C61: 6281 | D61: MarketScreener, Oct 13 2026; FY2027 is negative 37,003 (row 75)
B63: Derived here: September FY2026 consensus EPS less estimated H1'26 marks ($) | C63: =C6-C64 -> 11.850013 | D63: DERIVED here = September GAAP-basis consensus (row 6) less the H1'26 marks per share (row 64). Not a published consensus figure; it differs from base-case core EPS (11.82) because the methods differ.
B64: H1'26 equity-securities marks per share, after tax ($) | C64: ='06 Core EPS Bridge'!J7*(1-'15 Assumptions'!C85)/'05 Capital Structure'!C16 -> 8.749987 | D64: DERIVED = H1'26 gain x (1 - gains tax rate, 15 Assumptions C85) / H1'26 diluted shares
B66: CONSENSUS UPDATE - October 12, 2026 (StockAnalysis, S&P Global poll)
B67: FY2026 EPS - consensus mean, October 12, 2026 ($) | C67: 11.82 | D67: StockAnalysis (S&P Global poll), Oct 12 2026, as recorded that day: 52 analysts, range 11.38-12.43. The page did not say how the H1'26 marks were treated; the FY2027 growth rate it printed (+28.95%, row 34) works back to this figure. Its match with base-case core EPS is a coincidence, not a check of either. By Oct 16 the mean was 13.14 on a range of 11.38-20.65 (row 79), so analysts differ on whether to include the marks.
B68: FY2026 revenue - consensus | C68: 499290 | D68: 52 analysts, range 489,800-519,800
B69: FY2027 revenue - consensus | C69: 618790 | D69: StockAnalysis, Oct 12 2026. FY2027 EPS of 15.24 is from the same page's summary line (row 34).
B70: Provider forward P/E | C70: 25.56 | D70: S&P Global via StockAnalysis, close Oct 16 2026 at $340.59 (it was 26.18x on Oct 13 at $354.72). The basis is not stated; rows 81-83 show it matches neither FY2026 nor the FY2026-FY2027 average.
B71: Oct 12 consensus mean against the figure derived here (row 63) | C71: =C67/C63-1 -> -0.0025327428 | D71: DERIVED. A comparison of two figures, not a test of the provider's basis: row 63 is derived here from the September GAAP-basis consensus.
B72: Oct 12 consensus mean against base-case core EPS | C72: =C67/'DCF Base Model'!L48-1 -> 0.00011707917 | D72: DERIVED against the base engine ('DCF Base Model' L48), so it does not move with the scenario switch. A near-match of two independent figures, not a check of either.
B73: Oct 12 consensus pair: average of the FY2026 and FY2027 means ($) | C73: =AVERAGE(C67,C34) -> 13.53 | D73: DERIVED = equal-weighted average of the Oct 12 FY2026 mean (row 67) and FY2027 mean (row 34), one provider vintage. My own construction for a forward multiple; not the provider's next-four-quarter EPS, which it does not publish.
B74: Price / Oct 12 consensus pair | C74: ='11 Valuation'!C6/C73 -> 25.172949 | D74: ="DERIVED. "&TEXT(C74,"0.0")&"x against the provider's "&TEXT(C70,"0.0")&"x (row 70). The provider does not state its earnings basis, so the two are not like-for-like (rows 79-83). On Oct 13 the two came within 0.1% of each other, which is why the basis was once read as the next four quarters." -> DERIVED. 25.2x against the provider's 25.6x (row 70). The provider does not state its earnings basis, so the two are not like-for-like (rows 79-83). On Oct 13 the two came within 0.1% of each other, which is why the basis was once read as the next four quarters.
B75: FY2027 free cash flow - consensus | C75: -37003 | D75: MarketScreener, Oct 13 2026
B76: FY2027 capex - consensus | C76: 302822 | D76: MarketScreener, Oct 13 2026 (201,756 for FY2026 and 344,704 for FY2028). FactSet was about 257,000 as of Jul 22, 2026 (CNBC coverage of the Q2 results); no later FactSet figure found.
B78: PROVIDER CHECK - October 16, 2026 (StockAnalysis, S&P Global poll; page last updated Oct 16)
B79: FY2026 EPS - consensus mean, October 16, 2026 ($) | C79: 13.14 | D79: 52 analysts, range 11.38-20.65; +21.55% on FY2025's 10.81. The high end sits near the September GAAP-basis figure (20.60, which carries the H1'26 marks) and the low end near the ex-marks level, so the mean blends both treatments.
B80: FY2027 EPS - consensus mean, October 16, 2026 ($) | C80: 15.25 | D80: StockAnalysis, Oct 16 2026; +16.07% on the FY2026 mean. Range not shown on the free page.
B81: Provider forward P/E, October 16, 2026 | C81: 25.56 | D81: S&P Global via StockAnalysis statistics page, Oct 16 2026; the same figure as row 70. The basis is not stated.
B82: Share price for that forward P/E ($) | C82: 340.59 | D82: Close, Oct 16 2026 (StockAnalysis); also the reference price on 11 Valuation C6.
B83: EPS implied by the provider's forward P/E ($) | C83: =C82/C81 -> 13.325117 | D83: ="DERIVED. Against the FY2026 mean of "&TEXT(C79,"0.00")&" ("&TEXT(C82/C79,"0.0")&"x) and the FY2026-FY2027 average of "&TEXT(AVERAGE(C79,C80),"0.00")&" ("&TEXT(C82/AVERAGE(C79,C80),"0.0")&"x) it matches neither, so the provider's forward-earnings basis cannot be inferred from these figures." -> DERIVED. Against the FY2026 mean of 13.14 (25.9x) and the FY2026-FY2027 average of 14.20 (24.0x) it matches neither, so the provider's forward-earnings basis cannot be inferred from these figures.

Sheet 08 PPE and Depreciation
B2: 08 — PROPERTY & EQUIPMENT AND DEPRECIATION BASE
B3: $ millions. Policy from FY2025 10-K R31; asset detail from Q2 2026 10-Q R64.
B5: Asset class | C5: Dec 31, 2024 | D5: Dec 31, 2025 | E5: Jun 30, 2026 | F5: Change H1'26
B6: Technical infrastructure | C6: 141852 | D6: 203679 | E6: 247177 | F6: =E6-D6 -> 43498
B7: Office space | C7: 45403 | D7: 48348 | E7: 50635 | F7: =E7-D7 -> 2287
B8: Corporate and other assets | C8: 12574 | D8: 14463 | E8: 6498 | F8: =E8-D8 -> -7965
B9: ASSETS NOT YET IN SERVICE | C9: 50597 | D9: 78592 | E9: 122814 | F9: =E9-D9 -> 44222
B10: TOTAL GROSS PP&E | C10: =C6+C7+C8+C9 -> 250426 | D10: =D6+D7+D8+D9 -> 345082 | E10: =E6+E7+E8+E9 -> 427124 | F10: =E10-D10 -> 82042
B11: Less: accumulated depreciation | C11: -79390 | D11: -98485 | E11: -105912 | F11: =E11-D11 -> -7427
B12: NET PP&E | C12: =C10+C11 -> 171036 | D12: =D10+D11 -> 246597 | E12: =E10+E11 -> 321212 | F12: =E12-D12 -> 74615
B14: Estimated useful lives (unchanged; no change in accounting estimate disclosed)
B15: Asset class | C15: Estimated useful life
B16: Servers and network equipment | C16: generally 6 years
B17: Data center and office buildings | C17: 7 to 40 years
B18: Corporate and other assets | C18: 2 to 25 years
B19: Leasehold improvements | C19: shorter of remaining lease term or useful life
B20: Land | C20: not depreciated
B22: Depreciation ramp - illustrative only
B23: Metric | C23: Value | D23: Basis
B24: Assets not yet in service, Jun'26 | C24: =E9 -> 122814 | D24: filed
B25: As % of gross PP&E | C25: =C24/E10*100 -> 28.753711 | D25: DERIVED
B26: If placed in service on a 6-yr life: annual charge | C26: =C24/6 -> 20469 | D26: DERIVED - UPPER BOUND, see notes
B27: Current depreciation run rate, annualized | C27: ='09 Cash Flow'!G22*2 -> 27172 | D27: ="DERIVED = H1 "&TEXT('09 Cash Flow'!$G$22,"#,##0")&" x 2" -> DERIVED = H1 13,586 x 2
B28: Implied increase % | C28: =C26/C27*100 -> 75.331223 | D28: DERIVED - before any H2'26 or 2027 capex
B29: Implied H1 retirements / disposals | C29: ='09 Cash Flow'!G22+F11 -> 6159 | D29: ="DERIVED = "&TEXT('09 Cash Flow'!$G$22,"#,##0")&" expense less "&TEXT(-$F$11,"#,##0")&" accum-dep increase" -> DERIVED = 13,586 expense less 7,427 accum-dep increase
B31: Notes and caveats
B32: • POLICY, verbatim: "Property and equipment are stated at cost less accumulated depreciation. Depreciation commences once assets are ready for their intended use and is recorded using the straight-line method over the estimated useful lives of the assets, which we regularly evaluate for factors such as technological obsolescence and our planned use and utilization."
B33: • NO change in accounting estimate is disclosed in either the FY2025 10-K or the Q2 2026 10-Q. The 6-year server life set in the January 2023 revision (from 4 years) still stands.
B34: • TAIL RISK: the 'regularly evaluate ... technological obsolescence' language means a future shortening of the AI-vintage life would hit the P&L immediately.
B35: ="• KEY NUMBER: "&TEXT($C$24,"#,##0")&" sits in assets NOT YET IN SERVICE and is earning no depreciation. That is "&TEXT($C$25,"0.0")&"%"&" of gross PP&E, and it grew "&TEXT($F$9,"#,##0")&" in six months." -> • KEY NUMBER: 122,814 sits in assets NOT YET IN SERVICE and is earning no depreciation. That is 28.8% of gross PP&E, and it grew 44,222 in six months.
B36: ="• ILLUSTRATIVE RAMP: if that "&TEXT($C$24,"#,##0")&" were placed in service on the 6-year server life it alone would add "&"~"&TEXT($C$26,"#,##0")&"/yr"&", against a current run rate of "&"~"&TEXT($C$27,"#,##0")&" annualized (H1 "&TEXT('09 Cash Flow'!$G$22,"#,##0")&" doubled)"&". "&"A ~"&TEXT($C$28,"0")&"%"&" increase BEFORE any H2 2026 or 2027 capex. This is an UPPER BOUND on that tranche: the balance mixes 6-year servers with 7-40 year buildings, and the split is NOT disclosed." -> • ILLUSTRATIVE RAMP: if that 122,814 were placed in service on the 6-year server life it alone would add ~20,469/yr, against a current run rate of ~27,172 annualized (H1 13,586 doubled). A ~75% increase BEFORE any H2 2026 or 2027 capex. This is an UPPER BOUND on that tranche: the balance mixes 6-year servers with 7-40 year buildings, and the split is NOT disclosed.
B37: • THE SPLIT OF ASSETS-NOT-YET-IN-SERVICE BETWEEN SHORT- AND LONG-LIVED CLASSES IS THE SINGLE MOST SENSITIVE ASSUMPTION IN THE MODEL. Scenario it rather than picking a point estimate.
B38: ="• RETIREMENTS ARE MATERIAL: accumulated depreciation rose only "&TEXT(-$F$11,"#,##0")&" in H1 while depreciation expense was "&TEXT('09 Cash Flow'!$G$22,"#,##0")&", implying "&"~"&TEXT($C$29,"#,##0")&" of retirements and disposals. A roll-forward ignoring disposals will not tie." -> • RETIREMENTS ARE MATERIAL: accumulated depreciation rose only 7,427 in H1 while depreciation expense was 13,586, implying ~6,159 of retirements and disposals. A roll-forward ignoring disposals will not tie.
B39: ="• Corporate and other assets fell "&TEXT($D$8,"#,##0")&" -> "&TEXT($E$8,"#,##0")&", a "&TEXT(-$F$8/$D$8,"0%")&" drop"&" in six months. That is a reclassification or large disposal, not ordinary depreciation. Check the footnote; it may explain part of the retirement figure." -> • Corporate and other assets fell 14,463 -> 6,498, a 55% drop in six months. That is a reclassification or large disposal, not ordinary depreciation. Check the footnote; it may explain part of the retirement figure.
B40: ="• THE BUILD IS RECENT AND STEEP: technical infrastructure went "&TEXT($C$6,"#,##0")&" (Dec'24) to "&TEXT($D$6,"#,##0")&" (Dec'25) to "&TEXT($E$6,"#,##0")&" (Jun'26), +"&TEXT($E$6/$C$6-1,"0%")&" in eighteen months. Assets not yet in service went "&TEXT($C$9,"#,##0")&" to "&TEXT($D$9,"#,##0")&" to "&TEXT($E$9,"#,##0")&" over the same span, +"&TEXT($E$9/$C$9-1,"0%")&". The in-service base has not yet absorbed most of what has been bought." -> • THE BUILD IS RECENT AND STEEP: technical infrastructure went 141,852 (Dec'24) to 203,679 (Dec'25) to 247,177 (Jun'26), +74% in eighteen months. Assets not yet in service went 50,597 to 78,592 to 122,814 over the same span, +143%. The in-service base has not yet absorbed most of what has been bought.
B41: • Dec 2024 and Dec 2025 columns are from the FY2025 10-K note (R70); Jun 2026 from the Q2 10-Q (R64). The Dec 2025 gross total is 345,082 - the four classes sum to that and it ties to net PP&E after accumulated depreciation. An earlier reading recorded 345,182; that was a transcription error, corrected here.
B42: • Technical infrastructure is 247,177 gross, ~58% of the total. Blended against ~27,000 of current annual depreciation, the implied average life across the in-service base is well above 6 years, confirming buildings carry a meaningful share.
B43: • Recently issued standards not yet adopted, none affecting depreciation: ASU 2024-03 (expense disaggregation, 2027), ASU 2025-06 (internal-use software, 2028), ASU 2026-02 (environmental credits, 2028). ASU 2025-06 is worth tracking for software capitalization.

Sheet 09 Cash Flow
B2: 09 — CASH FLOW AND FREE CASH FLOW
B3: $ millions.
B5: Line item | C5: FY2023 | D5: FY2024 | E5: FY2025 | F5: TTM Mar'26 | G5: TTM Jun'26
B6: Net income | C6: ='01 Income Statement'!C18 -> 73795 | D6: ='01 Income Statement'!D18 -> 100118 | E6: ='01 Income Statement'!E18 -> 132170 | F6: ='01 Income Statement'!F18 -> 160208 | G6: ='01 Income Statement'!G18 -> 244205
B7: Depreciation & amortization | C7: 11946 | D7: 15311 | E7: 21136 | F7: 23131 | G7: =E7+G22-F22 -> 25237
B8: Stock-based compensation | C8: 22460 | D8: 22785 | E8: 24953 | F8: 26188 | G8: =E8+G23-F23 -> 28147
B9: Operating cash flow | C9: 101746 | D9: 125299 | E9: 164713 | F9: 174353 | G9: =E9+G19-F19 -> 185675
B10: Capital expenditures | C10: -32251 | D10: -52535 | E10: -91447 | F10: -109924 | G10: =E10+G20-F20 -> -132402
B11: FREE CASH FLOW | C11: =C9+C10 -> 69495 | D11: =D9+D10 -> 72764 | E11: =E9+E10 -> 73266 | F11: =F9+F10 -> 64429 | G11: =G9+G10 -> 53273
B12: FCF margin % | C12: =C11/'01 Income Statement'!C6*100 -> 22.607793 | D12: =D11/'01 Income Statement'!D6*100 -> 20.788645 | E12: =E11/'01 Income Statement'!E6*100 -> 18.18755 | F12: =F11/'01 Income Statement'!F6*100 -> 15.24954 | G12: =G11/'01 Income Statement'!G6*100 -> 11.948209
B13: Stock repurchases | C13: -61504 | D13: -62222 | E13: -45709 | F13: -30641
B14: Dividends paid | D14: -7363 | E14: -10049 | F14: -10157
B15: Acquisitions | C15: -495 | D15: -2931 | E15: -1592 | F15: -34873
B17: Quarterly detail around the inflection
B18: Line item | C18: Q2'25 | D18: Q1'26 | E18: Q2'26 | F18: H1'25 | G18: H1'26
B19: Operating cash flow | C19: 27747 | D19: =G19-E19 -> 45790 | E19: 39069 | F19: 63897 | G19: 84859
B20: Capital expenditures | C20: -22446 | D20: =G20-E20 -> -35674 | E20: -44924 | F20: -39643 | G20: -80598
B21: FREE CASH FLOW | C21: =C19+C20 -> 5301 | D21: =D19+D20 -> 10116 | E21: =E19+E20 -> -5855 | F21: =F19+F20 -> 24254 | G21: =G19+G20 -> 4261
B22: Depreciation | C22: 4998 | D22: =G22-E22 -> 6482 | E22: 7104 | F22: 9485 | G22: 13586
B23: Stock-based compensation | F23: 11514 | G23: 14708
B25: Notes and caveats
B26: ="• Q2 2026 is the FIRST NEGATIVE free-cash-flow quarter on record "&"("&TEXT($E$21,"#,##0")&")"&". H1'26 FCF of "&TEXT($G$21,"#,##0")&" is "&"down "&TEXT(1-$G$21/$F$21,"0%")&" from H1'25." -> • Q2 2026 is the FIRST NEGATIVE free-cash-flow quarter on record (-5,855). H1'26 FCF of 4,261 is down 82% from H1'25.
B27: ="• FCF trajectory: "&TEXT($C$11,"#,##0")&" -> "&TEXT($D$11,"#,##0")&" -> "&TEXT($E$11,"#,##0")&" -> "&TEXT($F$11,"#,##0")&" -> "&TEXT($G$11,"#,##0")&". FCF margin fell from "&TEXT($C$12,"0.0")&"% (FY2023) to "&TEXT($G$12,"0.0")&"%"&" (TTM Jun'26)." -> • FCF trajectory: 69,495 -> 72,764 -> 73,266 -> 64,429 -> 53,273. FCF margin fell from 22.6% (FY2023) to 11.9% (TTM Jun'26).
B28: • Q1'26 OCF, capex and depreciation are DERIVED as H1 less Q2. All cross-check against the TTM Mar'26 column.
B29: ="• TTM (Jun'26) D&A of "&TEXT($G$7,"#,##0")&" is DERIVED as FY2025 + H1'26 - H1'25, all on the cash-flow 'depreciation of property and equipment' basis. VERIFIED to the Q2 2026 10-Q: "&"H1'25 "&TEXT($F$22,"#,##0")&" and H1'26 "&TEXT($G$22,"#,##0")&" match the filed statement exactly. The earlier mixed-basis concern is resolved - the figure excludes amortisation of intangibles, so the label 'D&A' is strictly 'depreciation'." -> • TTM (Jun'26) D&A of 25,237 is DERIVED as FY2025 + H1'26 - H1'25, all on the cash-flow 'depreciation of property and equipment' basis. VERIFIED to the Q2 2026 10-Q: H1'25 9,485 and H1'26 13,586 match the filed statement exactly. The earlier mixed-basis concern is resolved - the figure excludes amortisation of intangibles, so the label 'D&A' is strictly 'depreciation'.
B30: ="• Capex guidance: FY2026 raised to 195,000-205,000 from 180,000-190,000. H1 capex was "&TEXT(-$G$20,"#,##0")&", so guidance implies 114,000-124,000 in H2 alone." -> • Capex guidance: FY2026 raised to 195,000-205,000 from 180,000-190,000. H1 capex was 80,598, so guidance implies 114,000-124,000 in H2 alone.
B31: • FY2027 capex guided 'significantly' higher, no dollar figure, and NO capex peak timeline was given on the Q2 call.
B32: • Buybacks suspended from Q1 2026. Dividends initiated Apr 2024, ~10,000/yr.
B33: ="• Stock-based compensation: "&"H1'25 "&TEXT($F$23,"#,##0")&" and H1'26 "&TEXT($G$23,"#,##0")&" are filed cash-flow figures from the Q2 2026 10-Q. TTM Jun'26 of "&TEXT($G$8,"#,##0")&" is derived on the same FY2025 + H1'26 - H1'25 convention. The 10-Q reports SBC only on a six-month basis in the cash flow statement, so no Q2'26 or Q1'26 split is available." -> • Stock-based compensation: H1'25 11,514 and H1'26 14,708 are filed cash-flow figures from the Q2 2026 10-Q. TTM Jun'26 of 28,147 is derived on the same FY2025 + H1'26 - H1'25 convention. The 10-Q reports SBC only on a six-month basis in the cash flow statement, so no Q2'26 or Q1'26 split is available.

Sheet 10 Guidance and Quotes
B2: 10 — CAPEX GUIDANCE TRAIL AND MANAGEMENT QUOTES
B3: Quotes verbatim from the Q2 2026 earnings call, July 22, 2026.
B5: Item | C5: Guidance
B6: FY2025 capex actual | C6: 91,447
B7: FY2026 capex - initial guide (Q4'25 call) | C7: 175,000 - 185,000
B8: FY2026 capex - raised (Q1'26 call, for Intersect) | C8: 180,000 - 190,000
B9: FY2026 capex - raised again (Q2'26 call) | C9: 195,000 - 205,000
B10: H1 2026 capex actual | C10: 80,598
B11: Implied H2 2026 capex | C11: 114,000 - 124,000
B12: FY2027 capex | C12: 'increase significantly', no dollar figure
B13: Capex peak timeline | C13: NONE GIVEN
B15: Verbatim quotes
B16: Speaker / topic | C16: Quote
B17: Ashkenazi - 2027 capex | C17: "we continue to expect our CapEx to increase significantly in 2027 and will provide more details at a later date."
B18: Ashkenazi - free cash flow | C18: "we expect the free cash flow will remain under pressure, driven by our investments in technical infrastructure, which enables us to capitalize on the AI opportunity and continue to drive attractive returns."
B19: Ashkenazi - depreciation | C19: "The significant increase in our investments in technical infrastructure will continue to put pressure on the P&L in the form of higher depreciation expense and related data center operations costs such as energy."
B20: Ashkenazi - Cloud margin | C20: Third-party capacity bridging will "create modest margin pressure in the near term." This is distinct from, and now alongside, the Wiz drag flagged in Q1.
B21: Ashkenazi - TPU revenue timing | C21: "We'll continue to ramp up throughout 2026, you'll see the vast majority of the revenue from that agreement come through in 2027."
B22: Ashkenazi - capex philosophy | C22: "we invest as long as we see an attractive return on that investment", taking a "multi-year view at what the needs are."
B23: Pichai - the opportunity | C23: "we've gotten more bullish on the opportunities ahead", characterising enterprise AI adoption as "very early."
B25: Notes and caveats
B26: • The 2026 raise to 195,000-205,000 was attributed to 'acceleration in delivery of capacity' - a SUPPLY-side reason (equipment arriving faster), not a demand re-rate. The guide went up because Alphabet CAN spend faster, not because it found more demand.
B27: • The FCF quote is the first time management has guided FCF pressure FORWARD as a stated expectation rather than describing it as an outcome. The base case cannot assume a near-term FCF inflection.
B28: • TPU note: the singular 'that agreement' means TPU revenue is concentrated in ONE large contract, not a diversified merchant-silicon business. Q2 cost of revenues also rose on 'inventory costs, primarily from the sales of TPU systems to customers', so TPU sales carry hardware COGS and will dilute consolidated gross margin as they scale.
B29: • WHAT THE ANALYSTS DID NOT ASK: nine analysts asked questions (Nowak/Morgan Stanley, Anmuth/JPMorgan, Sheridan/Goldman, Sandler/Barclays, Nathanson/MoffettNathanson, Shmulik/Bernstein, Josey/Citi, Gawrelski/Wells Fargo, Khajuria/Wolfe). Topics: GenAI ROIC sizing, 2027 capex budgeting, Gemini competitiveness, capital structure and cost of debt vs equity, TPU scaling and margins, third-party capacity, compute allocation, AI search monetization, Waymo structure.
B30: • REGULATORY, resolved: (1) Sept 2 2026 - Judge Brinkema DECLINED to order divestiture of AdX or DFP, rejecting DOJ's structural remedies for behavioural ones. With Mehta's Sept 2025 refusal on Chrome and Android, BOTH US structural break-up threats have now failed at district-court level. (2) July 23 2026 - the European Commission fined Google EUR 890M under the DMA (EUR 460M search self-preferencing + EUR 430M Play Store steering). That is roughly 2% of one quarter's operating income. Financially immaterial.
B31: • NEAR-TERM CATALYST: the DMA decision requires Google to end the conduct within 60 DAYS or face periodic penalties of up to 5% of average daily worldwide turnover. Sixty days from July 23 falls around SEPTEMBER 21, 2026. Check the compliance outcome.
B32: ="• NOT ONE asked about the "&TEXT('06 Core EPS Bridge'!$I$7,"#,##0")&" gain on equity securities, or that reported EPS of "&TEXT('06 Core EPS Bridge'!$I$13,"0.00")&" corresponds to "&"~"&TEXT('06 Core EPS Bridge'!$I$12,"0.00")&" of core earnings. The largest single-quarter investment gain in company history, "&TEXT('06 Core EPS Bridge'!$I$7/'06 Core EPS Bridge'!$I$6,"0%")&" of pretax"&" income, drew no question. That is direct evidence for the 'consensus gap' score on factor H." -> • NOT ONE asked about the 99,031 gain on equity securities, or that reported EPS of 9.11 corresponds to ~2.76 of core earnings. The largest single-quarter investment gain in company history, 71% of pretax income, drew no question. That is direct evidence for the 'consensus gap' score on factor H.

Sheet 11 Valuation
B2: 11 — VALUATION AT $340.59
B3: Prices at October 16, 2026; filed figures through Q2 2026. $ millions except per-share and ratios.
B5: Metric | C5: Value | D5: Basis
B6: Share price ($) | C6: 340.59 | D6: StockAnalysis, close Oct 16 2026 (4:00pm EDT)
B7: Market cap | C7: =C6*C9 -> 4165415.7
B8: Enterprise value (market cap less net cash and equity stakes outside net cash, plus preferred) | C8: =C7-'04 Balance Sheet'!G22+'05 Capital Structure'!C7-'04 Balance Sheet'!G54 -> 3915198.3 | D8: Operating EV: the equity stakes at '04 Balance Sheet'!G54 are non-operating, as in the 20 DCF bridge (changed 2026-10-13)
B9: Shares outstanding | C9: ='04 Balance Sheet'!G20 -> 12230
B11: Trailing P/E - REPORTED | C11: =C6/C22 -> 17.089313 | D11: ="on TTM EPS of "&TEXT($C$22,"0.00") -> on TTM EPS of 19.93
B12: Trailing P/E - CORE | C12: =C6/'06 Core EPS Bridge'!D17 -> 32.972614 | D12: ="on TTM core EPS of "&TEXT('06 Core EPS Bridge'!D17,"0.00")&" [DERIVED]" -> on TTM core EPS of 10.33 [DERIVED]
B13: Forward P/E - REPORTED | C13: =C6/'07 Consensus'!C6 -> 16.533495 | D13: ="on consensus FY26 EPS of "&TEXT('07 Consensus'!$C$6,"0.00")&" (GAAP basis, a dated September 8, 2026 reference)" -> on consensus FY26 EPS of 20.60 (GAAP basis, a dated September 8, 2026 reference)
B14: Forward P/E - CORE | C14: =C6/'06 Core EPS Bridge'!D18 -> 28.818094 | D14: ="on FY26E core EPS of "&TEXT('06 Core EPS Bridge'!$D$18,"0.00")&" (17 Model, "&'16 Scenarios'!$F$6&") [DERIVED]" -> on FY26E core EPS of 11.82 (17 Model, BASE CASE) [DERIVED]
B15: Forward P/E - Oct 12 consensus FY2026 mean | C15: =C6/'07 Consensus'!C67 -> 28.814721 | D15: ="on consensus FY26 EPS of "&TEXT('07 Consensus'!$C$67,"0.00")&" (Oct 12 2026 mean; the provider does not say how the marks are treated, and by Oct 16 the mean was "&TEXT('07 Consensus'!$C$79,"0.00")&"; '07 Consensus' rows 67 and 79)" -> on consensus FY26 EPS of 11.82 (Oct 12 2026 mean; the provider does not say how the marks are treated, and by Oct 16 the mean was 13.14; '07 Consensus' rows 67 and 79)
B16: Price / sales | C16: =C7/C20 -> 9.342304
B17: EV / EBITDA (TTM operating income + depreciation) | C17: =C8/('01 Income Statement'!G12+'09 Cash Flow'!G7) -> 22.648878
B18: Price / free cash flow | C18: =C7/C23 -> 78.189997 | D18: ="on TTM FCF of "&TEXT($C$23,"#,##0") -> on TTM FCF of 53,273
B20: TTM revenue | C20: ='01 Income Statement'!G6 -> 445866 | D20: filed-derived TTM
B21: TTM net income | C21: ='01 Income Statement'!G18 -> 244205 | D21: filed-derived TTM consolidated NI (the provider showed 244,120)
B22: TTM EPS ($) | C22: ='01 Income Statement'!G19 -> 19.93
B23: TTM free cash flow | C23: ='09 Cash Flow'!G11 -> 53273
B24: TTM operating cash flow | C24: ='09 Cash Flow'!G9 -> 185675
B25: TTM capital expenditures | C25: =-'09 Cash Flow'!G10 -> 132402
B26: Total cash | C26: ='04 Balance Sheet'!G8 -> 242474
B27: Total debt | C27: ='04 Balance Sheet'!G17 -> 102754
B29: Notes and caveats
B30: ="• THE CENTRAL FINDING: the trailing "&TEXT($C$11,"0.0")&"x"&" that makes GOOGL screen as the cheap mega-cap is built on TTM net income of "&TEXT($C$21,"#,##0")&", of which "&TEXT('17 Model'!$K$28,"#,##0")&" pretax ("&"about "&TEXT('17 Model'!$K$28*(1-'15 Assumptions'!$C$85),"#,##0")&" after tax, "&TEXT('17 Model'!$K$28*(1-'15 Assumptions'!$C$85)/$C$21,"0%")&" of net income"&") is non-operating mark-to-market on the equity-securities portfolio. On core earnings the same stock is at "&"about "&TEXT($C$12,"0.0")&"x"&"." -> • THE CENTRAL FINDING: the trailing 17.1x that makes GOOGL screen as the cheap mega-cap is built on TTM net income of 244,205, of which 148,982 pretax (about 117,696 after tax, 48% of net income) is non-operating mark-to-market on the equity-securities portfolio. On core earnings the same stock is at about 33.0x.
B31: • Rows marked CORE are DERIVED here, not provider or filed figures.
B32: Implied LT growth rate % (PEG denominator) | C32: n/a | D32: The provider does not disclose the growth rate behind its PEG. The 8.1% shown here before was backed out of the published 1.99 and was removed on 2026-10-13.
B33: PEG ratio | C33: 1.86 | D33: Provider figure: S&P Global via StockAnalysis, Oct 16 2026. Not derived here; the growth basis is not disclosed.
B35: NOPAT, TTM Jun'26 | C35: ='01 Income Statement'!G12*(1-'01 Income Statement'!G17/100) -> 120465.19 | D35: DERIVED = TTM operating income x (1 - TTM effective tax rate)
B36: Invested capital at Jun'26 | C36: ='04 Balance Sheet'!G19+'04 Balance Sheet'!G17-'04 Balance Sheet'!G8 -> 500760 | D36: DERIVED = total equity + total debt - cash & marketable securities
B37: Invested capital at FY2025 | C37: ='04 Balance Sheet'!E19+'04 Balance Sheet'!E17-'04 Balance Sheet'!E8 -> 339465 | D37: DERIVED = same build on the Dec 2025 column
B38: ROIC % - DERIVED on average invested capital | C38: =C35/AVERAGE(C36:C37)*100 -> 28.674506 | D38: DERIVED = NOPAT / average invested capital. Excess-cash treatment differs from the provider - see C39.
B39: ROIC % - provider basis (used in the comp table) | C39: 24.93 | D39: S&P Global via StockAnalysis, Sep 15 2026. Nets out EXCESS cash only, not all cash, so its invested capital is larger and it sits below the C38 build. Peer column uses this for like-for-like comparability.
B41: HISTORICAL P/E TREND — TWO PRICE CONVENTIONS
B42: Metric | C42: FY2023 | D42: FY2024 | E42: FY2025
B43: Year-end closing price ($) | C43: 138.46 | D43: 188.2 | E43: 312.39
B44: Annual-average closing price ($) | C44: 117.75 | D44: 162.56 | E44: 210.12
B45: Reported EPS ($) | C45: ='01 Income Statement'!C19 -> 5.8 | D45: ='01 Income Statement'!D19 -> 8.04 | E45: ='01 Income Statement'!E19 -> 10.81
B46: Core EPS ($) | C46: ='06 Core EPS Bridge'!C12 -> 5.7762396 | D46: ='06 Core EPS Bridge'!D12 -> 7.8078204 | E46: ='06 Core EPS Bridge'!E12 -> 9.2515781
B47: Year-end P/E — REPORTED | C47: =C43/C45 -> 23.872414 | D47: =D43/D45 -> 23.40796 | E47: =E43/E45 -> 28.898242
B48: Year-end P/E — CORE | C48: =C43/C46 -> 23.970612 | D48: =D43/D46 -> 24.104038 | E48: =E43/E46 -> 33.766131
B49: Average-price P/E — REPORTED | C49: =C44/C45 -> 20.301724 | D49: =D44/D45 -> 20.218905 | E49: =E44/E45 -> 19.437558
B50: Average-price P/E — CORE | C50: =C44/C46 -> 20.385235 | D50: =D44/D46 -> 20.820151 | E50: =E44/E46 -> 22.711801
B52: Method: year-end uses the final trading-day close; annual-average uses the arithmetic mean of daily closes. EPS matches each fiscal year.
B53: Source: StatMuse Money historical GOOGL pricing (2023–2025). Values are sourced inputs; P/E rows are live formulas.
B55: DCF MARKET INPUTS - sourced starter set
B56: Input | C56: Value | D56: Basis / date
B57: U.S. 10-year Treasury yield | C57: 0.0496 | D57: Latest available close Sep 21 2026; U.S. Treasury daily curve
B58: U.S. implied equity risk premium | C58: 0.0442 | D58: Damodaran July 2026 update
B59: GOOGL beta (5Y monthly) | C59: 1.23 | D59: Yahoo Finance, retrieved Sep 22 2026. Raw beta; the selector at 15 Assumptions C130 chooses which beta the DCF uses
B60: Cost of equity (CAPM) | C60: =C57+'15 Assumptions'!C137*C58 -> 0.097284095 | D60: Risk-free + beta used (15 Assumptions C137) x ERP
B61: Effective tax rate | C61: ='15 Assumptions'!C10 -> 0.1611201 | D61: Live link to model assumption
B62: Net cash at Jun'26 | C62: ='05 Capital Structure'!C25 -> 139720 | D62: Live link to '05 Capital Structure'
B63: Diluted shares | C63: ='05 Capital Structure'!C16 -> 12274 | D63: Live link to H1'26 weighted-average diluted shares
B64: Credit quality | C64: AA+ | D64: S&P issuer rating; stable outlook, Aug 6 2026
B65: Scope note | C65: Inputs staged; terminal growth and debt spread remain my choices.
B66: AA corporate option-adjusted spread | C66: 0.0059 | D66: ICE BofA AA index via FRED, Sep 10 2026
B67: Pre-tax cost of debt | C67: =C57+C66 -> 0.0555 | D67: 10-year Treasury plus AA spread
B68: Reference WACC | C68: =C7/(C7+'04 Balance Sheet'!G17)*C60+'04 Balance Sheet'!G17/(C7+'04 Balance Sheet'!G17)*C67*(1-C61) -> 0.096062887 | D68: Market-value weights; reference only for future FCFF DCF
B70: FORWARD EARNINGS BASIS AND RELATIVE VALUATION - added 2026-10-13, see 29 Change Log entry 65
B71: Metric | C71: Value | D71: Basis
B72: Oct 12 consensus pair: average of the FY2026 and FY2027 means ($) | C72: ='07 Consensus'!C73 -> 13.53 | D72: Equal-weighted average of the Oct 12 FY2026 and FY2027 consensus means ('07 Consensus' row 73). My own construction, not the provider's next-four-quarter EPS. Forward multiples go on a FY2026-FY2027 blend because FY2026 has under three months left.
B73: Model core EPS, average of FY2026E and FY2027E, base case ($) | C73: =AVERAGE('DCF Base Model'!L48,'DCF Base Model'!M48) -> 12.710659 | D73: DERIVED = equal-weighted average of FY2026E and FY2027E base-case core EPS (hidden base engine, so it does not move with the scenario switch). A blend of two fiscal years, not a quarterly next-four-quarter figure.
B74: Five-year average forward P/E | C74: =AVERAGE(26.61,17.89,21.69,22.05,29.41) -> 23.53 | D74: Average of the provider's forward P/E at fiscal year-ends 2021 to 2025 (26.61, 17.89, 21.69, 22.05, 29.41; StockAnalysis ratios page, Oct 13 2026). Replaced 24.8x on 2026-10-13: that figure was read from the provider in September and can no longer be found on its pages.
B75: Peer median forward P/E | C75: =MEDIAN('12 Peers'!F7:F11) -> 26.58 | D75: MSFT, META, AMZN, AAPL and NVDA on the provider basis (12 Peers column F)
B76: Peer median EV / EBITDA | C76: =MEDIAN('12 Peers'!G7:G11) -> 20.49 | D76: 12 Peers column G
B77: Value per share by method ($) | C77: On model EPS | D77: On the Oct 12 consensus pair
B78: Five-year average forward P/E x FY2026-FY2027 blended EPS | C78: =C74*C73 -> 299.08182 | D78: =C74*C72 -> 318.3609
B79: Peer median forward P/E x FY2026-FY2027 blended EPS | C79: =C75*C73 -> 337.84933 | D79: =C75*C72 -> 359.6274
B80: Peer median EV / EBITDA x TTM EBITDA, plus net cash and equity stakes, less preferred | C80: =(C76*('01 Income Statement'!G12+'09 Cash Flow'!G7)+'04 Balance Sheet'!G22+'04 Balance Sheet'!G54-'05 Capital Structure'!C7)/'05 Capital Structure'!C16 -> 308.96377 | D80: =C80 -> 308.96377
B81: Memo: equity stakes per share, which the P/E methods leave out ($) | C81: =('04 Balance Sheet'!G54+'04 Balance Sheet'!G40)/'05 Capital Structure'!C16 -> 17.643835 | D81: Stakes outside net cash plus marketable equity inside it; their gains are not in core earnings
B82: Memo: the two P/E multiples on FY2026E core EPS, the basis used before 2026-10-13 ($) | C82: =C74*'DCF Base Model'!L48 -> 278.09204 | D82: =C75*'DCF Base Model'!L48 -> 314.13882
B83: Row 82 puts the multiples on FY2026 alone, a fiscal year with under three months left. Rows 78-79 use a FY2026-FY2027 blend, which gives about 8% more on model earnings and 14% more on the consensus pair; the difference comes from choosing a higher, blended denominator. The provider's forward P/Es (rows 74-75) may rest on different earnings definitions from rows 72-73, so these values are approximate. C is the five-year average and D the peer median in row 82 only.
B85: DCF AT THE PRICE DATE, TWELVE-MONTH MODEL VALUE AND PERSONAL MODEL LABEL - added 2026-10-13, entry 65
C86: Base | D86: Best | E86: Worst
B87: Price date | C87: 46311
B88: Value per share as built: June 30 2026 valuation date, end-of-period discounting (20 DCF Valuation row 29) | C88: ='20 DCF Valuation'!C29 -> 193.52646 | D88: ='20 DCF Valuation'!D29 -> 348.27402 | E88: ='20 DCF Valuation'!E29 -> 77.246174
B89: With mid-period discounting of the forecast and fade cash flows (terminal value unchanged) | C89: =('20 DCF Valuation'!C16*(1+'20 DCF Valuation'!$H$18)^0.25+(SUM('20 DCF Valuation'!C17:C20)+'20 DCF Valuation'!C15)*(1+'20 DCF Valuation'!$H$18)^0.5+'20 DCF Valuation'!C21+SUM('20 DCF Valuation'!C23:C25))/'20 DCF Valuation'!C28 -> 197.14004 | D89: =('20 DCF Valuation'!D16*(1+'20 DCF Valuation'!$H$18)^0.25+(SUM('20 DCF Valuation'!D17:D20)+'20 DCF Valuation'!D15)*(1+'20 DCF Valuation'!$H$18)^0.5+'20 DCF Valuation'!D21+SUM('20 DCF Valuation'!D23:D25))/'20 DCF Valuation'!D28 -> 355.17545 | E89: =('20 DCF Valuation'!E16*(1+'20 DCF Valuation'!$H$18)^0.25+(SUM('20 DCF Valuation'!E17:E20)+'20 DCF Valuation'!E15)*(1+'20 DCF Valuation'!$H$18)^0.5+'20 DCF Valuation'!E21+SUM('20 DCF Valuation'!E23:E25))/'20 DCF Valuation'!E28 -> 78.384354
B90: Rolled from June 30 to the price date at the cost of equity: VALUE AT THE PRICE DATE | C90: =C89*(1+'20 DCF Valuation'!$H$11)^(($C$87-'20 DCF Valuation'!$H$25)/365) -> 202.63053 | D90: =D89*(1+'20 DCF Valuation'!$H$11)^(($C$87-'20 DCF Valuation'!$H$25)/365) -> 365.06733 | E90: =E89*(1+'20 DCF Valuation'!$H$11)^(($C$87-'20 DCF Valuation'!$H$25)/365) -> 80.567412
B91: Against the reference price | C91: =C90/$C$6-1 -> -0.40506025 | D91: =D90/$C$6-1 -> 0.071867434 | E91: =E90/$C$6-1 -> -0.76344751
B92: Dividends per share, next twelve months ($) | C92: 0.88
B93: TWELVE-MONTH MODEL VALUE: row 90 x (1 + cost of equity), less dividends | C93: =C90*(1+'20 DCF Valuation'!$H$11)-$C$92 -> 221.46326 | D93: =D90*(1+'20 DCF Valuation'!$H$11)-$C$92 -> 399.70257 | E93: =E90*(1+'20 DCF Valuation'!$H$11)-$C$92 -> 87.52534
B94: Model-implied twelve-month total return against the reference price | C94: =(C93+$C$92)/$C$6-1 -> -0.34718207 | D94: =(D93+$C$92)/$C$6-1 -> 0.17614309 | E94: =(E93+$C$92)/$C$6-1 -> -0.74043472
B95: Personal model label (Buy above +15%, Sell below -10%, otherwise Hold); not a trading recommendation | C95: =IF(C94>0.15,"BUY",IF(C94<-0.1,"SELL","HOLD")) -> SELL | D95: =IF(D94>0.15,"BUY",IF(D94<-0.1,"SELL","HOLD")) -> BUY | E95: =IF(E94>0.15,"BUY",IF(E94<-0.1,"SELL","HOLD")) -> SELL
B96: STATIC: value at the price date with the FY2030E margin held (15 Assumptions C91 = 0) | C96: 253.27 | D96: 411.47 | E96: 96.06
B97: Return on the whole capital base implied in the terminal year | C97: ='15 Assumptions'!C97 -> 0.15 | D97: ='15 Assumptions'!D97 -> 0.25 | E97: ='15 Assumptions'!E97 -> 0.1
B98: TTM ROIC on average invested capital (row 38) | C98: =C38/100 -> 0.28674506
B99: The model's row 29 values cash flows at June 30 2026 as if each arrived at period end; the price is three and a half months later. Rows 89-90 put the value on the price's date without rebuilding the DCF grids. Row 97: in a steady state, net reinvestment of growth / return x NOPAT makes the return on all capital equal the return on new capital, so the derived terminal margin carries that return for the whole business, against row 98 today. Row 96 is the value if the FY2030E margin is held instead.
B100: RECONCILIATION: FROM THE BASE DCF TO THE MULTIPLES AND THE PRICE - base case, $ per share; static rows generated 2026-10-18
B101: Step (each static step is added to the ones above it) | C101: Value / share | D101: Against the price
B102: Base DCF as built (row 88) | C102: =C88 -> 193.52646 | D102: =C102/$C$6-1 -> -0.43179054
B103: Mid-period discounting and the roll to the price date (row 90) | C103: =C90 -> 202.63053 | D103: =C103/$C$6-1 -> -0.40506025
B104: STATIC + FY2030E operating margin held to FY2040E (C91 = 0) | C104: 253.27 | D104: =C104/$C$6-1 -> -0.25637864
B105: STATIC + return on new capital of 25% after FY2030E (base 15%) | C105: 272.16 | D105: =C105/$C$6-1 -> -0.20091606
B106: STATIC + Cloud revenue added of 35 cents per $ of prior-year capex (base 30) | C106: 304.98 | D106: =C106/$C$6-1 -> -0.10455386
B107: STATIC + pre-ramp margin expansion of 1.0pp a year (base 0.5pp) | C107: 328.85 | D107: =C107/$C$6-1 -> -0.034469597
B108: Relative valuation, lowest method (rows 78-80) | C108: =MIN(C78:D80) -> 299.08182 | D108: =C108/$C$6-1 -> -0.12187141
B109: Relative valuation, highest method (rows 78-80) | C109: =MAX(C78:D80) -> 359.6274 | D109: =C109/$C$6-1 -> 0.055895358
B110: Reference price | C110: =C6 -> 340.59 | D110: =C110/$C$6-1 -> 0
B111: Static rows were generated with as-built base value ($): | C111: 193.5265 | D111: =IF(ABS(C111-C88)<0.005,"CURRENT","STALE: rerun the sensitivities") -> CURRENT
...

Sheet 12 Peers
B2: 12 — MEGA-CAP COMPARISON
B3: October 16, 2026 (close, StockAnalysis); TTM cash-flow and ROIC columns as of the latest filings. $ millions except per-share and ratios.
B5: Company | C5: Price ($) | D5: Mkt cap | E5: Trailing P/E | F5: Fwd P/E | G5: EV/EBITDA | H5: PEG | I5: P/FCF | J5: TTM FCF | K5: TTM capex | L5: ROIC %
B6: GOOGL | C6: ='11 Valuation'!C6 -> 340.59 | D6: ='11 Valuation'!C7 -> 4165415.7 | E6: ='11 Valuation'!C11 -> 17.089313 | F6: ='07 Consensus'!C70 -> 25.56 | G6: ='11 Valuation'!C17 -> 22.648878 | H6: ='11 Valuation'!C33 -> 1.86 | I6: ='11 Valuation'!C18 -> 78.189997 | J6: ='11 Valuation'!C23 -> 53273 | K6: ='11 Valuation'!C25 -> 132402 | L6: ='11 Valuation'!C39 -> 24.93
B7: MSFT | C7: 529.05 | D7: 3930000 | E7: 29.47 | F7: 26.75 | G7: 20.49 | H7: 1.7 | I7: 58.65 | J7: 66990 | K7: 115950 | L7: 26.18
B8: META | C8: 709.33 | D8: 1810000 | E8: 26.73 | F8: 22.19 | G8: 16.68 | H8: 1.13 | I8: 44.1 | J8: 40980 | K8: 89330 | L8: 25.4
B9: AMZN | C9: 250 | D9: 2700000 | E9: 20.1 | F9: 26.58 | G9: 16.73 | H9: 1.28 | J9: -7604 | K9: 169007 | L9: 11.94
B10: AAPL | C10: 343.46 | D10: 5010000 | E10: 39.4 | F10: 37.34 | G10: 29.47 | H10: 3.36 | I10: 36.67 | J10: 136680 | K10: 10040 | L10: 101.57
B11: NVDA | C11: 214.13 | D11: 5170000 | E11: 27.08 | F11: 17.7 | G11: 25.57 | H11: 0.35 | I11: 40.71 | J11: 127010 | K11: 7350 | L11: 92.03
B13: Relative performance since the June 26 close: eleven weeks to Sep 10, and to Oct 16
B14: Company | C14: 46199 | D14: Sep 10, 2026 | E14: % change | F14: 46311 | G14: % change since Jun 26
B15: GOOGL | C15: 337.39 | D15: 332.13 | E15: =(D15/C15-1)*100 -> -1.5590266 | F15: =C6 -> 340.59 | G15: =(F15/C15-1)*100 -> 0.94845727
B16: MSFT | C16: 372.97 | D16: 490.83 | E16: =(D16/C16-1)*100 -> 31.600397 | F16: =C7 -> 529.05 | G16: =(F16/C16-1)*100 -> 41.84787
B17: META | C17: 550.25 | D17: 647.48 | E17: =(D17/C17-1)*100 -> 17.67015 | F17: =C8 -> 709.33 | G17: =(F17/C17-1)*100 -> 28.910495
B18: AAPL | C18: 283.78 | D18: 324.12 | E18: =(D18/C18-1)*100 -> 14.215237 | F18: =C10 -> 343.46 | G18: =(F18/C18-1)*100 -> 21.030376
B19: NVDA | C19: 192.53 | D19: 217.95 | E19: =(D19/C19-1)*100 -> 13.203137 | F19: =C11 -> 214.13 | G19: =(F19/C19-1)*100 -> 11.219031
B20: AMZN | C20: 232.69 | D20: 252.05 | E20: =(D20/C20-1)*100 -> 8.3200825 | F20: =C9 -> 250 | G20: =(F20/C20-1)*100 -> 7.439082
B22: Notes and caveats
B23: • GOOGL forward P/E (F6) is the provider's figure from '07 Consensus' row 70, on the same basis as the five peers. GOOGL ROIC is the provider's (S&P Global via StockAnalysis, Sep 15 2026) and PEG the provider's of Oct 16 2026; both link to '11 Valuation' rows 32-39.
B24: ="• READ 1: THE REPORTED P/E IS NOT A LIKE-FOR-LIKE COMPARISON, FOR ALPHABET OR FOR AMAZON. On trailing reported earnings GOOGL ("&TEXT($E$6,"0.0")&"x) and AMZN ("&TEXT($E$9,"0.0")&"x) screen as the two cheapest names, and both carry large non-operating income: "&TEXT($E$32,"0")&"% of Alphabet's pretax income and "&TEXT($E$35,"0")&"% of Amazon's, against "&TEXT(MAX($E$33,$E$34,$E$36,$E$37),"0")&"% or less for the other four. "&"Measured the same way for all six, on market value to after-tax operating income (rows 32-37), GOOGL is at "&TEXT($H$32,"0.0")&"x, "&CHOOSE(RANK($H$32,$H$32:$H$37),"the dearest","the second dearest","the third dearest","fourth","fifth","the cheapest")&" of the six (AAPL "&TEXT($H$36,"0.0")&"x, AMZN "&TEXT($H$35,"0.0")&"x, NVDA "&TEXT($H$37,"0.0")&"x, MSFT "&TEXT($H$33,"0.0")&"x, META "&TEXT($H$34,"0.0")&"x). "&"On the provider's forward P/E (its earnings basis is not stated), GOOGL is at "&TEXT($F$6,"0.0")&"x against a peer median of "&TEXT(MEDIAN($F$7:$F$11),"0.0")&"x." -> • READ 1: THE REPORTED P/E IS NOT A LIKE-FOR-LIKE COMPARISON, FOR ALPHABET OR FOR AMAZON. On trailing reported earnings GOOGL (17.1x) and AMZN (20.1x) screen as the two cheapest names, and both carry large non-operating income: 51% of Alphabet's pretax income and 46% of Amazon's, against 14% or less for the other four. Measured the same way for all six, on market value to after-tax operating income (rows 32-37), GOOGL is at 34.6x, the third dearest of the six (AAPL 39.1x, AMZN 37.2x, NVDA 31.2x, MSFT 31.4x, META 26.8x). On the provider's forward P/E (its earnings basis is not stated), GOOGL is at 25.6x against a peer median of 26.6x.
B25: ="• READ 2: negative free cash flow is a COHORT FEATURE, not an Alphabet failure. Amazon's TTM FCF is "&"NEGATIVE "&TEXT(-$J$9,"#,##0")&" on "&TEXT($K$9,"#,##0")&" of capex, worse than Alphabet's "&"positive "&TEXT($J$6,"#,##0")&". A bear case has to argue Alphabet's conversion is worse than the cohort's, not merely that it is falling."&" (Amazon on its own net-capex basis, Q2 8-K: OCF 161,403 less net capex 169,007; corrected 2026-10-07 from gross purchases of 173,030.)" -> • READ 2: negative free cash flow is a COHORT FEATURE, not an Alphabet failure. Amazon's TTM FCF is NEGATIVE 7,604 on 169,007 of capex, worse than Alphabet's positive 53,273. A bear case has to argue Alphabet's conversion is worse than the cohort's, not merely that it is falling. (Amazon on its own net-capex basis, Q2 8-K: OCF 161,403 less net capex 169,007; corrected 2026-10-07 from gross purchases of 173,030.)
B26: ="• READ 3: the capital-light names hold the cash. NVDA generates "&TEXT($J$11,"#,##0")&" of FCF on "&TEXT($K$11,"#,##0")&" of capex; "&"AAPL "&TEXT($J$10,"#,##0")&" on "&TEXT($K$10,"#,##0")&". NVDA is now the largest company at "&"$"&TEXT($D$11/1000000,"0.00")&"T"&". The hyperscaler cohort is transferring free cash flow to its suppliers." -> • READ 3: the capital-light names hold the cash. NVDA generates 127,010 of FCF on 7,350 of capex; AAPL 136,680 on 10,040. NVDA is now the largest company at $5.17T. The hyperscaler cohort is transferring free cash flow to its suppliers.
B27: ="• READ 4: over the eleven weeks to Sep 10, GOOGL was the ONLY mega-cap to fall, against a quarter that delivered "&"+"&TEXT('02 Quarterly'!$E$23,"0")&"% revenue and +"&TEXT('02 Quarterly'!$E$28,"0")&"% operating income"&"." -> • READ 4: over the eleven weeks to Sep 10, GOOGL was the ONLY mega-cap to fall, against a quarter that delivered +24% revenue and +30% operating income.
B28: ="• READ 5: ROIC on the provider's basis is "&TEXT($L$6,"0.00")&"%, below MSFT ("&TEXT($L$7,"0.00")&") and META ("&TEXT($L$8,"0.00")&") as the capex build arrives in the denominator, while AAPL ("&TEXT($L$10,"0.00")&") and NVDA ("&TEXT($L$11,"0.00")&") operate on a fraction of the invested capital. The PEG of "&TEXT($H$6,"0.00")&" is the provider's figure. What the incremental capital earns is the question the model has to answer." -> • READ 5: ROIC on the provider's basis is 24.93%, below MSFT (26.18) and META (25.40) as the capex build arrives in the denominator, while AAPL (101.57) and NVDA (92.03) operate on a fraction of the invested capital. The PEG of 1.86 is the provider's figure. What the incremental capital earns is the question the model has to answer.
B30: LIKE-FOR-LIKE: MARKET VALUE TO AFTER-TAX OPERATING INCOME - non-operating income removed from every name (added 2026-10-13, entry 65)
B31: Company | C31: Operating income, TTM | D31: Pretax income, TTM | E31: Non-operating share of pretax % | F31: Effective tax rate % | G31: After-tax operating income | H31: Market cap / after-tax operating income | I31: EV / EBIT (provider)
B32: GOOGL | C32: ='01 Income Statement'!G12 -> 147628 | D32: ='01 Income Statement'!G15 -> 299269 | E32: =(D32-C32)/D32*100 -> 50.670467 | F32: ='01 Income Statement'!G17 -> 18.3995 | G32: =C32*(1-F32/100) -> 120465.19 | H32: =D6/G32 -> 34.577755 | I32: 27.39
B33: MSFT | C33: 155240 | D33: 165930 | E33: =(D33-C33)/D33*100 -> 6.4424757 | F33: 19.4 | G33: =C33*(1-F33/100) -> 125123.44 | H33: =D7/G33 -> 31.408983 | I33: 25.64
B34: META | C34: 86930 | D34: 87520 | E34: =(D34-C34)/D34*100 -> 0.67413163 | F34: 22.2 | G34: =C34*(1-F34/100) -> 67631.54 | H34: =D8/G34 -> 26.762661 | I34: 21.04
B35: AMZN | C35: 93710 | D35: 174900 | E35: =(D35-C35)/D35*100 -> 46.420812 | F35: 22.65 | G35: =C35*(1-F35/100) -> 72484.685 | H35: =D9/G35 -> 37.249248 | I35: 30.15
B36: AAPL | C36: 154860 | D36: 155910 | E36: =(D36-C36)/D36*100 -> 0.67346546 | F36: 17.3 | G36: =C36*(1-F36/100) -> 128069.22 | H36: =D10/G36 -> 39.11947 | I36: 31.97
B37: NVDA | C37: 197580 | D37: 229740 | E37: =(D37-C37)/D37*100 -> 13.998433 | F37: 16.05 | G37: =C37*(1-F37/100) -> 165868.41 | H37: =D11/G37 -> 31.169287 | I37: 26.05
B38: Source: StockAnalysis statistics pages (S&P Global data), Oct 16 2026, trailing twelve months to each company's latest reported quarter; GOOGL from the filed statements on sheet 01. Market caps are row 6-11. Column H divides market value by operating income after tax at each company's own effective rate, so interest, investment gains and equity-method results are excluded for all six. Checked 2026-10-13 against each peer's SEC XBRL filings (operating income and pretax income, trailing twelve months): all five tie to the provider within 0.3%. Amazon's filed non-operating income is 81,754 over the period (Q2 2026 Form 10-Q).

Sheet 13 EPIC Ranking
B2: 13 — EPIC RANKING
B3: Scores 1-5 per dimension. Critical factors are the top three. EPIC = Exceeds materiality / Probably occurs / I can forecast / Consensus gap - full explanation at row 28 below.
B5: Factor | C5: Exceeds materiality | D5: Probably occurs | E5: I can forecast | F5: Consensus gap | G5: TOTAL | H5: vs prior
B6: A. Valuation / the multiple | C6: 5 | D6: 5 | E6: 4 | F6: 3 | G6: =SUM(C6:F6) -> 17 | H6: +1
B7: B. Cloud growth & backlog to margin | C7: 5 | D7: 5 | E7: 4 | F7: 3 | G7: =SUM(C7:F7) -> 17 | H7: 0
B8: C. Capex / AI-infra ROI & FCF conversion | C8: 5 | D8: 5 | E8: 4 | F8: 3 | G8: =SUM(C8:F8) -> 17 | H8: -1
B9: D. Margins / depreciation | C9: 4 | D9: 5 | E9: 4 | F9: 3 | G9: =SUM(C9:F9) -> 16 | H9: +1
B10: E. Search / ad durability vs AI | C10: 5 | D10: 3 | E10: 3 | F10: 4 | G10: =SUM(C10:F10) -> 15 | H10: 0
B11: F. Gemini / AI model position | C11: 4 | D11: 4 | E11: 2 | F11: 3 | G11: =SUM(C11:F11) -> 13 | H11: 0
B12: G. Capital allocation | C12: 3 | D12: 4 | E12: 3 | F12: 3 | G12: =SUM(C12:F12) -> 13 | H12: +1
B13: H. Antitrust / regulatory | C13: 3 | D13: 4 | E13: 2 | F13: 2 | G13: =SUM(C13:F13) -> 11 | H13: 0
B15: Notes and caveats
B16: • Re-ranked 2026-09-10 after Q2 2026. Scores are 1-5 on each dimension and are reviewed periodically as new evidence arrives.
B17: ="A rises 16 -> "&$G$6&" (re-scored 2026-09-21; was 19). 'I can forecast' 3 -> 4 because normalising is arithmetic, not prediction. 'Consensus gap' back to 3: "&"consensus FY2027 EPS of "&TEXT('07 Consensus'!$C$34,"0.00")&" ("&TEXT('07 Consensus'!$C$34/'07 Consensus'!$C$6-1,"0%")&")"&" is consistent with the marks not being carried into FY2027, the FY2026 figure is core earnings plus H1 marks already booked, and the earlier '47 up, 0 down' revisions claim was not supported (FY2026: 4 up, 1 down). What survives: the he"&"adline "&TEXT('11 Valuation'!$C$13,"0.0")&"x forward P/E on the September GAAP consensus can distort screening-based comparisons using FY2026 reported EPS." -> A rises 16 -> 17 (re-scored 2026-09-21; was 19). 'I can forecast' 3 -> 4 because normalising is arithmetic, not prediction. 'Consensus gap' back to 3: consensus FY2027 EPS of 15.24 (-26%) is consistent with the marks not being carried into FY2027, the FY2026 figure is core earnings plus H1 marks already booked, and the earlier '47 up, 0 down' revisions claim was not supported (FY2026: 4 up, 1 down). What survives: the headline 16.5x forward P/E on the September GAAP consensus can distort screening-based comparisons using FY2026 reported EPS.
B18: • DISPERSION NOTE: narrowing reflects booked marks that every analyst must include; it does not independently support a high consensus-gap score. The current assessment is in row 17.
B19: ="• THE SEPTEMBER CONSENSUS IS STRUCK ON REPORTED EPS: the +90.54% FY2026 growth rate implies a base of 20.60/1.9054 = 10.81, which is the reported FY2025 EPS."&" That fits a GAAP basis; it does not show how each analyst treats the marks. Core growth over the same period is +"&TEXT(('06 Core EPS Bridge'!$D$18/'06 Core EPS Bridge'!$E$12-1)*100,"0.0")&"% (17 Model). A +90.5% headline against that core growth is the gap the reported multiple misreads." -> • THE SEPTEMBER CONSENSUS IS STRUCK ON REPORTED EPS: the +90.54% FY2026 growth rate implies a base of 20.60/1.9054 = 10.81, which is the reported FY2025 EPS. That fits a GAAP basis; it does not show how each analyst treats the marks. Core growth over the same period is +27.7% (17 Model). A +90.5% headline against that core growth is the gap the reported multiple misreads.
B20: ="• CORROBORATING EVIDENCE FROM THE Q2 CALL: nine sell-side analysts asked questions and NOT ONE asked about the "&TEXT('06 Core EPS Bridge'!$I$7,"#,##0")&" gain on equity securities or the gap between "&TEXT('06 Core EPS Bridge'!$I$13,"0.00")&" reported and "&"~"&TEXT('06 Core EPS Bridge'!$I$12,"0.00")&" core EPS. See '10 Guidance and Quotes'." -> • CORROBORATING EVIDENCE FROM THE Q2 CALL: nine sell-side analysts asked questions and NOT ONE asked about the 99,031 gain on equity securities or the gap between 9.11 reported and ~2.76 core EPS. See '10 Guidance and Quotes'.
B21: ="• "&"C falls 18 -> "&$G$8&". Still material and now actually occurring, but 'consensus gap' 4 -> 3 because the FCF decline ran in Semafor, Forbes, CNBC and Seeking Alpha within a week. The raw fact is crowded; the TIMING i"&"s not." -> • C falls 18 -> 17. Still material and now actually occurring, but 'consensus gap' 4 -> 3 because the FCF decline ran in Semafor, Forbes, CNBC and Seeking Alpha within a week. The raw fact is crowded; the TIMING is not.
B22: ="• "&"B holds at "&$G$7&" on offsetting moves: 'probably occurs' 4 -> 5 "&"(Cloud +"&TEXT('03 Segments'!$F$33,"0")&"%)"&", 'consensus gap' 4 -> 3 (visible to everyone)." -> • B holds at 17 on offsetting moves: 'probably occurs' 4 -> 5 (Cloud +82%), 'consensus gap' 4 -> 3 (visible to everyone).
B23: ="H rises 9 -> "&$G$13&" (re-scored 2026-09-21). The US structural threats failed (Brinkema declined AdX/DFP divestiture on Sep 2 2026; Mehta refused Chrome/Android in Sep 2025), but the Jul 16 2026 EU DMA specification deci"&"sions are binding and dated: Google must share ranking, query, click and view data with rival engines and AI chatbots from Jan 2027, and open Android to third-party AI assistants from Jul 2027. 'Excee"&"ds materiality' 2 -> 3 and 'Probably occurs' 2 -> 4; 'I can forecast' 3 -> 2 because the revenue effect is hard to size. Still not a critical factor, but no longer closed." -> H rises 9 -> 11 (re-scored 2026-09-21). The US structural threats failed (Brinkema declined AdX/DFP divestiture on Sep 2 2026; Mehta refused Chrome/Android in Sep 2025), but the Jul 16 2026 EU DMA specification decisions are binding and dated: Google must share ranking, query, click and view data with rival engines and AI chatbots from Jan 2027, and open Android to third-party AI assistants from Jul 2027. 'Exceeds materiality' 2 -> 3 and 'Probably occurs' 2 -> 4; 'I can forecast' 3 -> 2 because the revenue effect is hard to size. Still not a critical factor, but no longer closed.
B24: ="• "&"F holds at "&$G$11&" but as a RISING WATCH ITEM. Jeff Dean left after 27 years, with Sanjay Ghemawat, Oriol Vinyals and Quoc Le; Demis Hassabis moved to chairman of DeepMind. Forecastability stays at 2, which is why it d"&"oes not become a pillar despite the deterioration." -> • F holds at 13 but as a RISING WATCH ITEM. Jeff Dean left after 27 years, with Sanjay Ghemawat, Oriol Vinyals and Quoc Le; Demis Hassabis moved to chairman of DeepMind. Forecastability stays at 2, which is why it does not become a pillar despite the deterioration.
B25: ="G rises to "&$G$12&" on the confirmed "&TEXT('05 Capital Structure'!$C$7,"#,##0")&" preferred (~"&TEXT('05 Capital Structure'!$C$24,"#,##0")&"/yr"&" of dividends), the 40,000 ATM authorised and undrawn at Jun 30 (corrected 2026-09-21; the 30,400 figure was the separate June common offering), and suspended buybacks. A real EPS-bridge input now." -> G rises to 13 on the confirmed 19,000 preferred (~1,188/yr of dividends), the 40,000 ATM authorised and undrawn at Jun 30 (corrected 2026-09-21; the 30,400 figure was the separate June common offering), and suspended buybacks. A real EPS-bridge input now.
B26: ="CRITICAL FACTORS: "&IF(AND($G$6=$G$7,$G$7=$G$8),"A, B and C now tie at "&$G$6&".","A scores "&$G$6&", B "&$G$7&" and C "&$G$8&".")&" (1) A - valuation via earnings quality; (2) B - Cloud growth and backlog conversion; (3) C - capex to depreciation to FCF timing, where the live forecast gap sits: "&"consensus FY2027 operating margin is "&TEXT('07 Consensus'!$C$39,"0.0")&"%"&" (07 Consensus row 39) "&"against "&TEXT('DCF Base Model'!$M$25*100,"0.0")&"% in the base case"&". NAMED DOWNSIDE RISK: E - Search durability." -> CRITICAL FACTORS: A, B and C now tie at 17. (1) A - valuation via earnings quality; (2) B - Cloud growth and backlog conversion; (3) C - capex to depreciation to FCF timing, where the live forecast gap sits: consensus FY2027 operating margin is 35.3% (07 Consensus row 39) against 33.5% in the base case. NAMED DOWNSIDE RISK: E - Search durability.
B27: • FaVeS DIRECTION IS DELIBERATELY NOT RE-LOCKED. What is locked is the INSIGHT: consensus is anchored to an earnings base roughly half non-operating marks. That insight is directionally neutral. The DCF produces the direction. Locking the lean first and modelling toward it is the confirmation-bias failure mode the process checklist exists to catch - and this project has already been through one reversal.
B28: What EPIC is and how to read this sheet
B29: The acronym | C29: EPIC scores each research factor on four dimensions, one letter each. A factor only earns attention if it does well on all four - a high score on one dimension alone is not enough.
B30: E - Exceeds materiality | C30: If this factor moves, does it move the valuation enough to matter? A 5 means it could re-rate the stock on its own; a 1 means it is noise even if true.
B31: P - Probably occurs | C31: How likely is it to actually happen, on a horizon that matters? A 5 means it is already occurring and visible in the filings; a 1 means it is speculative.
B32: I - I can forecast | C32: Can I model it with the evidence in this pack? A 5 means the work is arithmetic on filed figures; a 1 means it depends on something unknowable, like a court ruling.
B33: C - Consensus gap | C33: How large is the difference between the evidence-based view and the market or consensus view? A 5 requires a clear, well-supported gap; a 1 indicates broad alignment.
B34: Why the fourth dimension decides | C34: E, P and I can all score 5 on a fact every analyst already knows - that is agreement, not opportunity. C is what separates a good insight from a tradable one, and it is the easiest score to flatter, so it carries the highest burden of proof here.
B35: Scoring and the TOTAL | C35: Each dimension is 1-5, so TOTAL runs 4 to 20. Column G is now a live =SUM(C:F) formula - change a score and the total follows. Column H shows the move against the prior ranking.
B36: What 'critical factor' means | C36: {="The top three by TOTAL are the critical factors and are what the model is built to answer: "&LEFT(INDEX($B$6:$B$13,_xlfn.AGGREGATE(15,6,(ROW($G$6:$G$13)-ROW($G$6)+1)/(($G$6:$G$13-ROW($G$6:$G$13)/1000)=_xlfn.AGGREGATE(14,6,$G$6:$G$13-ROW($G$6:$G$13)/1000,1)),1)),1)&" ("&INDEX($G$6:$G$13,_xlfn.AGGREGATE(15,6,(ROW($G$6:$G$13)-ROW($G$6)+1)/(($G$6:$G$13-ROW($G$6:$G$13)/1000)=_xlfn.AGGREGATE(14,6,$G$6:$G$13-ROW($G$6:$G$13)/1000,1)),1))&")"&", "&LEFT(INDEX($B$6:$B$13,_xlfn.AGGREGATE(15,6,(ROW($G$6:$G$13)-ROW($G$6)+1)/(($G$6:$G$13-ROW($G$6:$G$13)/1000)=_xlfn.AGGREGATE(14,6,$G$6:$G$13-ROW($G$6:$G$13)/1000,2)),1)),1)&" ("&INDEX($G$6:$G$13,_xlfn.AGGREGATE(15,6,(ROW($G$6:$G$13)-ROW($G$6)+1)/(($G$6:$G$13-ROW($G$6:$G$13)/1000)=_xlfn.AGGREGATE(14,6,$G$6:$G$13-ROW($G$6:$G$13)/1000,2)),1))&")"&" and "&LEFT(INDEX($B$6:$B$13,_xlfn.AGGREGATE(15,6,(ROW($G$6:$G$13)-ROW($G$6)+1)/(($G$6:$G$13-ROW($G$6:$G$13)/1000)=_xlfn.AGGREGATE(14,6,$G$6:$G$13-ROW($G$6:$G$13)/1000,3)),1)),1)&" ("&INDEX($G$6:$G$13,_xlfn.AGGREGATE(15,6,(ROW($G$6:$G$13)-ROW($G$6)+1)/(($G$6:$G$13-ROW($G$6:$G$13)/1000)=_xlfn.AGGREGATE(14,6,$G$6:$G$13-ROW($G$6:$G$13)/1000,3)),1))&")"&". Generated live from column G; ties are listed in row order. See the note at row 26."} -> The top three by TOTAL are the critical factors and are what the model is built to answer: A (17), B (17) and C (17). Generated live from column G; ties are listed in row order. See the note at row 26.
B37: Row order is rank order | C37: Rows 6-13 are in rank order and lettered A to H by rank (re-lettered 2026-10-16, entry 73). Until then the letters followed the order the factors were first listed in June; old to new: H to A, B and C unchanged, E to D, A to E, G to F, F to G, D to H. Dated notes, the change log and the markdown records before 2026-10-16 use the old letters.
B38: Where it feeds | C38: The critical factors set the model's scope. A drives '11 Valuation' and '06 Core EPS Bridge'; B and C drive the revenue and capex lines on '17 Model'.
B39: This is a judgement framework, not data | C39: Every score here is my assessment, not a filed or provider figure. Evidence for each score appears in the notes above and is reviewed as new information arrives.

Sheet 14 Model Cover
B2: 14 — MODEL COVER
B3: Five-Year Operating Model - vertical format
B5: Company | C5: Alphabet Inc.
B6: Ticker | C6: GOOGL
B7: Model date | C7: 46280
B8: Currency | C8: $ millions except per-share
B9: Historical source | C9: Sheets 01-09 of this workbook (filed / derived)
B10: Forecast basis | C10: Segment revenue build, scenario-switched
B12: How this model is wired
B13: 1. 15 Assumptions holds every hard input. All blue. Nothing else in the model is typed.
B14: 2. 16 Scenarios turns those inputs into three cases and exposes ONE switch: 16 Scenarios!D6 (1=Base, 2=Best, 3=Worst). Every driver row is a CHOOSE() off that cell.
B15: 3. 17 Model runs the schedules top to bottom: Revenue -> Income Statement -> Depreciation -> Free Cash Flow -> Valuation. Each block reads the block above it.
B16: 4. Columns H,I,J are HISTORICAL (FY2023, FY2024, FY2025) and are linked live from '01 Income Statement', '03 Segments', '06 Core EPS Bridge', '09 Cash Flow' and '11 Valuation' - they are not retyped. Column K is TTM Jun'26. Columns L through P are the five forecast years FY2026E-FY2030E.
B17: 5. Colour convention follows the existing pack: BLUE = hard input, BLACK = same-sheet formula, GREEN = link to another sheet.
B18: 6. The equity-securities mark-to-market gain is forecast at ZERO in the operating case. Reported and core earnings are shown side by side so the gap stays visible rather than being buried.
B20: Answer to the question 'is converting the pack to this format doable'
B21: The pack and the template are different kinds of artifact. The pack looks BACKWARD: filed statements, a source register, a quote log, an audit sheet. It contains no forecast year, no driver, no scenario switch. The template looks FORWARD: it is an engine that turns a handful of drivers into five projected years.
B22: So this is not a reformatting job. Nothing in the pack can simply be poured into the template's shape, because the thing the template exists to do - project - does not yet exist in the pack.
B23: What IS doable, and is what these sheets do, is to BUILD the forward model in the template's architecture and FEED it from the pack. The history is linked, not copied, so the pack stays the single source of truth and the model inherits any correction made upstream.
B24: The model now includes '18 Balance Sheet': a live cash, debt and equity roll-forward from the filed Jun'26 opening position. It is deliberately compact rather than a fully disaggregated three-statement model; the 'Other equity / valuation movements' row exposes the residual for unmodeled OCI, securities revaluation, acquisitions and detailed working capital instead of hiding it.

Sheet 15 Assumptions
B2: 15 — ASSUMPTIONS
B3: $ millions except per-share and %. Percentages stored as TRUE DECIMALS on this sheet (0.12 = 12%), unlike sheets 01-13 of the pack which store whole numbers.
B5: GENERAL | E5: Source / reasoning
B6: First forecast year | C6: 2026 | E6: FY2026 is the first full year not yet filed.
B7: Share price used for valuation ($) | C7: 340.59 | E7: Price used throughout '11 Valuation'.
B8: Diluted shares, H1'26 base (millions) | C8: ='05 Capital Structure'!C16 -> 12274 | E8: Filed H1'26 weighted-average diluted, 05 Capital Structure. Buybacks are suspended, so the forecast count on 17 Model row 37 grows each year by stock-based compensation divided by the reference share price (FY2026E a quarter of that, for H2 issuance). The ATM exists to fund tax on those grants, so gross issuance is the right measure. Corrected 2026-09-24: this note used to say buybacks offset the June raise.
B9: Preferred dividend, annual | C9: 1187.5 | E9: Sheet 05 Capital Structure: 19,000 of 6.25% mandatory convertible, annual dividend 1,187.5. Reduces earnings available to common.
B10: Effective tax rate (core basis, forecast) | C10: =IF(ISNUMBER(C87),C87,C86) -> 0.1611201 | E10: ="Core basis since 2026-10-07 (entry 53): "&TEXT(C10,"0.0%")&", from row 86 unless C87 overrides it. The old 18.5% carried forward the reported TTM rate of "&TEXT('01 Income Statement'!$G$17/100,"0.0%")&", which the equity gains push up because they are taxed near 21% (row 85)." -> Core basis since 2026-10-07 (entry 53): 16.1%, from row 86 unless C87 overrides it. The old 18.5% carried forward the reported TTM rate of 18.4%, which the equity gains push up because they are taxed near 21% (row 85).
B12: SEGMENT REVENUE GROWTH - BASE CASE
C13: FY2026E | D13: FY2027E | E13: FY2028E | F13: FY2029E | G13: FY2030E | H13: Reasoning
B14: Google Search & other | C14: 0.15 | D14: 0.12 | E14: 0.1 | F14: 0.09 | G14: 0.08 | H14: ="Ran 19.1% Q1'26 / 16.8% Q2'26. Decays toward GDP-plus as the base gets larger. Cross-check: total revenue grows "&TEXT('DCF Base Model'!$M$19,"0.0%")&" in FY2027E against "&TEXT('07 Consensus'!$C$35/'07 Consensus'!$C$7-1,"0.0%")&" for consensus, so the base sits slightly below the Street. One point more or less a year on Services segments moves base value by about +$8 / -$8. Sensitivity and confidence are summarized in this rationale." -> Ran 19.1% Q1'26 / 16.8% Q2'26. Decays toward GDP-plus as the base gets larger. Cross-check: total revenue grows 21.2% in FY2027E against 24.2% for consensus, so the base sits slightly below the Street. One point more or less a year on Services segments moves base value by about +$8 / -$8. Sensitivity and confidence are summarized in this rationale.
B15: YouTube ads | C15: 0.125 | D15: 0.115 | E15: 0.105 | F15: 0.1 | G15: 0.095 | H15: Low-teens and steady; 10.7% and 12.9% in the two most recent quarters.
B16: Google Network | C16: -0.02 | D16: -0.02 | E16: -0.02 | F16: -0.02 | G16: -0.02 | H16: Structurally declining - negative in FY2024, FY2025 and both 2026 quarters.
B17: Subscriptions, platforms & devices | C17: 0.16 | D17: 0.145 | E17: 0.13 | F17: 0.12 | G17: 0.11 | H17: Mid-to-high teens, the most consistent grower in the Services stack.
B18: Google Cloud | C18: 0.7 | D18: row 74 | E18: row 74 | F18: row 74 | G18: row 74 | H18: 81.8% in Q2'26. FY2026E only: from FY2027E Cloud revenue follows prior-year capex at rows 74 to 76, so D18:G18 are no longer inputs (retired 2026-09-24).
B19: Other Bets | C19: 0.05 | D19: 0.05 | E19: 0.05 | F19: 0.05 | G19: 0.05 | H19: Immaterial to the total; held at a nominal rate.
B21: SCENARIO DELTAS - applied to every segment growth rate above
B22: Best case, growth added | C22: 0.03 | E22: Parallel shift on all six segments. Best case = AI monetisation lands faster than base. From FY2027E Cloud follows capex (rows 74 to 76), so the shift reaches Cloud in FY2026E only.
B23: Worst case, growth added | C23: -0.04 | E23: Worst case is deliberately wider than best: search share loss to AI assistants is the asymmetric risk.
B24: Hedging / other revenue, held flat at | C24: 0 | E24: Hedging was -127 in FY2025 and -74 in H1'26; it swings sign year to year, so it is not forecast. Note: the model carries the TTM Jun'26 figure of -349 in the last actual column.
B26: OPERATING MARGIN BEFORE THE DEPRECIATION RAMP | H26: Each input is operating margin before depreciation charged above the base-period rate of 5.66% of revenue (TTM Jun'26). 17 Model row 26 subtracts the excess, so reported operating margin is an output at 17 Model row 25. Historical equivalent: FY2023 25.6%, FY2024 30.8%, FY2025 31.6%, TTM Jun'26 33.1%, H1'26 35.3%.
B27: Operating margin before depreciation ramp, base | C27: 0.353 | D27: 0.358 | E27: 0.363 | F27: 0.368 | G27: 0.373 | H27: Anchored to H1'26 actual, where the equivalent was 35.3% (operating margin 35.0% plus depreciation at 5.9% of revenue, less 5.66%). Expands 0.5pp a year, a third of the roughly 1.5pp a year from FY2024 to TTM Jun'26, so most of the depreciation ramp still passes through to reported margin. Cross-check 2026-10-07: 17 Model rows 117-125 show this path against a mix-weighted path built from the model's own segment mix (switch at C117).
B28: Operating margin before depreciation ramp, best | C28: 0.358 | D28: 0.368 | E28: 0.378 | F28: 0.388 | G28: 0.398 | H28: Starts 0.5pp above the H1'26 anchor and expands 1.0pp a year. Cloud margin went 23.7% to 35.6% in a year, and in Q1'26 headcount grew 4.8% against revenue growth of 21.8%, so mix and operating leverage absorb more of the ramp.
B29: Operating margin before depreciation ramp, worst | C29: 0.345 | D29: 0.34 | E29: 0.335 | F29: 0.33 | G29: 0.325 | H29: ="Starts 0.8pp below the H1'26 anchor and gives back 0.5pp a year as growth slows. "&"The low reported margin in this case comes mainly from depreciation on the capex path at row 34, peaking at "&TEXT(MAX($C$34:$G$34),"0%")&" of revenue, against slowing revenue, not from this input." -> Starts 0.8pp below the H1'26 anchor and gives back 0.5pp a year as growth slows. The low reported margin in this case comes mainly from depreciation on the capex path at row 34, peaking at 46% of revenue, against slowing revenue, not from this input.
B31: CAPEX AND THE DEPRECIATION BASE - the heart of the model
B32: Capex intensity, % of revenue, base | C32: 0.41 | D32: 0.433 | E32: 0.37 | F32: 0.31 | G32: 0.25 | H32: FY2026E lands inside the 195,000-205,000 guidance. FY2027E is set at about 257,000 (43.3% of revenue), the low end of the Street range of 257,000 (FactSet via CNBC, Jul 22 2026) to 302,822 (MarketScreener, Oct 2026), because management guided on the Q2 2026 call to a significant increase in 2027. Intensity then steps down six points a year to 25% by FY2030E. Reset 2026-10-13 (entry 65) from 36% / 32% / 28% / 25%, which put FY2027E only 6% above FY2026E. History: 10.5%, 15.0%, 22.7% and 29.7% from FY2023 to TTM Jun'26.
B33: Capex intensity, % of revenue, best | C33: 0.4 | D33: 0.39 | E33: 0.32 | F33: 0.25 | G33: 0.2 | H33: Best: the FY2027E step-up still happens, at 39% of faster-growing revenue, and intensity then falls fastest, to 20% by FY2030E, as utilisation of the build improves. This is the free-cash-flow recovery case. Reset 2026-10-13 (entry 65) from 32% / 26% / 21% / 18%, which held FY2027E capex flat against guidance of a significant increase.
B34: Capex intensity, % of revenue, worst | C34: 0.42 | D34: 0.46 | E34: 0.4 | F34: 0.33 | G34: 0.27 | H34: Worst: demand disappoints after the FY2027E build is committed, so intensity peaks at 46% of slower revenue in FY2027E and management moderates with a one-year lag, to 27% by FY2030E. Reset 2026-10-13 (entry 65) from 40% / 35% / 30% / 26% so the worst case still spends more per dollar of revenue than the base.
B36: Assets not yet in service, Jun'26 | C36: 122814 | E36: ="Source: '08 PPE and Depreciation'. Earning no depreciation today - "&TEXT('08 PPE and Depreciation'!$C$25,"0.0")&"% of gross PP&E." -> Source: '08 PPE and Depreciation'. Earning no depreciation today - 28.8% of gross PP&E.
B37: Short-lived share of that balance, base | C37: 0.6 | E37: Source: '08 PPE and Depreciation'. This split is THE SINGLE MOST SENSITIVE ASSUMPTION and should be scenarioed, not point-estimated. The split is NOT disclosed. Evidence: the in-service base implies about a third short-lived at these lives (in-service gross PP&E / annual depreciation is about 11 years, land included), while the AI build is server-heavy, so 60% assumes the new assets skew to servers. Still a judgment. 45% and 80% move base value by +$9 and -$9. Sensitivities and confidence: the assumptions rationale.
B38: Short-lived share, best | C38: 0.45 | E38: Best case = more of the build is long-lived buildings, so the charge spreads over 20 years.
B39: Short-lived share, worst | C39: 0.8 | E39: Worst case = mostly 6-year servers, so the charge hits fast and hard.
B40: Short-lived useful life (years) | C40: 6 | E40: Servers and network equipment, 'generally 6 years' per the FY2025 10-K.
B41: Long-lived useful life (years) | C41: 20 | E41: Proxy for data-centre and office buildings, disclosed as 7 to 40 years (midpoint 23.5); 20 is slightly short of the midpoint, so slightly conservative. 15 and 30 years move base value by -$3 and +$3. Sensitivities and confidence: the assumptions rationale.
B42: Not yet in service at year end, years of capex | C42: 0.9 | E42: Depreciation starts when assets are placed in service (FY2025 10-K policy), and about 0.9 years of capex is always waiting: not-yet-in-service was 0.96 years of capex at Dec'24, 0.86 at Dec'25 and 0.93 (TTM) at Jun'26. 17 Model row 56 holds that balance; placements are capex less its increase. Set 2026-09-24, entry 45; replaced 'the 122,814 enters service evenly over three years', which started depreciation on capex when spent.
B44: OTHER CASH-FLOW AND EARNINGS ITEMS
B45: Stock-based compensation, % of revenue | C45: 0.06 | D45: 0.058 | E45: 0.056 | F45: 0.054 | G45: 0.052 | H45: ="TTM SBC "&TEXT('09 Cash Flow'!$G$8,"#,##0")&" on revenue "&TEXT('01 Income Statement'!$G$6,"#,##0")&" = "&TEXT('09 Cash Flow'!$G$8/'01 Income Statement'!$G$6,"0.0%")&". Drifts down as revenue outgrows grant value."&" SBC is expensed inside operating income, so it is already a cost in FCFF, and value per share uses today's diluted count: this path changes EPS and the forecast share count, not the DCF value." -> TTM SBC 28,147 on revenue 445,866 = 6.3%. Drifts down as revenue outgrows grant value. SBC is expensed inside operating income, so it is already a cost in FCFF, and value per share uses today's diluted count: this path changes EPS and the forecast share count, not the DCF value.
B46: Other income excl. equity gains, annual | C46: 3000 | D46: 3200 | E46: 3400 | F46: 3600 | G46: 3800 | H46: Interest and the rest, stripped of the mark-to-market gain. FCFF is built on operating income, so this line moves EPS, not the DCF value. 3,000 is above the H1'26 run-rate excluding gains (about -500 a year, 10-Q R68) and below the 5,000-12,000 consensus implies; it assumes interest income on the larger cash pile recovers. A risk to EPS, not to value.
B47: Equity-securities mark-to-market gain, base | C47: 135946 | D47: 0 | E47: 0 | F47: 0 | G47: 0 | H47: FY2026E carries the H1'26 gain already booked, 135,946 (filed, Q2 2026 10-Q), so reported FY2026E is comparable with consensus. Zero from H2'26 onward by design; see the note below. Core earnings exclude it in every year.
B48: D&A already running (annualised, Jun'26) | C48: 27172 | H48: Source: '08 PPE and Depreciation'. H1'26 depreciation of 13,586 doubled; this is the base the new assets layer on top of.
B50: WHY THE EQUITY-SECURITIES GAIN IS FORECAST AT ZERO
B51: ="TTM Jun'26 net income of "&TEXT('01 Income Statement'!$G$18,"#,##0")&" contains "&TEXT('17 Model'!$K$28,"#,##0")&" of pretax mark-to-market gains on the equity-securities portfolio ("&"FY2025 "&TEXT('06 Core EPS Bridge'!$E$7,"#,##0")&" + "&"H1'26 "&TEXT('06 Core EPS Bridge'!$J$7,"#,##0")&" - "&"H1'25 "&TEXT('06 Core EPS Bridge'!$F$7+'06 Core EPS Bridge'!$H$7,"#,##0")&", all filed), "&"about "&TEXT('17 Model'!$K$28*(1-$C$85),"#,##0")&" after tax"&". In Q2'26 alone the gain was "&TEXT('06 Core EPS Bridge'!$I$7,"#,##0")&", which is "&TEXT('06 Core EPS Bridge'!$I$7/'06 Core EPS Bridge'!$I$6,"0%")&" of pretax"&" income. That is why the stock looks like "&TEXT('11 Valuation'!$C$11,"0.0")&"x"&" earnings on reported figures and "&"about "&TEXT('11 Valuation'!$C$12,"0")&"x"&" on core." -> TTM Jun'26 net income of 244,205 contains 148,982 of pretax mark-to-market gains on the equity-securities portfolio (FY2025 24,080 + H1'26 135,946 - H1'25 11,044, all filed), about 117,696 after tax. In Q2'26 alone the gain was 99,031, which is 71% of pretax income. That is why the stock looks like 17.1x earnings on reported figures and about 33x on core.
B52: These gains are revaluations of holdings, not cash generated by the business. They are as likely to reverse as to repeat - ASU 2016-01 forces the swing through the income statement either way. Forecasting them at anything other than zero would mean predicting the direction of a portfolio, which is not a modelling exercise.
B53: Setting them to zero is therefore not a claim that they will be zero. It is a statement that the operating case should not depend on them. The model still prints a REPORTED line alongside the CORE line, so if a gain does land you can type it into row 47 and watch exactly how much of the resulting EPS is real.
B55: RECONCILIATION INPUTS ADDED 2026-09-17 - see 29 Change Log entry 24
B56: H1'26 capex already inside the Jun'26 depreciation base | C56: 80598 | E56: Filed H1 2026 capex, live from 09 Cash Flow G20. The Jun'26 opening balances on the depreciation schedule already contain this spend, so it is netted out of the FY2026E new-capex layer at 17 Model L60 to stop it being depreciated twice. The cash capex line still carries the full calendar year. Set to 0 to restore the prior treatment.
B57: Working capital, deferred taxes and other, % of revenue | C57: 0 | E57: ="Drives the reconciling line at 17 Model row 73. Held at zero deliberately. The historical residual is "&TEXT('17 Model'!$H$73,"+#,##0;-#,##0")&" (FY2023), "&TEXT('17 Model'!$I$73,"+#,##0;-#,##0")&" (FY2024), "&TEXT('17 Model'!$J$73,"+#,##0;-#,##0")&" (FY2025) and "&TEXT('17 Model'!$K$73,"+#,##0;-#,##0")&" (TTM Jun'26)"&", and the TTM figure is mostly deferred tax on the equity-securities gain, which is forecast at zero, so extrapolating it would be wrong. Zero is the neutral choice, not a forecast. Set a view here if"&" you want one." -> Drives the reconciling line at 17 Model row 73. Held at zero deliberately. The historical residual is -6,063 (FY2023), -9,201 (FY2024), +10,534 (FY2025) and +37,068 (TTM Jun'26), and the TTM figure is mostly deferred tax on the equity-securities gain, which is forecast at zero, so extrapolating it would be wrong. Zero is the neutral choice, not a forecast. Set a view here if you want one.
B58: Share of a year new FY2026E placements depreciate | C58: 0.25 | E58: H1'26 depreciation is already inside the run rate, so FY2026E placements land across H2 and earn a quarter-year on average, not the half-year used from FY2027E. With 0.5 the schedule implied H2'26 depreciation roughly double H1; with 0.25 H2 runs about 50% above H2'25, in line with the capex acceleration.
B59: One-off cash outflow FY2026E: EU Android fine plus interest | C59: -5200 | E59: Q2 2026 10-Q, Note 10: the Court of Justice denied the appeal in July 2026 and 'In July 2026, we made a cash payment of $5.2 billion for the fine plus accrued interest.' Accrued in 2018, so no P&L effect; it reduces FY2026E operating cash flow at 17 Model L73 and H2 FCFF on 20 DCF Valuation.
B60: BALANCE SHEET AND DEBT ASSUMPTIONS
B61: Input | C61: FY2026E | D61: FY2027E | E61: FY2028E | F61: FY2029E | G61: FY2030E | H61: Source / reasoning
B62: Receivables as % of revenue | C62: ='04 Balance Sheet'!G9/'01 Income Statement'!G6 -> 0.15514751 | D62: =$C62 -> 0.15514751 | E62: =$C62 -> 0.15514751 | F62: =$C62 -> 0.15514751 | G62: =$C62 -> 0.15514751 | H62: Jun'26 receivables divided by TTM revenue; held constant.
B63: Other current assets as % of revenue | C63: =('04 Balance Sheet'!G10-'04 Balance Sheet'!G8-'04 Balance Sheet'!G9)/'01 Income Statement'!G6 -> 0.071490089 | D63: =$C63 -> 0.071490089 | E63: =$C63 -> 0.071490089 | F63: =$C63 -> 0.071490089 | G63: =$C63 -> 0.071490089 | H63: Jun'26 current assets excluding cash/securities and receivables, divided by TTM revenue; held constant.
B64: Current liabilities as % of revenue | C64: ='04 Balance Sheet'!G15/'01 Income Statement'!G6 -> 0.28284507 | D64: =$C64 -> 0.28284507 | E64: =$C64 -> 0.28284507 | F64: =$C64 -> 0.28284507 | G64: =$C64 -> 0.28284507 | H64: Jun'26 current liabilities divided by TTM revenue; held constant.
B65: Other liabilities as % of revenue | C65: =('04 Balance Sheet'!G18-'04 Balance Sheet'!G15-'04 Balance Sheet'!G17)/'01 Income Statement'!G6 -> 0.11805789 | D65: =$C65 -> 0.11805789 | E65: =$C65 -> 0.11805789 | F65: =$C65 -> 0.11805789 | G65: =$C65 -> 0.11805789 | H65: Jun'26 liabilities excluding current liabilities and debt, divided by TTM revenue; held constant.
B66: Goodwill held constant | C66: ='04 Balance Sheet'!G13 -> 57828 | D66: =$C66 -> 57828 | E66: =$C66 -> 57828 | F66: =$C66 -> 57828 | G66: =$C66 -> 57828 | H66: Jun'26 goodwill; no acquisition forecast.
B67: Other non-current assets held constant | C67: ='04 Balance Sheet'!G14-'04 Balance Sheet'!G10-'04 Balance Sheet'!G12-'04 Balance Sheet'!G13 -> 199419 | D67: =$C67 -> 199419 | E67: =$C67 -> 199419 | F67: =$C67 -> 199419 | G67: =$C67 -> 199419 | H67: Jun'26 residual non-current assets; held constant.
B68: Common dividend per share | C68: 0.8724 | D68: 0.9153 | E68: 0.9546 | F68: =E68*1.05 -> 1.00233 | G68: =F68*1.05 -> 1.0524465 | H68: MarketScreener consensus DPS through FY2028E; 5% growth thereafter.
B69: New debt issuance | C69: 0 | D69: 0 | E69: 0 | F69: 0 | G69: 0 | H69: Zero by default. Enter gross issuance if financing plans change.
B70: Debt repayments | C70: 0 | D70: 0 | E70: 0 | F70: 0 | G70: 0 | H70: Zero by default. Enter principal repayment as a positive number.
B72: CAPEX RETURN AND FADE STAGE - added 2026-09-24, see 29 Change Log entry 42
C73: FY2026E | D73: FY2027E | E73: FY2028E | F73: FY2029E | G73: FY2030E | H73: Reasoning
B74: Cloud revenue added per $ of prior-year capex, base | D74: 0.3 | E74: 0.3 | F74: 0.3 | G74: 0.3 | H74: ="17 Model row 14: Cloud(t) = Cloud(t-1) + this x capex(t-1). Set 2026-10-07 (entry 61) to 30 cents, the FY2024-FY2025 history ("&TEXT('DCF Base Model'!$I$114,"0.0")&" and "&TEXT('DCF Base Model'!$J$114,"0.0")&" cents). The earlier 22.4-25.0 only reproduced the old growth-rate path and was never a view. FY2026E runs about 45 on the supply-constrained H1 pace and keeps its growth rate in row 18. Backlog check"&" (17 Model rows 107-112): modeled Cloud revenue in the 24 months after Jun'26 is "&TEXT('DCF Base Model'!$O$108,"#,##0")&" against "&TEXT('DCF Base Model'!$O$109,"#,##0")&" of backlog converting, "&TEXT('DCF Base Model'!$O$111,"0%")&" beyond signed contracts." -> 17 Model row 14: Cloud(t) = Cloud(t-1) + this x capex(t-1). Set 2026-10-07 (entry 61) to 30 cents, the FY2024-FY2025 history (31.4 and 29.5 cents). The earlier 22.4-25.0 only reproduced the old growth-rate path and was never a view. FY2026E runs about 45 on the supply-constrained H1 pace and keeps its growth rate in row 18. Backlog check (17 Model rows 107-112): modeled Cloud revenue in the 24 months after Jun'26 is 333,676 against 256,950 of backlog converting, 30% beyond signed contracts.
B75: Cloud revenue added per $ of prior-year capex, best | D75: 0.33 | E75: 0.34 | F75: 0.355 | G75: 0.374 | H75: Best starts at 33 cents, above the base and the history, and rises to 37.4 cents as utilisation of the build improves (raised 2026-10-07 so best stays above base).
B76: Cloud revenue added per $ of prior-year capex, worst | D76: 0.201 | E76: 0.184 | F76: 0.185 | G76: 0.195 | H76: About 35% below the FY2024-FY2025 history of about 30 cents: the demand-disappoints case in which the build outruns Cloud demand. Moving base itself to 25 cents costs about $17 a share. Sensitivities and confidence: the assumptions rationale.
B78: Fade stage switch (1 = on, 0 = off) | C78: 1 | E78: 1 values the business through a fade to terminal growth (20 DCF Valuation rows 14 to 22). 0 reverts to the method used before 2026-09-24: terminal value struck on FY2030E, which drops from 12.5% revenue growth straight to perpetual growth.
B79: Fade length, years (1 to 10) | C79: 10 | E79: Years over which revenue growth fades linearly from its FY2030E rate to terminal growth. After the fade ends growth holds at the terminal rate, so FY2040E is a steady state for any value from 1 to 10. Why 10: it is the usual high-growth-to-stable transition in a three-stage DCF (Damodaran), and FY2030E revenue growth is still about 12.5%, so a 5-year fade would cut growth by about 2 points a year. 5 years lowers base value by about $33. Sensitivities and confidence: the assumptions rationale.
B80: Return on new invested capital after FY2030E, base | C80: 0.15 | E80: =_xlfn._LONGTEXT("Return on each new dollar reinvested after FY2030E. It sets terminal reinvestment (growth / this x NOPAT) and, since 2026-10-07, the terminal margin (row 104). In that steady state the return on the whole capital base equals this figure, so it is a statem","ent about the legacy business as well as the new capital; 11 Valuation rows 96-112 show the value with the FY2030E margin held and reconcile the DCF to the multiples. Why 15% in the base: (1) the five-year b")&"uild earns about "&TEXT('20 DCF Valuation'!$C$71,"0%")&" in the base case (20 DCF Valuation C71), so 15% assumes post-2030 investment earns about what the AI build earns; (2) it sits "&TEXT(($C$80-'20 DCF Valuation'!$H$18)*100,"0.0")&" points above the "&TEXT('20 DCF Valuation'!$H$18,"0.0%")&" WACC, so growth still adds value; (3) it is well below Alphabet's TTM ROIC of "&TEXT('11 Valuation'!$C$38/100,"0%")&" (11 Valuation C38), which the capital-light search business earns and new data-centre capital will not resemble; (4) capital-heavy peers bracket it: Amazon "&TEXT('12 Peers'!$L$9/100,"0%")&", Microsoft "&TEXT('12 Peers'!$L$7/100,"0%")&" (12 Peers). A judgment, not a derived figure, set toward the conservative side of that range. Best 25% (what the existing base earns), worst 10% (about the cost of capital). 10% and 25% move base val"&"ue by about -$41 and +$51. Sensitivities and confidence: the assumptions rationale." -> Return on each new dollar reinvested after FY2030E. It sets terminal reinvestment (growth / this x NOPAT) and, since 2026-10-07, the terminal margin (row 104). In that steady state the return on the whole capital base equals this figure, so it is a statement about the legacy business as well as the new capital; 11 Valuation rows 96-112 show the value with the FY2030E margin held and reconcile the DCF to the multiples. Why 15% in the base: (1) the five-year build earns about 15% in the base case (20 DCF Valuation C71), so 15% assumes post-2030 investment earns about what the AI build earns; (2) it sits 5.4 points above the 9.6% WACC, so growth still adds value; (3) it is well below Alphabet's TTM ROIC of 29% (11 Valuation C38), which the capital-light search business earns and new data-centre capital will not resemble; (4) capital-heavy peers bracket it: Amazon 12%, Microsoft 26% (12 Peers). A judgment, not a derived figure, set toward the conservative side of that range. Best 25% (what the existing base earns), worst 10% (about the cost of capital). 10% and 25% move base value by about -$41 and +$51. Sensitivities and confidence: the assumptions rationale.
B81: Return on new invested capital after FY2030E, best | C81: 0.25 | E81: Best: new capital keeps earning about what the existing base earns.
B82: Return on new invested capital after FY2030E, worst | C82: 0.1 | E82: Worst: competition pushes returns on new capital to about the cost of capital, so growth after FY2030E adds almost no value.
B84: TAX ON EQUITY-SECURITIES GAINS AND THE CORE RATE - added 2026-10-07, see 29 Change Log entry 53
B85: Tax rate on equity-securities gains | C85: 0.21 | E85: ="Not disclosed: the Q2 2026 10-Q tax note (R23, R81, R82) gives only effective rates and unrecognised benefits. 21% is the US federal statutory rate. Corroboration: the net deferred tax liability rose "&TEXT('04 Balance Sheet'!$G$36-'04 Balance Sheet'!$E$36,"#,##0")&" in H1'26, "&TEXT('04 Balance Sheet'!$G$37,"0.0%")&" of the "&TEXT('06 Core EPS Bridge'!$J$7,"#,##0")&" of H1 gains, most of them unrealised (04 Balance Sheet rows 34-37)." -> Not disclosed: the Q2 2026 10-Q tax note (R23, R81, R82) gives only effective rates and unrecognised benefits. 21% is the US federal statutory rate. Corroboration: the net deferred tax liability rose 29,565 in H1'26, 21.7% of the 135,946 of H1 gains, most of them unrealised (04 Balance Sheet rows 34-37).
B86: Core effective tax rate, average of FY2024, FY2025 and H1'26 | C86: =AVERAGE('06 Core EPS Bridge'!D36,'06 Core EPS Bridge'!E36,'06 Core EPS Bridge'!J36)/100 -> 0.1611201 | E86: ="DERIVED. Core rates on 06 Core EPS Bridge row 36: FY2024 "&TEXT('06 Core EPS Bridge'!$D$36,"0.0")&"%, FY2025 "&TEXT('06 Core EPS Bridge'!$E$36,"0.0")&"%, H1'26 "&TEXT('06 Core EPS Bridge'!$J$36,"0.0")&"%. FY2023 ("&TEXT('06 Core EPS Bridge'!$C$36,"0.0")&"%) is left out since 2026-10-07 (entry 61): it is older and below every later period, which cluster within half a point. Quarters are left out because they overlap H1'26." -> DERIVED. Core rates on 06 Core EPS Bridge row 36: FY2024 16.3%, FY2025 16.0%, H1'26 16.0%. FY2023 (13.9%) is left out since 2026-10-07 (entry 61): it is older and below every later period, which cluster within half a point. Quarters are left out because they overlap H1'26.
B87: Override for the forecast core rate (blank = use row 86) | E87: Optional override. Leave blank to use the row 86 average; enter a rate such as 0.165 only when a documented alternative view is intended. The rate drives forecast core tax, NOPAT and the WACC tax shield.
B89: FADE STAGE: REINVESTMENT AND MARGIN PATHS - added 2026-10-07, see 29 Change Log entry 54
B90: Reinvestment fade switch (1 = fade from the FY2030E rate, 0 = growth / return from FY2031E) | C90: 1 | E90: 1 starts FY2031E net reinvestment at the FY2030E rate, (capex - depreciation) / NOPAT, and fades it linearly to terminal growth / return on new capital over the fade length (C79). 0 restores the 2026-09-24 method, growth / return from FY2031E, which jumped reinvestment from the FY2030E rate to about 77% of NOPAT and halved FY2031E FCFF.
B91: Terminal margin fade switch (1 = fade to row 106, 0 = hold the FY2030E margin) | C91: 1 | E91: Set to 1 on 2026-10-07 (entry 61). With the reinvestment fade on (C90), the terminal year reinvests g / return on new capital; holding the FY2030E margin at the same time implies far less depreciation than that reinvestment produces at the model's asset lives. Row 104 is the margin consistent with both. It is driven by the return on new capital (C80): at 15% base it is about 21%, at 25% about 26%. 0 restores the held FY2030E margin.
B92: Terminal margin derivation (feeds row 106) | C92: Base | D92: Best | E92: Worst | H92: Derivation
B93: Operating margin before the ramp, FY2030E (scenario) | C93: ='DCF Base Drivers'!G25 -> 0.373 | D93: ='DCF Best Drivers'!G25 -> 0.398 | E93: ='DCF Worst Drivers'!G25 -> 0.325 | H93: The scenario's FY2030E pre-ramp margin (16 Scenarios row 25 on each hidden engine).
B94: Base-period depreciation rate (TTM Jun'26 depreciation / revenue) | C94: ='17 Model'!$K$64/'17 Model'!$K$23 -> 0.056602208 | D94: ='17 Model'!$K$64/'17 Model'!$K$23 -> 0.056602208 | E94: ='17 Model'!$K$64/'17 Model'!$K$23 -> 0.056602208 | H94: Pre-ramp margin is struck after depreciation at this rate, so pre-ramp + this rate = margin before all depreciation.
B95: Blended depreciation life of placements (years) | C95: ='DCF Base Drivers'!C29 -> 8.3333333 | D95: ='DCF Best Drivers'!C29 -> 9.7560976 | E95: ='DCF Worst Drivers'!C29 -> 6.9767442 | H95: The life the model applies to every placement (17 Model row 62), by scenario.
B96: Terminal growth | C96: ='20 DCF Valuation'!$H$19 -> 0.03 | D96: ='20 DCF Valuation'!$H$19 -> 0.03 | E96: ='20 DCF Valuation'!$H$19 -> 0.03 | H96: 20 DCF Valuation H19.
B97: Return on new capital after FY2030E | C97: =$C$80 -> 0.15 | D97: =$C$81 -> 0.25 | E97: =$C$82 -> 0.1 | H97: Rows 80-82.
B98: Not-yet-in-service lag (years of capex) | C98: =$C$42 -> 0.9 | D98: =$C$42 -> 0.9 | E98: =$C$42 -> 0.9 | H98: Row 42. Placements trail capex by this lag; the model charges a half year on placements.
B99: Steady-state depreciation / capex | C99: =(1+C96)^-(C98-0.5)*(1-(1+C96)^-C95)/(C96*C95) -> 0.86305734 | D99: =(1+D96)^-(D98-0.5)*(1-(1+D96)^-D95)/(D96*D95) -> 0.84589003 | E99: =(1+E96)^-(E98-0.5)*(1-(1+E96)^-E95)/(E96*E95) -> 0.87987094 | H99: Straight-line life L, capex growing at g: D/C = (1+g)^-(lag-0.5) x (1 - (1+g)^-L) / (g x L). Close to 1 at low growth.
B100: Terminal capex intensity consistent with the return on new capital | C100: =(C96/C97)*(1-$C$10)*(C93+C94)/((1-C99)+(C96/C97)*(1-$C$10)*C99) -> 0.25582515 | D100: =(D96/D97)*(1-$C$10)*(D93+D94)/((1-D99)+(D96/D97)*(1-$C$10)*D99) -> 0.19126648 | E100: =(E96/E97)*(1-$C$10)*(E93+E94)/((1-E99)+(E96/E97)*(1-$C$10)*E99) -> 0.28116665 | H100: Solves capex - depreciation = (g / return) x NOPAT with NOPAT = (pre-ramp + base rate - D/C x capex) x (1 - tax). DERIVED, no typed number.
B101: Terminal capex intensity override (blank = use row 100) | H101: Optional override. A lower intensity raises the terminal margin, but the implied reinvestment then falls below g / return in rows 107-108.
B102: Terminal capex intensity used | C102: =IF(ISNUMBER(C101),C101,C100) -> 0.25582515 | D102: =IF(ISNUMBER(D101),D101,D100) -> 0.19126648 | E102: =IF(ISNUMBER(E101),E101,E100) -> 0.28116665
B103: Steady-state depreciation, % of revenue | C103: =C102*C99 -> 0.22079177 | D103: =D102*D99 -> 0.16179041 | E103: =E102*E99 -> 0.24739037 | H103: Capex intensity x D/C.
B104: Terminal operating margin, DERIVED | C104: =C93+C94-C103 -> 0.20881044 | D104: =D93+D94-D103 -> 0.2928118 | E104: =E93+E94-E103 -> 0.13421184 | H104: Pre-ramp margin + base-period depreciation rate - steady-state depreciation.
B105: Terminal operating margin override (blank = use row 104) | H105: Optional override. Use only with a documented terminal-margin view; the derived value in row 104 is the internally consistent default.
B106: TERMINAL OPERATING MARGIN USED when C91 = 1 | C106: =IF(ISNUMBER(C105),C105,C104) -> 0.20881044 | D106: =IF(ISNUMBER(D105),D105,D104) -> 0.2928118 | E106: =IF(ISNUMBER(E105),E105,E104) -> 0.13421184 | H106: Read by 16 Scenarios row 33 and each hidden Drivers sheet.
B107: Memo: net reinvestment / NOPAT implied by rows 102-106 | C107: =C102*(1-C99)/(C106*(1-$C$10)) -> 0.2 | D107: =D102*(1-D99)/(D106*(1-$C$10)) -> 0.12 | E107: =E102*(1-E99)/(E106*(1-$C$10)) -> 0.3 | H107: Equals row 108 when no override is used.
B108: Memo: g / return on new capital (the fade's terminal reinvestment rate) | C108: =C96/C97 -> 0.2 | D108: =D96/D97 -> 0.12 | E108: =E96/E97 -> 0.3
B109: Memo: FY2030E reported operating margin (what C91 = 0 holds) | C109: ='DCF Base Model'!P25 -> 0.28565561 | D109: ='DCF Best Model'!P25 -> 0.34540843 | E109: ='DCF Worst Model'!P25 -> 0.17642158
B111: CLOUD BACKLOG CROSS-CHECK - added 2026-10-07, see 29 Change Log entry 55
B112: Google Cloud remaining performance obligations, Jun'26 | C112: 513900 | E112: Q2 2026 10-Q revenue note: Cloud RPO of 513,900 within 519,500 total RPO at Jun 30, 2026 (also 03 Segments B46).
B113: Share of Cloud RPO expected to convert within 24 months | C113: 0.5 | E113: Q2 2026 10-Q: 'just over 50%' expected to be recognised as revenue over the next 24 months. 50% is used, so the conversion is slightly understated.
B114: Warning threshold: non-backlog Cloud revenue as % of backlog conversion | C114: 0.1 | E114: 17 Model O112 shows a warning, not a failure, when modeled Cloud revenue over the 24 months exceeds the converting backlog by less than this.
B116: MIX-WEIGHTED PRE-RAMP MARGIN - added 2026-10-07, see 29 Change Log entry 56
...

Sheet 16 Scenarios
B2: 16 — SCENARIOS
B3: Change D6 only. Everything below, and every forecast column on 17 Model, follows it.
B6: SCENARIO SWITCH (1 = Base, 2 = Best, 3 = Worst) | D6: 1 | F6: =CHOOSE($D$6,"BASE CASE","BEST CASE","WORST CASE") -> BASE CASE
B8: Why these three drivers and not others
B9: A scenario axis is only worth building where the outcome is genuinely uncertain AND the model is sensitive to it. Three items on Alphabet qualify, and they are deliberately flexed TOGETHER off one switch because they are not independent - the same AI-capex thesis that drives one drives the others.
B10: ="1. DEPRECIATION LIFE SPLIT. Sheet '08 PPE and Depreciation' states it outright: the split of the "&TEXT('08 PPE and Depreciation'!$C$24,"#,##0")&" of assets-not-yet-in-service between short- and long-lived classes is the single most sensitive assumption in the model, it is NOT disclosed, and it should be scenarioed rather than point-estimated. "&"On a 6-year life that tranche alone adds "&"~"&TEXT('08 PPE and Depreciation'!$C$26,"#,##0")&"/yr against a ~"&TEXT('08 PPE and Depreciation'!$C$27,"#,##0")&" run rate - a ~"&TEXT('08 PPE and Depreciation'!$C$28,"0")&"%"&" increase before any further capex." -> 1. DEPRECIATION LIFE SPLIT. Sheet '08 PPE and Depreciation' states it outright: the split of the 122,814 of assets-not-yet-in-service between short- and long-lived classes is the single most sensitive assumption in the model, it is NOT disclosed, and it should be scenarioed rather than point-estimated. On a 6-year life that tranche alone adds ~20,469/yr against a ~27,172 run rate - a ~75% increase before any further capex.
B11: ="2. CAPEX PLATEAU TIMING. The Contents sheet names this as the open question: whether "&"~"&TEXT('06 Core EPS Bridge'!$D$19,"0")&"x core"&" earnings is defensible depends on what free cash flow normalises to once capex plateaus. Q2'26 was the first negative FCF quarter on record. Whether that reverses in FY2027 or FY2029 is the differenc"&"e between a cash machine and a capital sink." -> 2. CAPEX PLATEAU TIMING. The Contents sheet names this as the open question: whether ~33x core earnings is defensible depends on what free cash flow normalises to once capex plateaus. Q2'26 was the first negative FCF quarter on record. Whether that reverses in FY2027 or FY2029 is the difference between a cash machine and a capital sink.
B12: ="3. REVENUE GROWTH AND OPERATING MARGIN. The conventional axis, included because it is what the capex is being spent to buy. Note the deltas are asymmetric: "&"best adds "&TEXT('15 Assumptions'!$C$22*100,"0.0")&"pp"&" of growth, "&"worst subtracts "&TEXT(-'15 Assumptions'!$C$23*100,"0.0")&"pp"&". Search share loss to AI assistants is a larger risk than AI upside is an opportunity, because the base is "&TEXT('03 Segments'!$E$7,"#,##0")&" of high-margin revenue that has no replacement." -> 3. REVENUE GROWTH AND OPERATING MARGIN. The conventional axis, included because it is what the capex is being spent to buy. Note the deltas are asymmetric: best adds 3.0pp of growth, worst subtracts 4.0pp. Search share loss to AI assistants is a larger risk than AI upside is an opportunity, because the base is 224,532 of high-margin revenue that has no replacement.
B15: RESOLVED DRIVERS - these are what 17 Model actually reads
C16: FY2026E | D16: FY2027E | E16: FY2028E | F16: FY2029E | G16: FY2030E
B17: Segment revenue growth
B18: Google Search & other | C18: =CHOOSE($D$6,'15 Assumptions'!C14,'15 Assumptions'!C14+'15 Assumptions'!$C$22,'15 Assumptions'!C14+'15 Assumptions'!$C$23) -> 0.15 | D18: =CHOOSE($D$6,'15 Assumptions'!D14,'15 Assumptions'!D14+'15 Assumptions'!$C$22,'15 Assumptions'!D14+'15 Assumptions'!$C$23) -> 0.12 | E18: =CHOOSE($D$6,'15 Assumptions'!E14,'15 Assumptions'!E14+'15 Assumptions'!$C$22,'15 Assumptions'!E14+'15 Assumptions'!$C$23) -> 0.1 | F18: =CHOOSE($D$6,'15 Assumptions'!F14,'15 Assumptions'!F14+'15 Assumptions'!$C$22,'15 Assumptions'!F14+'15 Assumptions'!$C$23) -> 0.09 | G18: =CHOOSE($D$6,'15 Assumptions'!G14,'15 Assumptions'!G14+'15 Assumptions'!$C$22,'15 Assumptions'!G14+'15 Assumptions'!$C$23) -> 0.08
B19: YouTube ads | C19: =CHOOSE($D$6,'15 Assumptions'!C15,'15 Assumptions'!C15+'15 Assumptions'!$C$22,'15 Assumptions'!C15+'15 Assumptions'!$C$23) -> 0.125 | D19: =CHOOSE($D$6,'15 Assumptions'!D15,'15 Assumptions'!D15+'15 Assumptions'!$C$22,'15 Assumptions'!D15+'15 Assumptions'!$C$23) -> 0.115 | E19: =CHOOSE($D$6,'15 Assumptions'!E15,'15 Assumptions'!E15+'15 Assumptions'!$C$22,'15 Assumptions'!E15+'15 Assumptions'!$C$23) -> 0.105 | F19: =CHOOSE($D$6,'15 Assumptions'!F15,'15 Assumptions'!F15+'15 Assumptions'!$C$22,'15 Assumptions'!F15+'15 Assumptions'!$C$23) -> 0.1 | G19: =CHOOSE($D$6,'15 Assumptions'!G15,'15 Assumptions'!G15+'15 Assumptions'!$C$22,'15 Assumptions'!G15+'15 Assumptions'!$C$23) -> 0.095
B20: Google Network | C20: =CHOOSE($D$6,'15 Assumptions'!C16,'15 Assumptions'!C16+'15 Assumptions'!$C$22,'15 Assumptions'!C16+'15 Assumptions'!$C$23) -> -0.02 | D20: =CHOOSE($D$6,'15 Assumptions'!D16,'15 Assumptions'!D16+'15 Assumptions'!$C$22,'15 Assumptions'!D16+'15 Assumptions'!$C$23) -> -0.02 | E20: =CHOOSE($D$6,'15 Assumptions'!E16,'15 Assumptions'!E16+'15 Assumptions'!$C$22,'15 Assumptions'!E16+'15 Assumptions'!$C$23) -> -0.02 | F20: =CHOOSE($D$6,'15 Assumptions'!F16,'15 Assumptions'!F16+'15 Assumptions'!$C$22,'15 Assumptions'!F16+'15 Assumptions'!$C$23) -> -0.02 | G20: =CHOOSE($D$6,'15 Assumptions'!G16,'15 Assumptions'!G16+'15 Assumptions'!$C$22,'15 Assumptions'!G16+'15 Assumptions'!$C$23) -> -0.02
B21: Subscriptions, platforms & devices | C21: =CHOOSE($D$6,'15 Assumptions'!C17,'15 Assumptions'!C17+'15 Assumptions'!$C$22,'15 Assumptions'!C17+'15 Assumptions'!$C$23) -> 0.16 | D21: =CHOOSE($D$6,'15 Assumptions'!D17,'15 Assumptions'!D17+'15 Assumptions'!$C$22,'15 Assumptions'!D17+'15 Assumptions'!$C$23) -> 0.145 | E21: =CHOOSE($D$6,'15 Assumptions'!E17,'15 Assumptions'!E17+'15 Assumptions'!$C$22,'15 Assumptions'!E17+'15 Assumptions'!$C$23) -> 0.13 | F21: =CHOOSE($D$6,'15 Assumptions'!F17,'15 Assumptions'!F17+'15 Assumptions'!$C$22,'15 Assumptions'!F17+'15 Assumptions'!$C$23) -> 0.12 | G21: =CHOOSE($D$6,'15 Assumptions'!G17,'15 Assumptions'!G17+'15 Assumptions'!$C$22,'15 Assumptions'!G17+'15 Assumptions'!$C$23) -> 0.11
B22: Google Cloud (FY2027E on: output of row 24) | C22: =CHOOSE($D$6,'15 Assumptions'!C18,'15 Assumptions'!C18+'15 Assumptions'!$C$22,'15 Assumptions'!C18+'15 Assumptions'!$C$23) -> 0.7 | D22: ='17 Model'!M14/'17 Model'!L14-1 -> 0.60385278 | E22: ='17 Model'!N14/'17 Model'!M14-1 -> 0.4820625 | F22: ='17 Model'!O14/'17 Model'!N14-1 -> 0.33371628 | G22: ='17 Model'!P14/'17 Model'!O14-1 -> 0.24537439
B23: Other Bets | C23: =CHOOSE($D$6,'15 Assumptions'!C19,'15 Assumptions'!C19+'15 Assumptions'!$C$22,'15 Assumptions'!C19+'15 Assumptions'!$C$23) -> 0.05 | D23: =CHOOSE($D$6,'15 Assumptions'!D19,'15 Assumptions'!D19+'15 Assumptions'!$C$22,'15 Assumptions'!D19+'15 Assumptions'!$C$23) -> 0.05 | E23: =CHOOSE($D$6,'15 Assumptions'!E19,'15 Assumptions'!E19+'15 Assumptions'!$C$22,'15 Assumptions'!E19+'15 Assumptions'!$C$23) -> 0.05 | F23: =CHOOSE($D$6,'15 Assumptions'!F19,'15 Assumptions'!F19+'15 Assumptions'!$C$22,'15 Assumptions'!F19+'15 Assumptions'!$C$23) -> 0.05 | G23: =CHOOSE($D$6,'15 Assumptions'!G19,'15 Assumptions'!G19+'15 Assumptions'!$C$22,'15 Assumptions'!G19+'15 Assumptions'!$C$23) -> 0.05
B24: Cloud revenue per $ of prior-year capex | D24: =CHOOSE($D$6,'15 Assumptions'!D74,'15 Assumptions'!D75,'15 Assumptions'!D76) -> 0.3 | E24: =CHOOSE($D$6,'15 Assumptions'!E74,'15 Assumptions'!E75,'15 Assumptions'!E76) -> 0.3 | F24: =CHOOSE($D$6,'15 Assumptions'!F74,'15 Assumptions'!F75,'15 Assumptions'!F76) -> 0.3 | G24: =CHOOSE($D$6,'15 Assumptions'!G74,'15 Assumptions'!G75,'15 Assumptions'!G76) -> 0.3
B25: Operating margin before the depreciation ramp | C25: =IF('15 Assumptions'!$C$117=1,'17 Model'!L123,CHOOSE($D$6,'15 Assumptions'!C27,'15 Assumptions'!C28,'15 Assumptions'!C29)) -> 0.353 | D25: =IF('15 Assumptions'!$C$117=1,'17 Model'!M123,CHOOSE($D$6,'15 Assumptions'!D27,'15 Assumptions'!D28,'15 Assumptions'!D29)) -> 0.358 | E25: =IF('15 Assumptions'!$C$117=1,'17 Model'!N123,CHOOSE($D$6,'15 Assumptions'!E27,'15 Assumptions'!E28,'15 Assumptions'!E29)) -> 0.363 | F25: =IF('15 Assumptions'!$C$117=1,'17 Model'!O123,CHOOSE($D$6,'15 Assumptions'!F27,'15 Assumptions'!F28,'15 Assumptions'!F29)) -> 0.368 | G25: =IF('15 Assumptions'!$C$117=1,'17 Model'!P123,CHOOSE($D$6,'15 Assumptions'!G27,'15 Assumptions'!G28,'15 Assumptions'!G29)) -> 0.373
B26: Capex intensity, % of revenue | C26: =CHOOSE($D$6,'15 Assumptions'!C32,'15 Assumptions'!C33,'15 Assumptions'!C34) -> 0.41 | D26: =CHOOSE($D$6,'15 Assumptions'!D32,'15 Assumptions'!D33,'15 Assumptions'!D34) -> 0.433 | E26: =CHOOSE($D$6,'15 Assumptions'!E32,'15 Assumptions'!E33,'15 Assumptions'!E34) -> 0.37 | F26: =CHOOSE($D$6,'15 Assumptions'!F32,'15 Assumptions'!F33,'15 Assumptions'!F34) -> 0.31 | G26: =CHOOSE($D$6,'15 Assumptions'!G32,'15 Assumptions'!G33,'15 Assumptions'!G34) -> 0.25
B27: Return on new capital after FY2030E | C27: =CHOOSE($D$6,'15 Assumptions'!$C$80,'15 Assumptions'!$C$81,'15 Assumptions'!$C$82) -> 0.15
B28: Short-lived share of assets not yet in service | C28: =CHOOSE($D$6,'15 Assumptions'!$C$37,'15 Assumptions'!$C$38,'15 Assumptions'!$C$39) -> 0.6
B29: Blended life of that balance (years) | C29: =1/(C28/'15 Assumptions'!$C$40+(1-C28)/'15 Assumptions'!$C$41) -> 8.3333333 | E29: Harmonic blend: a dollar on a 6-year life depreciates six times faster than one on a 20-year life, so the lives must be weighted on annual CHARGE, not on years.
B31: Annual charge once fully in service | C31: ='15 Assumptions'!$C$36/C29 -> 14737.68 | E31: ="The "&TEXT('15 Assumptions'!$C$36,"#,##0")&" spread over its blended life. This is the number that does not exist in the reported figures today." -> The 122,814 spread over its blended life. This is the number that does not exist in the reported figures today.
B33: Terminal operating margin (used when 15 Assumptions C91 = 1) | C33: =CHOOSE($D$6,'15 Assumptions'!$C$106,'15 Assumptions'!$D$106,'15 Assumptions'!$E$106) -> 0.20881044
B35: Services margin change by FY2030E (mix path) | C35: =CHOOSE($D$6,'15 Assumptions'!$C$119,'15 Assumptions'!$D$119,'15 Assumptions'!$E$119) -> 0
B36: Cloud margin change by FY2030E (mix path) | C36: =CHOOSE($D$6,'15 Assumptions'!$C$120,'15 Assumptions'!$D$120,'15 Assumptions'!$E$120) -> 0
B37: Other Bets + Alphabet-level change by FY2030E (mix path) | C37: =CHOOSE($D$6,'15 Assumptions'!$C$121,'15 Assumptions'!$D$121,'15 Assumptions'!$E$121) -> 0

Sheet DCF Base Drivers
B2: DCF BASE DRIVERS — HIDDEN HELPER
B3: Change D6 only. Everything below, and every forecast column on 17 Model, follows it.
B6: SCENARIO SWITCH (1 = Base, 2 = Best, 3 = Worst) | D6: 1 | F6: =CHOOSE($D$6,"BASE CASE","BEST CASE","WORST CASE") -> BASE CASE
B8: Why these three drivers and not others
B9: A scenario axis is only worth building where the outcome is genuinely uncertain AND the model is sensitive to it. Three items on Alphabet qualify, and they are deliberately flexed TOGETHER off one switch because they are not independent - the same AI-capex thesis that drives one drives the others.
B10: 1. DEPRECIATION LIFE SPLIT. Sheet '08 PPE and Depreciation' states it outright: the split of the 122,814 of assets-not-yet-in-service between short- and long-lived classes is the single most sensitive assumption in the model, it is NOT disclosed, and it should be scenarioed rather than point-estimated. On a 6-year life that tranche alone adds ~20,500/yr against a ~27,200 run rate - a ~75% increase before any further capex.
B11: 2. CAPEX PLATEAU TIMING. The Contents sheet names this as the open question: whether ~33x core earnings is defensible depends on what free cash flow normalises to once capex plateaus. Q2'26 was the first negative FCF quarter on record. Whether that reverses in FY2027 or FY2029 is the difference between a cash machine and a capital sink.
B12: 3. REVENUE GROWTH AND OPERATING MARGIN. The conventional axis, included because it is what the capex is being spent to buy. Note the deltas are asymmetric: best adds 3.0pp of growth, worst subtracts 4.0pp. Search share loss to AI assistants is a larger risk than AI upside is an opportunity, because the base is 224,532 of high-margin revenue that has no replacement.
B15: RESOLVED DRIVERS - these are what 17 Model actually reads
C16: FY2026E | D16: FY2027E | E16: FY2028E | F16: FY2029E | G16: FY2030E
B17: Segment revenue growth
B18: Google Search & other | C18: =CHOOSE($D$6,'15 Assumptions'!C14,'15 Assumptions'!C14+'15 Assumptions'!$C$22,'15 Assumptions'!C14+'15 Assumptions'!$C$23) -> 0.15 | D18: =CHOOSE($D$6,'15 Assumptions'!D14,'15 Assumptions'!D14+'15 Assumptions'!$C$22,'15 Assumptions'!D14+'15 Assumptions'!$C$23) -> 0.12 | E18: =CHOOSE($D$6,'15 Assumptions'!E14,'15 Assumptions'!E14+'15 Assumptions'!$C$22,'15 Assumptions'!E14+'15 Assumptions'!$C$23) -> 0.1 | F18: =CHOOSE($D$6,'15 Assumptions'!F14,'15 Assumptions'!F14+'15 Assumptions'!$C$22,'15 Assumptions'!F14+'15 Assumptions'!$C$23) -> 0.09 | G18: =CHOOSE($D$6,'15 Assumptions'!G14,'15 Assumptions'!G14+'15 Assumptions'!$C$22,'15 Assumptions'!G14+'15 Assumptions'!$C$23) -> 0.08
B19: YouTube ads | C19: =CHOOSE($D$6,'15 Assumptions'!C15,'15 Assumptions'!C15+'15 Assumptions'!$C$22,'15 Assumptions'!C15+'15 Assumptions'!$C$23) -> 0.125 | D19: =CHOOSE($D$6,'15 Assumptions'!D15,'15 Assumptions'!D15+'15 Assumptions'!$C$22,'15 Assumptions'!D15+'15 Assumptions'!$C$23) -> 0.115 | E19: =CHOOSE($D$6,'15 Assumptions'!E15,'15 Assumptions'!E15+'15 Assumptions'!$C$22,'15 Assumptions'!E15+'15 Assumptions'!$C$23) -> 0.105 | F19: =CHOOSE($D$6,'15 Assumptions'!F15,'15 Assumptions'!F15+'15 Assumptions'!$C$22,'15 Assumptions'!F15+'15 Assumptions'!$C$23) -> 0.1 | G19: =CHOOSE($D$6,'15 Assumptions'!G15,'15 Assumptions'!G15+'15 Assumptions'!$C$22,'15 Assumptions'!G15+'15 Assumptions'!$C$23) -> 0.095
B20: Google Network | C20: =CHOOSE($D$6,'15 Assumptions'!C16,'15 Assumptions'!C16+'15 Assumptions'!$C$22,'15 Assumptions'!C16+'15 Assumptions'!$C$23) -> -0.02 | D20: =CHOOSE($D$6,'15 Assumptions'!D16,'15 Assumptions'!D16+'15 Assumptions'!$C$22,'15 Assumptions'!D16+'15 Assumptions'!$C$23) -> -0.02 | E20: =CHOOSE($D$6,'15 Assumptions'!E16,'15 Assumptions'!E16+'15 Assumptions'!$C$22,'15 Assumptions'!E16+'15 Assumptions'!$C$23) -> -0.02 | F20: =CHOOSE($D$6,'15 Assumptions'!F16,'15 Assumptions'!F16+'15 Assumptions'!$C$22,'15 Assumptions'!F16+'15 Assumptions'!$C$23) -> -0.02 | G20: =CHOOSE($D$6,'15 Assumptions'!G16,'15 Assumptions'!G16+'15 Assumptions'!$C$22,'15 Assumptions'!G16+'15 Assumptions'!$C$23) -> -0.02
B21: Subscriptions, platforms & devices | C21: =CHOOSE($D$6,'15 Assumptions'!C17,'15 Assumptions'!C17+'15 Assumptions'!$C$22,'15 Assumptions'!C17+'15 Assumptions'!$C$23) -> 0.16 | D21: =CHOOSE($D$6,'15 Assumptions'!D17,'15 Assumptions'!D17+'15 Assumptions'!$C$22,'15 Assumptions'!D17+'15 Assumptions'!$C$23) -> 0.145 | E21: =CHOOSE($D$6,'15 Assumptions'!E17,'15 Assumptions'!E17+'15 Assumptions'!$C$22,'15 Assumptions'!E17+'15 Assumptions'!$C$23) -> 0.13 | F21: =CHOOSE($D$6,'15 Assumptions'!F17,'15 Assumptions'!F17+'15 Assumptions'!$C$22,'15 Assumptions'!F17+'15 Assumptions'!$C$23) -> 0.12 | G21: =CHOOSE($D$6,'15 Assumptions'!G17,'15 Assumptions'!G17+'15 Assumptions'!$C$22,'15 Assumptions'!G17+'15 Assumptions'!$C$23) -> 0.11
B22: Google Cloud (FY2027E on: output of row 24) | C22: =CHOOSE($D$6,'15 Assumptions'!C18,'15 Assumptions'!C18+'15 Assumptions'!$C$22,'15 Assumptions'!C18+'15 Assumptions'!$C$23) -> 0.7 | D22: ='DCF Base Model'!M14/'DCF Base Model'!L14-1 -> 0.60385278 | E22: ='DCF Base Model'!N14/'DCF Base Model'!M14-1 -> 0.4820625 | F22: ='DCF Base Model'!O14/'DCF Base Model'!N14-1 -> 0.33371628 | G22: ='DCF Base Model'!P14/'DCF Base Model'!O14-1 -> 0.24537439
B23: Other Bets | C23: =CHOOSE($D$6,'15 Assumptions'!C19,'15 Assumptions'!C19+'15 Assumptions'!$C$22,'15 Assumptions'!C19+'15 Assumptions'!$C$23) -> 0.05 | D23: =CHOOSE($D$6,'15 Assumptions'!D19,'15 Assumptions'!D19+'15 Assumptions'!$C$22,'15 Assumptions'!D19+'15 Assumptions'!$C$23) -> 0.05 | E23: =CHOOSE($D$6,'15 Assumptions'!E19,'15 Assumptions'!E19+'15 Assumptions'!$C$22,'15 Assumptions'!E19+'15 Assumptions'!$C$23) -> 0.05 | F23: =CHOOSE($D$6,'15 Assumptions'!F19,'15 Assumptions'!F19+'15 Assumptions'!$C$22,'15 Assumptions'!F19+'15 Assumptions'!$C$23) -> 0.05 | G23: =CHOOSE($D$6,'15 Assumptions'!G19,'15 Assumptions'!G19+'15 Assumptions'!$C$22,'15 Assumptions'!G19+'15 Assumptions'!$C$23) -> 0.05
B24: Cloud revenue per $ of prior-year capex | D24: =CHOOSE($D$6,'15 Assumptions'!D74,'15 Assumptions'!D75,'15 Assumptions'!D76) -> 0.3 | E24: =CHOOSE($D$6,'15 Assumptions'!E74,'15 Assumptions'!E75,'15 Assumptions'!E76) -> 0.3 | F24: =CHOOSE($D$6,'15 Assumptions'!F74,'15 Assumptions'!F75,'15 Assumptions'!F76) -> 0.3 | G24: =CHOOSE($D$6,'15 Assumptions'!G74,'15 Assumptions'!G75,'15 Assumptions'!G76) -> 0.3
B25: Operating margin before the depreciation ramp | C25: =IF('15 Assumptions'!$C$117=1,'DCF Base Model'!L123,CHOOSE($D$6,'15 Assumptions'!C27,'15 Assumptions'!C28,'15 Assumptions'!C29)) -> 0.353 | D25: =IF('15 Assumptions'!$C$117=1,'DCF Base Model'!M123,CHOOSE($D$6,'15 Assumptions'!D27,'15 Assumptions'!D28,'15 Assumptions'!D29)) -> 0.358 | E25: =IF('15 Assumptions'!$C$117=1,'DCF Base Model'!N123,CHOOSE($D$6,'15 Assumptions'!E27,'15 Assumptions'!E28,'15 Assumptions'!E29)) -> 0.363 | F25: =IF('15 Assumptions'!$C$117=1,'DCF Base Model'!O123,CHOOSE($D$6,'15 Assumptions'!F27,'15 Assumptions'!F28,'15 Assumptions'!F29)) -> 0.368 | G25: =IF('15 Assumptions'!$C$117=1,'DCF Base Model'!P123,CHOOSE($D$6,'15 Assumptions'!G27,'15 Assumptions'!G28,'15 Assumptions'!G29)) -> 0.373
B26: Capex intensity, % of revenue | C26: =CHOOSE($D$6,'15 Assumptions'!C32,'15 Assumptions'!C33,'15 Assumptions'!C34) -> 0.41 | D26: =CHOOSE($D$6,'15 Assumptions'!D32,'15 Assumptions'!D33,'15 Assumptions'!D34) -> 0.433 | E26: =CHOOSE($D$6,'15 Assumptions'!E32,'15 Assumptions'!E33,'15 Assumptions'!E34) -> 0.37 | F26: =CHOOSE($D$6,'15 Assumptions'!F32,'15 Assumptions'!F33,'15 Assumptions'!F34) -> 0.31 | G26: =CHOOSE($D$6,'15 Assumptions'!G32,'15 Assumptions'!G33,'15 Assumptions'!G34) -> 0.25
B27: Return on new capital after FY2030E | C27: =CHOOSE($D$6,'15 Assumptions'!$C$80,'15 Assumptions'!$C$81,'15 Assumptions'!$C$82) -> 0.15
B28: Short-lived share of assets not yet in service | C28: =CHOOSE($D$6,'15 Assumptions'!$C$37,'15 Assumptions'!$C$38,'15 Assumptions'!$C$39) -> 0.6
B29: Blended life of that balance (years) | C29: =1/(C28/'15 Assumptions'!$C$40+(1-C28)/'15 Assumptions'!$C$41) -> 8.3333333 | E29: Harmonic blend: a dollar on a 6-year life depreciates six times faster than one on a 20-year life, so the lives must be weighted on annual CHARGE, not on years.
B31: Annual charge once fully in service | C31: ='15 Assumptions'!$C$36/C29 -> 14737.68 | E31: The 122,814 spread over its blended life. This is the number that does not exist in the reported figures today.
B33: Terminal operating margin (used when 15 Assumptions C91 = 1) | C33: =CHOOSE($D$6,'15 Assumptions'!$C$106,'15 Assumptions'!$D$106,'15 Assumptions'!$E$106) -> 0.20881044
B35: Services margin change by FY2030E (mix path) | C35: =CHOOSE($D$6,'15 Assumptions'!$C$119,'15 Assumptions'!$D$119,'15 Assumptions'!$E$119) -> 0
B36: Cloud margin change by FY2030E (mix path) | C36: =CHOOSE($D$6,'15 Assumptions'!$C$120,'15 Assumptions'!$D$120,'15 Assumptions'!$E$120) -> 0
B37: Other Bets + Alphabet-level change by FY2030E (mix path) | C37: =CHOOSE($D$6,'15 Assumptions'!$C$121,'15 Assumptions'!$D$121,'15 Assumptions'!$E$121) -> 0

Sheet DCF Best Drivers
B2: DCF BEST DRIVERS — HIDDEN HELPER
B3: Change D6 only. Everything below, and every forecast column on 17 Model, follows it.
B6: SCENARIO SWITCH (1 = Base, 2 = Best, 3 = Worst) | D6: 2 | F6: =CHOOSE($D$6,"BASE CASE","BEST CASE","WORST CASE") -> BEST CASE
B8: Why these three drivers and not others
B9: A scenario axis is only worth building where the outcome is genuinely uncertain AND the model is sensitive to it. Three items on Alphabet qualify, and they are deliberately flexed TOGETHER off one switch because they are not independent - the same AI-capex thesis that drives one drives the others.
B10: 1. DEPRECIATION LIFE SPLIT. Sheet '08 PPE and Depreciation' states it outright: the split of the 122,814 of assets-not-yet-in-service between short- and long-lived classes is the single most sensitive assumption in the model, it is NOT disclosed, and it should be scenarioed rather than point-estimated. On a 6-year life that tranche alone adds ~20,500/yr against a ~27,200 run rate - a ~75% increase before any further capex.
B11: 2. CAPEX PLATEAU TIMING. The Contents sheet names this as the open question: whether ~33x core earnings is defensible depends on what free cash flow normalises to once capex plateaus. Q2'26 was the first negative FCF quarter on record. Whether that reverses in FY2027 or FY2029 is the difference between a cash machine and a capital sink.
B12: 3. REVENUE GROWTH AND OPERATING MARGIN. The conventional axis, included because it is what the capex is being spent to buy. Note the deltas are asymmetric: best adds 3.0pp of growth, worst subtracts 4.0pp. Search share loss to AI assistants is a larger risk than AI upside is an opportunity, because the base is 224,532 of high-margin revenue that has no replacement.
B15: RESOLVED DRIVERS - these are what 17 Model actually reads
C16: FY2026E | D16: FY2027E | E16: FY2028E | F16: FY2029E | G16: FY2030E
B17: Segment revenue growth
B18: Google Search & other | C18: =CHOOSE($D$6,'15 Assumptions'!C14,'15 Assumptions'!C14+'15 Assumptions'!$C$22,'15 Assumptions'!C14+'15 Assumptions'!$C$23) -> 0.18 | D18: =CHOOSE($D$6,'15 Assumptions'!D14,'15 Assumptions'!D14+'15 Assumptions'!$C$22,'15 Assumptions'!D14+'15 Assumptions'!$C$23) -> 0.15 | E18: =CHOOSE($D$6,'15 Assumptions'!E14,'15 Assumptions'!E14+'15 Assumptions'!$C$22,'15 Assumptions'!E14+'15 Assumptions'!$C$23) -> 0.13 | F18: =CHOOSE($D$6,'15 Assumptions'!F14,'15 Assumptions'!F14+'15 Assumptions'!$C$22,'15 Assumptions'!F14+'15 Assumptions'!$C$23) -> 0.12 | G18: =CHOOSE($D$6,'15 Assumptions'!G14,'15 Assumptions'!G14+'15 Assumptions'!$C$22,'15 Assumptions'!G14+'15 Assumptions'!$C$23) -> 0.11
B19: YouTube ads | C19: =CHOOSE($D$6,'15 Assumptions'!C15,'15 Assumptions'!C15+'15 Assumptions'!$C$22,'15 Assumptions'!C15+'15 Assumptions'!$C$23) -> 0.155 | D19: =CHOOSE($D$6,'15 Assumptions'!D15,'15 Assumptions'!D15+'15 Assumptions'!$C$22,'15 Assumptions'!D15+'15 Assumptions'!$C$23) -> 0.145 | E19: =CHOOSE($D$6,'15 Assumptions'!E15,'15 Assumptions'!E15+'15 Assumptions'!$C$22,'15 Assumptions'!E15+'15 Assumptions'!$C$23) -> 0.135 | F19: =CHOOSE($D$6,'15 Assumptions'!F15,'15 Assumptions'!F15+'15 Assumptions'!$C$22,'15 Assumptions'!F15+'15 Assumptions'!$C$23) -> 0.13 | G19: =CHOOSE($D$6,'15 Assumptions'!G15,'15 Assumptions'!G15+'15 Assumptions'!$C$22,'15 Assumptions'!G15+'15 Assumptions'!$C$23) -> 0.125
B20: Google Network | C20: =CHOOSE($D$6,'15 Assumptions'!C16,'15 Assumptions'!C16+'15 Assumptions'!$C$22,'15 Assumptions'!C16+'15 Assumptions'!$C$23) -> 0.01 | D20: =CHOOSE($D$6,'15 Assumptions'!D16,'15 Assumptions'!D16+'15 Assumptions'!$C$22,'15 Assumptions'!D16+'15 Assumptions'!$C$23) -> 0.01 | E20: =CHOOSE($D$6,'15 Assumptions'!E16,'15 Assumptions'!E16+'15 Assumptions'!$C$22,'15 Assumptions'!E16+'15 Assumptions'!$C$23) -> 0.01 | F20: =CHOOSE($D$6,'15 Assumptions'!F16,'15 Assumptions'!F16+'15 Assumptions'!$C$22,'15 Assumptions'!F16+'15 Assumptions'!$C$23) -> 0.01 | G20: =CHOOSE($D$6,'15 Assumptions'!G16,'15 Assumptions'!G16+'15 Assumptions'!$C$22,'15 Assumptions'!G16+'15 Assumptions'!$C$23) -> 0.01
B21: Subscriptions, platforms & devices | C21: =CHOOSE($D$6,'15 Assumptions'!C17,'15 Assumptions'!C17+'15 Assumptions'!$C$22,'15 Assumptions'!C17+'15 Assumptions'!$C$23) -> 0.19 | D21: =CHOOSE($D$6,'15 Assumptions'!D17,'15 Assumptions'!D17+'15 Assumptions'!$C$22,'15 Assumptions'!D17+'15 Assumptions'!$C$23) -> 0.175 | E21: =CHOOSE($D$6,'15 Assumptions'!E17,'15 Assumptions'!E17+'15 Assumptions'!$C$22,'15 Assumptions'!E17+'15 Assumptions'!$C$23) -> 0.16 | F21: =CHOOSE($D$6,'15 Assumptions'!F17,'15 Assumptions'!F17+'15 Assumptions'!$C$22,'15 Assumptions'!F17+'15 Assumptions'!$C$23) -> 0.15 | G21: =CHOOSE($D$6,'15 Assumptions'!G17,'15 Assumptions'!G17+'15 Assumptions'!$C$22,'15 Assumptions'!G17+'15 Assumptions'!$C$23) -> 0.14
B22: Google Cloud (FY2027E on: output of row 24) | C22: =CHOOSE($D$6,'15 Assumptions'!C18,'15 Assumptions'!C18+'15 Assumptions'!$C$22,'15 Assumptions'!C18+'15 Assumptions'!$C$23) -> 0.73 | D22: ='DCF Best Model'!M14/'DCF Best Model'!L14-1 -> 0.65251178 | E22: ='DCF Best Model'!N14/'DCF Best Model'!M14-1 -> 0.49400065 | F22: ='DCF Best Model'!O14/'DCF Best Model'!N14-1 -> 0.3471217 | G22: ='DCF Best Model'!P14/'DCF Best Model'!O14-1 -> 0.25315673
B23: Other Bets | C23: =CHOOSE($D$6,'15 Assumptions'!C19,'15 Assumptions'!C19+'15 Assumptions'!$C$22,'15 Assumptions'!C19+'15 Assumptions'!$C$23) -> 0.08 | D23: =CHOOSE($D$6,'15 Assumptions'!D19,'15 Assumptions'!D19+'15 Assumptions'!$C$22,'15 Assumptions'!D19+'15 Assumptions'!$C$23) -> 0.08 | E23: =CHOOSE($D$6,'15 Assumptions'!E19,'15 Assumptions'!E19+'15 Assumptions'!$C$22,'15 Assumptions'!E19+'15 Assumptions'!$C$23) -> 0.08 | F23: =CHOOSE($D$6,'15 Assumptions'!F19,'15 Assumptions'!F19+'15 Assumptions'!$C$22,'15 Assumptions'!F19+'15 Assumptions'!$C$23) -> 0.08 | G23: =CHOOSE($D$6,'15 Assumptions'!G19,'15 Assumptions'!G19+'15 Assumptions'!$C$22,'15 Assumptions'!G19+'15 Assumptions'!$C$23) -> 0.08
B24: Cloud revenue per $ of prior-year capex | D24: =CHOOSE($D$6,'15 Assumptions'!D74,'15 Assumptions'!D75,'15 Assumptions'!D76) -> 0.33 | E24: =CHOOSE($D$6,'15 Assumptions'!E74,'15 Assumptions'!E75,'15 Assumptions'!E76) -> 0.34 | F24: =CHOOSE($D$6,'15 Assumptions'!F74,'15 Assumptions'!F75,'15 Assumptions'!F76) -> 0.355 | G24: =CHOOSE($D$6,'15 Assumptions'!G74,'15 Assumptions'!G75,'15 Assumptions'!G76) -> 0.374
B25: Operating margin before the depreciation ramp | C25: =IF('15 Assumptions'!$C$117=1,'DCF Best Model'!L123,CHOOSE($D$6,'15 Assumptions'!C27,'15 Assumptions'!C28,'15 Assumptions'!C29)) -> 0.358 | D25: =IF('15 Assumptions'!$C$117=1,'DCF Best Model'!M123,CHOOSE($D$6,'15 Assumptions'!D27,'15 Assumptions'!D28,'15 Assumptions'!D29)) -> 0.368 | E25: =IF('15 Assumptions'!$C$117=1,'DCF Best Model'!N123,CHOOSE($D$6,'15 Assumptions'!E27,'15 Assumptions'!E28,'15 Assumptions'!E29)) -> 0.378 | F25: =IF('15 Assumptions'!$C$117=1,'DCF Best Model'!O123,CHOOSE($D$6,'15 Assumptions'!F27,'15 Assumptions'!F28,'15 Assumptions'!F29)) -> 0.388 | G25: =IF('15 Assumptions'!$C$117=1,'DCF Best Model'!P123,CHOOSE($D$6,'15 Assumptions'!G27,'15 Assumptions'!G28,'15 Assumptions'!G29)) -> 0.398
B26: Capex intensity, % of revenue | C26: =CHOOSE($D$6,'15 Assumptions'!C32,'15 Assumptions'!C33,'15 Assumptions'!C34) -> 0.4 | D26: =CHOOSE($D$6,'15 Assumptions'!D32,'15 Assumptions'!D33,'15 Assumptions'!D34) -> 0.39 | E26: =CHOOSE($D$6,'15 Assumptions'!E32,'15 Assumptions'!E33,'15 Assumptions'!E34) -> 0.32 | F26: =CHOOSE($D$6,'15 Assumptions'!F32,'15 Assumptions'!F33,'15 Assumptions'!F34) -> 0.25 | G26: =CHOOSE($D$6,'15 Assumptions'!G32,'15 Assumptions'!G33,'15 Assumptions'!G34) -> 0.2
B27: Return on new capital after FY2030E | C27: =CHOOSE($D$6,'15 Assumptions'!$C$80,'15 Assumptions'!$C$81,'15 Assumptions'!$C$82) -> 0.25
B28: Short-lived share of assets not yet in service | C28: =CHOOSE($D$6,'15 Assumptions'!$C$37,'15 Assumptions'!$C$38,'15 Assumptions'!$C$39) -> 0.45
B29: Blended life of that balance (years) | C29: =1/(C28/'15 Assumptions'!$C$40+(1-C28)/'15 Assumptions'!$C$41) -> 9.7560976 | E29: Harmonic blend: a dollar on a 6-year life depreciates six times faster than one on a 20-year life, so the lives must be weighted on annual CHARGE, not on years.
B31: Annual charge once fully in service | C31: ='15 Assumptions'!$C$36/C29 -> 12588.435 | E31: The 122,814 spread over its blended life. This is the number that does not exist in the reported figures today.
B33: Terminal operating margin (used when 15 Assumptions C91 = 1) | C33: =CHOOSE($D$6,'15 Assumptions'!$C$106,'15 Assumptions'!$D$106,'15 Assumptions'!$E$106) -> 0.2928118
B35: Services margin change by FY2030E (mix path) | C35: =CHOOSE($D$6,'15 Assumptions'!$C$119,'15 Assumptions'!$D$119,'15 Assumptions'!$E$119) -> 0.02
B36: Cloud margin change by FY2030E (mix path) | C36: =CHOOSE($D$6,'15 Assumptions'!$C$120,'15 Assumptions'!$D$120,'15 Assumptions'!$E$120) -> 0.05
B37: Other Bets + Alphabet-level change by FY2030E (mix path) | C37: =CHOOSE($D$6,'15 Assumptions'!$C$121,'15 Assumptions'!$D$121,'15 Assumptions'!$E$121) -> 0

Sheet DCF Worst Drivers
B2: DCF WORST DRIVERS — HIDDEN HELPER
B3: Change D6 only. Everything below, and every forecast column on 17 Model, follows it.
B6: SCENARIO SWITCH (1 = Base, 2 = Best, 3 = Worst) | D6: 3 | F6: =CHOOSE($D$6,"BASE CASE","BEST CASE","WORST CASE") -> WORST CASE
B8: Why these three drivers and not others
B9: A scenario axis is only worth building where the outcome is genuinely uncertain AND the model is sensitive to it. Three items on Alphabet qualify, and they are deliberately flexed TOGETHER off one switch because they are not independent - the same AI-capex thesis that drives one drives the others.
B10: 1. DEPRECIATION LIFE SPLIT. Sheet '08 PPE and Depreciation' states it outright: the split of the 122,814 of assets-not-yet-in-service between short- and long-lived classes is the single most sensitive assumption in the model, it is NOT disclosed, and it should be scenarioed rather than point-estimated. On a 6-year life that tranche alone adds ~20,500/yr against a ~27,200 run rate - a ~75% increase before any further capex.
B11: 2. CAPEX PLATEAU TIMING. The Contents sheet names this as the open question: whether ~33x core earnings is defensible depends on what free cash flow normalises to once capex plateaus. Q2'26 was the first negative FCF quarter on record. Whether that reverses in FY2027 or FY2029 is the difference between a cash machine and a capital sink.
B12: 3. REVENUE GROWTH AND OPERATING MARGIN. The conventional axis, included because it is what the capex is being spent to buy. Note the deltas are asymmetric: best adds 3.0pp of growth, worst subtracts 4.0pp. Search share loss to AI assistants is a larger risk than AI upside is an opportunity, because the base is 224,532 of high-margin revenue that has no replacement.
B15: RESOLVED DRIVERS - these are what 17 Model actually reads
C16: FY2026E | D16: FY2027E | E16: FY2028E | F16: FY2029E | G16: FY2030E
B17: Segment revenue growth
B18: Google Search & other | C18: =CHOOSE($D$6,'15 Assumptions'!C14,'15 Assumptions'!C14+'15 Assumptions'!$C$22,'15 Assumptions'!C14+'15 Assumptions'!$C$23) -> 0.11 | D18: =CHOOSE($D$6,'15 Assumptions'!D14,'15 Assumptions'!D14+'15 Assumptions'!$C$22,'15 Assumptions'!D14+'15 Assumptions'!$C$23) -> 0.08 | E18: =CHOOSE($D$6,'15 Assumptions'!E14,'15 Assumptions'!E14+'15 Assumptions'!$C$22,'15 Assumptions'!E14+'15 Assumptions'!$C$23) -> 0.06 | F18: =CHOOSE($D$6,'15 Assumptions'!F14,'15 Assumptions'!F14+'15 Assumptions'!$C$22,'15 Assumptions'!F14+'15 Assumptions'!$C$23) -> 0.05 | G18: =CHOOSE($D$6,'15 Assumptions'!G14,'15 Assumptions'!G14+'15 Assumptions'!$C$22,'15 Assumptions'!G14+'15 Assumptions'!$C$23) -> 0.04
B19: YouTube ads | C19: =CHOOSE($D$6,'15 Assumptions'!C15,'15 Assumptions'!C15+'15 Assumptions'!$C$22,'15 Assumptions'!C15+'15 Assumptions'!$C$23) -> 0.085 | D19: =CHOOSE($D$6,'15 Assumptions'!D15,'15 Assumptions'!D15+'15 Assumptions'!$C$22,'15 Assumptions'!D15+'15 Assumptions'!$C$23) -> 0.075 | E19: =CHOOSE($D$6,'15 Assumptions'!E15,'15 Assumptions'!E15+'15 Assumptions'!$C$22,'15 Assumptions'!E15+'15 Assumptions'!$C$23) -> 0.065 | F19: =CHOOSE($D$6,'15 Assumptions'!F15,'15 Assumptions'!F15+'15 Assumptions'!$C$22,'15 Assumptions'!F15+'15 Assumptions'!$C$23) -> 0.06 | G19: =CHOOSE($D$6,'15 Assumptions'!G15,'15 Assumptions'!G15+'15 Assumptions'!$C$22,'15 Assumptions'!G15+'15 Assumptions'!$C$23) -> 0.055
B20: Google Network | C20: =CHOOSE($D$6,'15 Assumptions'!C16,'15 Assumptions'!C16+'15 Assumptions'!$C$22,'15 Assumptions'!C16+'15 Assumptions'!$C$23) -> -0.06 | D20: =CHOOSE($D$6,'15 Assumptions'!D16,'15 Assumptions'!D16+'15 Assumptions'!$C$22,'15 Assumptions'!D16+'15 Assumptions'!$C$23) -> -0.06 | E20: =CHOOSE($D$6,'15 Assumptions'!E16,'15 Assumptions'!E16+'15 Assumptions'!$C$22,'15 Assumptions'!E16+'15 Assumptions'!$C$23) -> -0.06 | F20: =CHOOSE($D$6,'15 Assumptions'!F16,'15 Assumptions'!F16+'15 Assumptions'!$C$22,'15 Assumptions'!F16+'15 Assumptions'!$C$23) -> -0.06 | G20: =CHOOSE($D$6,'15 Assumptions'!G16,'15 Assumptions'!G16+'15 Assumptions'!$C$22,'15 Assumptions'!G16+'15 Assumptions'!$C$23) -> -0.06
B21: Subscriptions, platforms & devices | C21: =CHOOSE($D$6,'15 Assumptions'!C17,'15 Assumptions'!C17+'15 Assumptions'!$C$22,'15 Assumptions'!C17+'15 Assumptions'!$C$23) -> 0.12 | D21: =CHOOSE($D$6,'15 Assumptions'!D17,'15 Assumptions'!D17+'15 Assumptions'!$C$22,'15 Assumptions'!D17+'15 Assumptions'!$C$23) -> 0.105 | E21: =CHOOSE($D$6,'15 Assumptions'!E17,'15 Assumptions'!E17+'15 Assumptions'!$C$22,'15 Assumptions'!E17+'15 Assumptions'!$C$23) -> 0.09 | F21: =CHOOSE($D$6,'15 Assumptions'!F17,'15 Assumptions'!F17+'15 Assumptions'!$C$22,'15 Assumptions'!F17+'15 Assumptions'!$C$23) -> 0.08 | G21: =CHOOSE($D$6,'15 Assumptions'!G17,'15 Assumptions'!G17+'15 Assumptions'!$C$22,'15 Assumptions'!G17+'15 Assumptions'!$C$23) -> 0.07
B22: Google Cloud (FY2027E on: output of row 24) | C22: =CHOOSE($D$6,'15 Assumptions'!C18,'15 Assumptions'!C18+'15 Assumptions'!$C$22,'15 Assumptions'!C18+'15 Assumptions'!$C$23) -> 0.66 | D22: ='DCF Worst Model'!M14/'DCF Worst Model'!L14-1 -> 0.41047266 | E22: ='DCF Worst Model'!N14/'DCF Worst Model'!M14-1 -> 0.33316149 | F22: ='DCF Worst Model'!O14/'DCF Worst Model'!N14-1 -> 0.24626785 | G22: ='DCF Worst Model'!P14/'DCF Worst Model'!O14-1 -> 0.19046569
B23: Other Bets | C23: =CHOOSE($D$6,'15 Assumptions'!C19,'15 Assumptions'!C19+'15 Assumptions'!$C$22,'15 Assumptions'!C19+'15 Assumptions'!$C$23) -> 0.01 | D23: =CHOOSE($D$6,'15 Assumptions'!D19,'15 Assumptions'!D19+'15 Assumptions'!$C$22,'15 Assumptions'!D19+'15 Assumptions'!$C$23) -> 0.01 | E23: =CHOOSE($D$6,'15 Assumptions'!E19,'15 Assumptions'!E19+'15 Assumptions'!$C$22,'15 Assumptions'!E19+'15 Assumptions'!$C$23) -> 0.01 | F23: =CHOOSE($D$6,'15 Assumptions'!F19,'15 Assumptions'!F19+'15 Assumptions'!$C$22,'15 Assumptions'!F19+'15 Assumptions'!$C$23) -> 0.01 | G23: =CHOOSE($D$6,'15 Assumptions'!G19,'15 Assumptions'!G19+'15 Assumptions'!$C$22,'15 Assumptions'!G19+'15 Assumptions'!$C$23) -> 0.01
B24: Cloud revenue per $ of prior-year capex | D24: =CHOOSE($D$6,'15 Assumptions'!D74,'15 Assumptions'!D75,'15 Assumptions'!D76) -> 0.201 | E24: =CHOOSE($D$6,'15 Assumptions'!E74,'15 Assumptions'!E75,'15 Assumptions'!E76) -> 0.184 | F24: =CHOOSE($D$6,'15 Assumptions'!F74,'15 Assumptions'!F75,'15 Assumptions'!F76) -> 0.185 | G24: =CHOOSE($D$6,'15 Assumptions'!G74,'15 Assumptions'!G75,'15 Assumptions'!G76) -> 0.195
B25: Operating margin before the depreciation ramp | C25: =IF('15 Assumptions'!$C$117=1,'DCF Worst Model'!L123,CHOOSE($D$6,'15 Assumptions'!C27,'15 Assumptions'!C28,'15 Assumptions'!C29)) -> 0.345 | D25: =IF('15 Assumptions'!$C$117=1,'DCF Worst Model'!M123,CHOOSE($D$6,'15 Assumptions'!D27,'15 Assumptions'!D28,'15 Assumptions'!D29)) -> 0.34 | E25: =IF('15 Assumptions'!$C$117=1,'DCF Worst Model'!N123,CHOOSE($D$6,'15 Assumptions'!E27,'15 Assumptions'!E28,'15 Assumptions'!E29)) -> 0.335 | F25: =IF('15 Assumptions'!$C$117=1,'DCF Worst Model'!O123,CHOOSE($D$6,'15 Assumptions'!F27,'15 Assumptions'!F28,'15 Assumptions'!F29)) -> 0.33 | G25: =IF('15 Assumptions'!$C$117=1,'DCF Worst Model'!P123,CHOOSE($D$6,'15 Assumptions'!G27,'15 Assumptions'!G28,'15 Assumptions'!G29)) -> 0.325
B26: Capex intensity, % of revenue | C26: =CHOOSE($D$6,'15 Assumptions'!C32,'15 Assumptions'!C33,'15 Assumptions'!C34) -> 0.42 | D26: =CHOOSE($D$6,'15 Assumptions'!D32,'15 Assumptions'!D33,'15 Assumptions'!D34) -> 0.46 | E26: =CHOOSE($D$6,'15 Assumptions'!E32,'15 Assumptions'!E33,'15 Assumptions'!E34) -> 0.4 | F26: =CHOOSE($D$6,'15 Assumptions'!F32,'15 Assumptions'!F33,'15 Assumptions'!F34) -> 0.33 | G26: =CHOOSE($D$6,'15 Assumptions'!G32,'15 Assumptions'!G33,'15 Assumptions'!G34) -> 0.27
B27: Return on new capital after FY2030E | C27: =CHOOSE($D$6,'15 Assumptions'!$C$80,'15 Assumptions'!$C$81,'15 Assumptions'!$C$82) -> 0.1
B28: Short-lived share of assets not yet in service | C28: =CHOOSE($D$6,'15 Assumptions'!$C$37,'15 Assumptions'!$C$38,'15 Assumptions'!$C$39) -> 0.8
B29: Blended life of that balance (years) | C29: =1/(C28/'15 Assumptions'!$C$40+(1-C28)/'15 Assumptions'!$C$41) -> 6.9767442 | E29: Harmonic blend: a dollar on a 6-year life depreciates six times faster than one on a 20-year life, so the lives must be weighted on annual CHARGE, not on years.
B31: Annual charge once fully in service | C31: ='15 Assumptions'!$C$36/C29 -> 17603.34 | E31: The 122,814 spread over its blended life. This is the number that does not exist in the reported figures today.
B33: Terminal operating margin (used when 15 Assumptions C91 = 1) | C33: =CHOOSE($D$6,'15 Assumptions'!$C$106,'15 Assumptions'!$D$106,'15 Assumptions'!$E$106) -> 0.13421184
B35: Services margin change by FY2030E (mix path) | C35: =CHOOSE($D$6,'15 Assumptions'!$C$119,'15 Assumptions'!$D$119,'15 Assumptions'!$E$119) -> -0.02
B36: Cloud margin change by FY2030E (mix path) | C36: =CHOOSE($D$6,'15 Assumptions'!$C$120,'15 Assumptions'!$D$120,'15 Assumptions'!$E$120) -> -0.05
B37: Other Bets + Alphabet-level change by FY2030E (mix path) | C37: =CHOOSE($D$6,'15 Assumptions'!$C$121,'15 Assumptions'!$D$121,'15 Assumptions'!$E$121) -> 0

Sheet 17 Model
O1: ="CURRENTLY RUNNING: "&'16 Scenarios'!F6 -> CURRENTLY RUNNING: BASE CASE
B2: 17 — OPERATING MODEL
B3: $ millions except per-share. H:J historical, linked live from '01 Income Statement', '03 Segments', '06 Core EPS Bridge', '09 Cash Flow' and '11 Valuation'. K = TTM Jun'26. L:P forecast.
L6: Projected
H7: FY2023 | I7: FY2024 | J7: FY2025 | K7: TTM Jun'26 | L7: FY2026E | M7: FY2027E | N7: FY2028E | O7: FY2029E | P7: FY2030E
B9: REVENUE SCHEDULE
C10: Google Search & other | H10: ='03 Segments'!C7 -> 175033 | I10: ='03 Segments'!D7 -> 198084 | J10: ='03 Segments'!E7 -> 224532 | K10: ='03 Segments'!E7+'03 Segments'!G7+'03 Segments'!I7-'03 Segments'!F7-'03 Segments'!H7 -> 243310 | L10: =J10*(1+'16 Scenarios'!C18) -> 258211.8 | M10: =L10*(1+'16 Scenarios'!D18) -> 289197.22 | N10: =M10*(1+'16 Scenarios'!E18) -> 318116.94 | O10: =N10*(1+'16 Scenarios'!F18) -> 346747.46 | P10: =O10*(1+'16 Scenarios'!G18) -> 374487.26
C11: YouTube ads | H11: ='03 Segments'!C8 -> 31510 | I11: ='03 Segments'!D8 -> 36147 | J11: ='03 Segments'!E8 -> 40367 | K11: ='03 Segments'!E8+'03 Segments'!G8+'03 Segments'!I8-'03 Segments'!F8-'03 Segments'!H8 -> 42582 | L11: =J11*(1+'16 Scenarios'!C19) -> 45412.875 | M11: =L11*(1+'16 Scenarios'!D19) -> 50635.356 | N11: =M11*(1+'16 Scenarios'!E19) -> 55952.068 | O11: =N11*(1+'16 Scenarios'!F19) -> 61547.275 | P11: =O11*(1+'16 Scenarios'!G19) -> 67394.266
C12: Google Network | H12: ='03 Segments'!C9 -> 31312 | I12: ='03 Segments'!D9 -> 30359 | J12: ='03 Segments'!E9 -> 29792 | K12: ='03 Segments'!E9+'03 Segments'!G9+'03 Segments'!I9-'03 Segments'!F9-'03 Segments'!H9 -> 29456 | L12: =J12*(1+'16 Scenarios'!C20) -> 29196.16 | M12: =L12*(1+'16 Scenarios'!D20) -> 28612.237 | N12: =M12*(1+'16 Scenarios'!E20) -> 28039.992 | O12: =N12*(1+'16 Scenarios'!F20) -> 27479.192 | P12: =O12*(1+'16 Scenarios'!G20) -> 26929.608
C13: Subscriptions, platforms & devices | H13: ='03 Segments'!C11 -> 34688 | I13: ='03 Segments'!D11 -> 40340 | J13: ='03 Segments'!E11 -> 48030 | K13: ='03 Segments'!E11+'03 Segments'!G11+'03 Segments'!I11-'03 Segments'!F11-'03 Segments'!H11 -> 51743 | L13: =J13*(1+'16 Scenarios'!C21) -> 55714.8 | M13: =L13*(1+'16 Scenarios'!D21) -> 63793.446 | N13: =M13*(1+'16 Scenarios'!E21) -> 72086.594 | O13: =N13*(1+'16 Scenarios'!F21) -> 80736.985 | P13: =O13*(1+'16 Scenarios'!G21) -> 89618.054
C14: Google Cloud | H14: ='03 Segments'!C13 -> 33088 | I14: ='03 Segments'!D13 -> 43229 | J14: ='03 Segments'!E13 -> 58705 | K14: ='03 Segments'!E13+'03 Segments'!G13+'03 Segments'!I13-'03 Segments'!F13-'03 Segments'!H13 -> 77617 | L14: =J14*(1+'16 Scenarios'!C22) -> 99798.5 | M14: =L14-L75*'16 Scenarios'!D24 -> 160062.1 | N14: =M14-M75*'16 Scenarios'!E24 -> 237222.04 | O14: =N14-N75*'16 Scenarios'!F24 -> 316386.9 | P14: =O14-O75*'16 Scenarios'!G24 -> 394020.14
